Workbook

Sheet Inputs
A1: Entity 1
B2: Subscriber Management Fee | C2: =SUM(C3:C6) -> 5.27 | D2: Retail Pricing | F2: Start Up Costs (per Brand) | K2: Year 1 Customer Equipment | Y2: Susidy | AB2: Additional Packaged Items
B3: Per service component 1 | C3: 3.37 | D3: Product 1 | E3: =(AD135+BB135)/AY135 -> 0.11296647 | F3: Item | G3: Quantity | H3: Cost Per | I3: Total Cost | K3: Make - Model | L3: Our Cost | M3: Add-Ins (net cost) | N3: Packaging & Shipping | O3: Decorator | P3: Imaging | Q3: Add-Ins (cust price) | R3: Retail Price | S3: Profit | T3: % Penetration | U3: Total Units | V3: Total Cost | W3: Total Rev | X3: Total Profit | Y3: % | AB3: Item | AC3: Cost | AD3: Price | AE3: Pro$F$it (LOSS)
B4: Per service component 2 | C4: 0.35 | D4: Product 2 | E4: =(AE135+BC135)/AZ135 -> 0.11183241 | F4: Component 1 | G4: 5000 | H4: =C16 -> 3.81 | I4: =G4*H4 -> 19050 | L4: 99 | N4: 9 | O4: 5 | P4: =0.85*4 -> 3.4 | R4: =SUM(N4:P4,L4,Q4) -> 116.4 | S4: =Q4+R4-SUM(L4:P4) -> 0 | U4: =T4*$D$39 -> 0 | V4: =U4*L4 -> 0 | W4: =U4*R4 -> 0 | X4: =W4-V4 -> 0 | Y4: =-S4/(SUM(L4,M4,N4,O4,P4)) -> 0
B5: Payment Type Cost | C5: 0.58 | D5: Product 3 | E5: =AF135/BA135 -> 0.1 | F5: Electrical Profile | G5: 1 | H5: 7500 | I5: =G5*H5 -> 7500 | L5: 150 | N5: 9 | O5: 5 | P5: =0.85*4 -> 3.4 | R5: =SUM(N5:P5,L5,Q5) -> 167.4 | S5: =Q5+R5-SUM(L5:P5) -> 0 | U5: =T5*$D$39 -> 0 | V5: =U5*L5 -> 0 | W5: =U5*R5 -> 0 | X5: =W5-V5 -> 0 | Y5: =-S5/(SUM(L5,M5,N5,O5,P5)) -> 0 | AB5: USB Flash Disk | AC5: 28 | AD5: 50 | AE5: =AD5-AC5 -> 22
B6: Customer Care | C6: 0.97 | D6: Product 4 | E6: 0 | F6: Graphical Profile | G6: 0 | H6: 2500 | I6: =G6*H6 -> 0 | L6: 105 | N6: 9 | O6: 5 | P6: =0.85*4 -> 3.4 | R6: =SUM(N6:P6,L6,Q6) -> 122.4 | S6: =Q6+R6-SUM(L6:P6) -> 0 | U6: =T6*$D$39 -> 0 | V6: =U6*L6 -> 0 | W6: =U6*R6 -> 0 | X6: =W6-V6 -> 0 | Y6: =-S6/(SUM(L6,M6,N6,O6,P6)) -> 0
B7: Operational Costs | D7: Various Figures | F7: service component 1 | G7: =G4 -> 5000 | H7: 3.37 | I7: =G7*H7 -> 16850 | L7: 155 | N7: 9 | O7: 5 | P7: =0.85*4 -> 3.4 | R7: =SUM(N7:P7,L7,Q7) -> 172.4 | S7: =Q7+R7-SUM(L7:P7) -> 0 | U7: =T7*$D$39 -> 0 | V7: =U7*L7 -> 0 | W7: =U7*R7 -> 0 | X7: =W7-V7 -> 0 | Y7: =-S7/(SUM(L7,M7,N7,O7,P7)) -> 0
B8: Product 1 | C8: 0.0641 | D8: Longevity (months) | E8: 12 | F8: service component 2 | G8: =G4 -> 5000 | H8: 0.35 | I8: =G8*H8 -> 1750 | L8: 105 | N8: 9 | O8: 5 | P8: =0.85*4 -> 3.4 | R8: =SUM(N8:P8,L8,Q8) -> 122.4 | S8: =Q8+R8-SUM(L8:P8) -> 0 | U8: =T8*$D$39 -> 0 | V8: =U8*L8 -> 0 | W8: =U8*R8 -> 0 | X8: =W8-V8 -> 0 | Y8: =-S8/(SUM(L8,M8,N8,O8,P8)) -> 0
B9: Product 2 | C9: 0.04 | D9: Customer Loss | E9: 0.05 | F9: 1 Month of flat fee | G9: 0 | H9: =C12 -> 1450 | I9: =G9*H9 -> 0 | L9: 39 | N9: 9 | O9: 5 | P9: =0.85*4 -> 3.4 | R9: =SUM(N9:P9,L9,Q9) -> 56.4 | S9: =Q9+R9-SUM(L9:P9) -> 0 | T9: 1 | U9: =T9*$D$39 -> 55869.18 | V9: =U9*L9 -> 2178898 | W9: =U9*R9 -> 3151021.8 | X9: =W9-V9 -> 972123.73 | Y9: =-S9/(SUM(L9,M9,N9,O9,P9)) -> 0
B10: Product 3 | C10: 2 | D10: Daily Service Charge | E10: =1/7 -> 0.14285714 | F10: Pre-purchased product 1 | G10: 0 | H10: =C8 -> 0.0641 | I10: =G10*H10 -> 0 | U10: =T10*$D$39 -> 0 | V10: =U10*L10 -> 0 | W10: =U10*R10 -> 0 | X10: =W10-V10 -> 0 | Y10: =-S10/(SUM(L10,M10,N10,O10,P10)) -> #DIV/0!
B11: Product 1 Commission | C11: 0.15 | D11: Annual Growth Rate (plus 100%) | E11: 1.5 | F11: customer equipment | G11: 0 | H11: =C19 -> 56.4 | I11: =G11*H11 -> 0 | L11: 109 | N11: 10 | O11: 10 | P11: 10 | R11: =SUM(N11:P11,L11,Q11) -> 139 | S11: =Q11+R11-SUM(L11:P11) -> 0 | T11: 0 | U11: =T11*$D$39 -> 0 | V11: =U11*L11 -> 0 | W11: =U11*R11 -> 0 | X11: =W11-V11 -> 0 | Y11: =-S11/(SUM(L11,M11,N11,O11,P11)) -> 0
B12: Monthly Flat Fee | C12: 1450 | F12: equipment branding (physical) | G12: 1 | H12: 1500 | I12: =G12*H12 -> 1500 | L12: 185 | N12: 9 | O12: 5 | P12: =0.85*4 -> 3.4 | R12: =SUM(N12:P12,L12,Q12) -> 202.4 | S12: =Q12+R12-SUM(L12:P12) -> 0 | U12: =T12*$D$39 -> 0 | V12: =U12*L12 -> 0 | W12: =U12*R12 -> 0 | X12: =W12-V12 -> 0 | Y12: =-S12/(SUM(L12,M12,N12,O12,P12)) -> 0
B13: Activation Costs | C13: =SUM(C14:C20) -> 79.63 | D13: Activation Revenue | E13: =SUM(E14:E17) -> 56.4 | F13: software licensing | G13: 0 | H13: 16000 | I13: =G13*H13 -> 0 | L13: 329 | N13: 9 | O13: 5 | P13: =0.85*4 -> 3.4 | R13: =SUM(N13:P13,L13,Q13) -> 346.4 | S13: =Q13+R13-SUM(L13:P13) -> 0 | U13: =T13*$D$39 -> 0 | V13: =U13*L13 -> 0 | W13: =U13*R13 -> 0 | X13: =W13-V13 -> 0 | Y13: =-S13/(SUM(L13,M13,N13,O13,P13)) -> 0
B14: Activation Cost 1 | C14: 0 | D14: Activation Fee | E14: 0 | F14: equipment branding (digital) | G14: 1 | H14: 3000 | I14: =G14*H14 -> 3000 | U14: =T14*$D$39 -> 0 | V14: =U14*L14 -> 0 | W14: =U14*R14 -> 0 | X14: =W14-V14 -> 0 | Y14: =-S14/(SUM(L14,M14,N14,O14,P14)) -> #DIV/0!
B15: Activation Cost 2 | C15: 3 | D15: Customer Equipment | E15: =V20 -> 56.4 | H15: Per-Brand Maximum Setup Cost | I15: =SUM(I4:I14) -> 49650 | U15: =T15*$D$39 -> 0 | V15: =U15*L15 -> 0 | W15: =U15*R15 -> 0 | X15: =W15-V15 -> 0 | Y15: =-S15/(SUM(L15,M15,N15,O15,P15)) -> #DIV/0!
B16: Component | C16: 3.81 | F16: StartUp Costs (One-Time) | U16: =T16*$D$39 -> 0 | V16: =U16*L16 -> 0 | W16: =U16*R16 -> 0 | X16: =W16-V16 -> 0 | Y16: =-S16/(SUM(L16,M16,N16,O16,P16)) -> #DIV/0!
B17: Dealer Commission | C17: 15 | F17: Provisionsing Setup | G17: 1 | H17: 60000 | I17: =G17*H17 -> 60000 | S17: =Q17+R17-SUM(L17:P17) -> 0 | U17: =T17*$D$39 -> 0 | V17: =U17*L17 -> 0 | W17: =U17*R17 -> 0 | X17: =W17-V17 -> 0 | Y17: =-S17/(SUM(L17,M17,N17,O17,P17)) -> #DIV/0!
B18: Payment Processing | C18: 1.42 | D18: Per-Month Cust. Profit | E18: =SUM(F23:F26) -> 18.401398 | F18: Data setup | G18: 1 | H18: 15000 | I18: =G18*H18 -> 15000 | U18: =T18*$D$39 -> 0 | V18: =U18*L18 -> 0 | W18: =U18*R18 -> 0 | X18: =W18-V18 -> 0 | Y18: =-S18/(SUM(L18,M18,N18,O18,P18)) -> #DIV/0!
B19: Customer Equipment | C19: =V20 -> 56.4 | D19: Activation Subsidy | E19: =C13-E13 -> 23.23 | F19: Data Transfer | G19: 1 | H19: 500 | I19: =G19*H19 -> 500 | R19: Totals | S19: =SUM(T4:T18) -> 1 | T19: =SUM(U4:U18) -> 55869.18 | U19: =SUM(V4:V18) -> 2178898 | V19: =SUM(W4:W18) -> 3151021.8 | W19: =SUM(X4:X18) -> 972123.73
D20: Months to Recover Subsidy | E20: =E19/E18 -> 1.2624041 | F20: Application Development | G20: 0.5 | H20: 90000 | I20: =G20*H20 -> 45000 | T20: Averages | U20: =ROUNDDOWN(U19/$D$39,2) -> 39 | V20: =ROUNDDOWN(V19/$D$39,2) -> 56.4 | W20: =ROUNDDOWN(W19/$D$39,2) -> 17.4 | AB20: Total | AC20: =SUM(AC5:AC19) -> 28 | AD20: =SUM(AD5:AD19) -> 50 | AE20: =SUM(AE5:AE19) -> 22
B21: Average Usage | H21: Total One Time Costs | I21: =SUM(I17:I20) -> 120500
C22: Quantity | D22: Revenue | E22: Cost | F22: Profit | K22: Product 3 conversion | L22: 1 | M22: Converted Product 3 | O22: Fully Loaded Costs
B23: Product 1 per user | C23: =ROUNDUP(G39/12/D39,0) -> 229 | D23: =(BB135+AD135)/D39 -> 26.235724 | E23: =C23*C8 -> 14.6789 | F23: =D23-E23 -> 11.556824 | K23: Product 3 conversion | L23: =ROUNDUP(L22/10,0) -> 1 | M23: =C10/1000000*10000 -> 0.02 | P23: Base | Q23: Commission | R23: Customer Management | S23: Flat Operating Fee | T23: Activation (divided by longevity) | U23: Per Unit Charge | V23: Fully Loaded Cost | W23: Retail | X23: Surplus (Deficit)
B24: Product 2 per user | C24: =ROUNDUP(I39/D39/12,0) -> 93 | D24: =(BC135+AE135)/D39 -> 10.547721 | E24: =C24*C9 -> 3.72 | F24: =D24-E24 -> 6.8277214 | G24: Monthly Fixed Revenue | H24: Per Unit Charge | K24: Product 3 billed rate | L24: =C10/L23 -> 2 | O24: Product 1 | P24: =C8 -> 0.0641 | Q24: =C11*E3 -> 0.01694497 | R24: =C2/SUM(C23:C25) -> 0.016355945 | S24: =C12/AY138 -> 7.9424176e-05 | T24: =(C13-E15-E14)/(SUM(C23:C25)*E8) -> 0.0060080424 | U24: =-H25 -> -0.0065979006 | V24: =SUM(P24:U24) -> 0.096890481 | W24: =E3 -> 0.11296647 | X24: =W24-V24 -> 0.016075988
B25: Product 3 per user | C25: =ROUNDDOWN(K39/D39/12,3) -> 0.207 | D25: =AF135/D39 -> 0.020993186 | E25: =C25*M23 -> 0.00414 | F25: =D25-E25 -> 0.016853186 | G25: Average per user | H25: =AI136/SUM(C23:C25) -> 0.0065979006 | I25: ARPU (from chart 1) | J25: Need to drop | O25: Product 2 | P25: =C9 -> 0.04 | R25: =R24 -> 0.016355945 | S25: =S24 -> 7.9424176e-05 | T25: =T24 -> 0.0060080424 | U25: =-H25 -> -0.0065979006 | V25: =SUM(P25:U25) -> 0.055845511 | W25: =E4 -> 0.11183241 | X25: =W25-V25 -> 0.055986899
B26: Product 4 per user | C26: =M39/12/D39 -> 0 | D26: =C26*E6 -> 0 | E26: - | F26: =D26 -> 0 | G26: =AC135/D39 -> 4.3740898 | I26: ='Entity 1 Outputs'!L53 -> 49.637343 | J26: ='Entity 1 Outputs'!D72 -> -3.362657 | O26: Product 3 | P26: =M23 -> 0.02 | R26: =R24 -> 0.016355945 | S26: =S25 -> 7.9424176e-05 | T26: =T25 -> 0.0060080424 | U26: =-H25 -> -0.0065979006 | V26: =SUM(P26:U26) -> 0.035845511 | W26: =E5 -> 0.1 | X26: =W26-V26 -> 0.064154489
B28: Brands | C28: Year 1 Estimates | F28: Monthly | G28: Annual - Aggregate | H28: Monthly | I28: Annual - Aggregate | J28: Monthly Average | K28: Annual - Aggregate | L28: Monthly | M28: Annual - Aggregate
B29: Name | C29: Target Audience | D29: Expected Customers | E29: Penetration Rate | F29: Average Product 1 Sales | G29: Total Product 1 Sales | H29: Average Product 2 Sales | I29: Total Product 2 Sales | J29: Product 3 Sales | K29: Total Product 3 Sales | L29: Average Product 4 | M29: Total Product 4
B30: Brand 1 | C30: 1500000 | D30: 15000 | E30: =D30/C30 -> 0.01 | F30: 229 | G30: =F30*$D30*12 -> 41220000 | H30: 180 | I30: =H30*$D30*12 -> 32400000 | J30: 0.5 | K30: =J30*$D30*12 -> 90000 | L30: 0 | M30: =L30*$D30*12 -> 0
B31: Brand 2 | C31: 328510 | D31: 10000 | E31: =D31/C31 -> 0.030440474 | F31: 229 | G31: =F31*$D31*12 -> 27480000 | H31: 60 | I31: =H31*$D31*12 -> 7200000 | J31: 0.1 | K31: =J31*$D31*12 -> 12000 | L31: 0 | M31: =L31*$D31*12 -> 0
B32: Brand 3 | C32: 895861 | D32: 5000 | E32: =D32/C32 -> 0.005581223 | F32: 229 | G32: =F32*$D32*12 -> 13740000 | H32: 60 | I32: =H32*$D32*12 -> 3600000 | J32: 0.1 | K32: =J32*$D32*12 -> 6000 | L32: 0 | M32: =L32*$D32*12 -> 0
B33: Brand 4 | C33: 1800000 | D33: 5000 | E33: =D33/C33 -> 0.0027777778 | F33: 229 | G33: =F33*$D33*12 -> 13740000 | H33: 60 | I33: =H33*$D33*12 -> 3600000 | J33: 0.1 | K33: =J33*$D33*12 -> 6000 | L33: 0 | M33: =L33*$D33*12 -> 0
B34: Brand 5 | C34: 1066085 | D34: 5000 | E34: =D34/C34 -> 0.0046900575 | F34: 229 | G34: =F34*$D34*12 -> 13740000 | H34: 60 | I34: =H34*$D34*12 -> 3600000 | J34: 0.1 | K34: =J34*$D34*12 -> 6000 | L34: 0 | M34: =L34*$D34*12 -> 0
B35: Brand 6 | C35: 11831495 | D35: 5000 | E35: =D35/C35 -> 0.00042260086 | F35: 229 | G35: =F35*$D35*12 -> 13740000 | H35: 60 | I35: =H35*$D35*12 -> 3600000 | J35: 0.1 | K35: =J35*$D35*12 -> 6000 | L35: 0 | M35: =L35*$D35*12 -> 0
B36: Brand 7 | C36: 86918 | D36: =$E$30*C36 -> 869.18 | E36: =D36/C36 -> 0.01 | F36: 229 | G36: =F36*$D36*12 -> 2388506.6 | H36: 60 | I36: =H36*$D36*12 -> 625809.6 | J36: 0.1 | K36: =J36*$D36*12 -> 1043.016 | L36: 0 | M36: =L36*$D36*12 -> 0
B37: Brand 8 | C37: 18951793 | D37: 5000 | E37: =D37/C37 -> 0.00026382728 | F37: 229 | G37: =F37*$D37*12 -> 13740000 | H37: 60 | I37: =H37*$D37*12 -> 3600000 | J37: 0.1 | K37: =J37*$D37*12 -> 6000 | L37: 0 | M37: =L37*$D37*12 -> 0
B38: Brand 9 | C38: 63786438 | D38: 5000 | E38: =D38/C38 -> 7.8386569e-05 | F38: 229 | G38: =F38*$D38*12 -> 13740000 | H38: 60 | I38: =H38*$D38*12 -> 3600000 | J38: 0.1 | K38: =J38*$D38*12 -> 6000 | L38: 0 | M38: =L38*$D38*12 -> 0
B39: Totals | C39: =SUM(C30:C38) -> 100247100 | D39: =SUM(D30:D38) -> 55869.18 | E39: =D39/C39 -> 0.00055731468 | F39: =G39/$D$39/12 -> 229 | G39: =SUM(G30:G38) -> 1.5352851e+08 | H39: =I39/$D$39/12 -> 92.218121 | I39: =SUM(I30:I38) -> 61825810 | J39: =K39/$D$39/12 -> 0.20739374 | K39: =SUM(K30:K38)*L23 -> 139043.02 | L39: =M39/$D$39/12 -> 0 | M39: =SUM(M30:M38) -> 0
C41: Program Name | D41: Monthly Charge | E41: Product 1 | F41: Product 2 | G41: Product 1 Surplus | H41: Product 2 Surplus | I41: Product 3 | J41: Daily Charge | K41: % of Monthly Fee for Prodcut 1 | L41: % of Monthly fee for Prodcut 2 | M41: % of Monthly Fee for Plan Cost | N41: Price of Prodcut 1 | O41: Price of Product 2 | P41: Total Price of Provided Units | Q41: Price of Plan | R41: Difference | S41: Target | T41: Off-Target
A42: 0.05 | C42: Program 1 | D42: 1e-05 | E42: 0 | F42: 0 | G42: 0.13 | H42: 0.1 | I42: 0.1 | J42: 0.05 | K42: =(E42*G42)/$D42 -> 0 | L42: =(F42*H42)/$D42 -> 0 | M42: =1-K42-L42 -> 1 | N42: =E42*G42 -> 0 | O42: =F42*H42 -> 0 | P42: =N42+O42 -> 0 | Q42: =D42 -> 1e-05 | R42: =P42-Q42 -> -1e-05 | S42: -0.5 | T42: =R42-S42 -> 0.49999
A43: 0.15 | B43: Default Program | C43: Program 2 | D43: 0.0001 | E43: 0 | F43: 0 | G43: 0.17 | H43: 0.13 | I43: 0.1 | J43: 0.17 | K43: =(E43*G43)/$D43 -> 0 | L43: =(F43*H43)/$D43 -> 0 | M43: =1-K43-L43 -> 1 | N43: =E43*G43 -> 0 | O43: =F43*H43 -> 0 | P43: =N43+O43 -> 0 | Q43: =D43 -> 0.0001 | R43: =P43-Q43 -> -0.0001 | S43: -0.5 | T43: =R43-S43 -> 0.4999
A44: 0.1 | C44: Program 3 | D44: 10 | E44: 75 | F44: 0 | G44: 0.15 | H44: 0.1 | I44: 0.1 | J44: 0 | K44: 1 | L44: =(F44*H44)/$D44 -> 0 | M44: =1-K44-L44 -> 0 | N44: =E44*G44 -> 11.25 | O44: =F44*H44 -> 0 | P44: =N44+O44 -> 11.25 | Q44: =D44 -> 10 | R44: =P44-Q44 -> 1.25 | S44: -0.5 | T44: =R44-S44 -> 1.75
A45: 0.1 | C45: Program 4 | D45: 25 | E45: 200 | F45: 0 | G45: 0.13 | H45: 0.1 | I45: 0.1 | J45: 0 | K45: 1 | L45: =(F45*H45)/$D45 -> 0 | M45: =1-K45-L45 -> 0 | N45: =E45*G45 -> 26 | O45: =F45*H45 -> 0 | P45: =N45+O45 -> 26 | Q45: =D45 -> 25 | R45: =P45-Q45 -> 1 | S45: -0.5 | T45: =R45-S45 -> 1.5
A46: 0.05 | C46: Program 5 | D46: 50 | E46: 450 | F46: 0 | G46: 0.13 | H46: 0.1 | I46: 0.1 | J46: 0 | K46: 1 | L46: =(F46*H46)/$D46 -> 0 | M46: =1-K46-L46 -> 0 | N46: =E46*G46 -> 58.5 | O46: =F46*H46 -> 0 | P46: =N46+O46 -> 58.5 | Q46: =D46 -> 50 | R46: =P46-Q46 -> 8.5 | S46: -0.5 | T46: =R46-S46 -> 9
A47: 0.01 | C47: Program 6 | D47: 100 | E47: 1000 | F47: 0 | G47: 0.1 | H47: 0.05 | I47: 0.05 | J47: 0 | K47: 1 | L47: =(F47*H47)/$D47 -> 0 | M47: =1-K47-L47 -> 0 | N47: =E47*G47 -> 100 | O47: =F47*H47 -> 0 | P47: =N47+O47 -> 100 | Q47: =D47 -> 100 | R47: =P47-Q47 -> 0 | S47: -0.5 | T47: =R47-S47 -> 0.5
A48: 0.02 | D48: 0.001 | E48: 0 | F48: 0 | G48: 0 | H48: 0 | I48: 0 | J48: 0 | K48: 1 | L48: =(F48*H48)/$D48 -> 0 | M48: =1-K48-L48 -> 0 | N48: =E48*G48 -> 0 | O48: =F48*H48 -> 0 | P48: =N48+O48 -> 0 | Q48: =D48 -> 0.001 | R48: =P48-Q48 -> -0.001 | S48: 0 | T48: =R48-S48 -> -0.001
F50: Per Subscriber | AC50: Aggregate
F51: Revenue | N51: Cost | V51: Profit | AC51: Revenue | AJ51: Cost | AR51: Profit (EBITDA) | AY51: Total Usage
B52: MVNO | C52: Program | D52: Penetration Rate of Program | E52: Number of Customers | F52: Program | G52: Product 1 Portion of Plan | H52: Product 1 Overage | I52: Product 2 Overage | J52: Product 3 Usage | K52: Product 1 Breakage | L52: Product 2 Breakage | M52: Daily Charge | N52: Program | O52: Product 1 Commission | P52: Product 1 Overage | Q52: Product 2 Overage | R52: Product 3 Usage | S52: Product 1 Breakage | T52: Product 2 Breakage | U52: Daily Charge | V52: Program | W52: Product 1 Overage | X52: Product 2 Overage | Y52: Product 3 Usage | Z52: Product 1 Breakage | AA52: Product 2 Breakage | AB52: Daily Charge | AC52: Program | AD52: Product 1 Overage | AE52: Product 2 Overage | AF52: Product 3 Usage | AG52: Product 1 Breakage | AH52: Product 2 Breakage | AI52: Daily Charge | AJ52: Program | AK52: Product 1 Commission | AL52: Product 1 Overage | AM52: Product 2 Overage | AN52: Product 3 Usage | AO52: Product 1 Breakage | AP52: Product 2 Breakage | AQ52: Daily Charge | AR52: Program | AS52: Product 1 Overage | AT52: Product 2 Overage | AU52: Product 3 Usage | AV52: Product 1 Breakage | AW52: Product 2 Breakage | AX52: Daily Charge | AY52: Product 1 Units | AZ52: Product 2 Messages | BA52: Product 3 Units | BB52: Product 1 Portion | BC52: Product 2 Portion
B53: =B30 -> Brand 1 | C53: =$C$42 -> Program 1 | D53: 0.27 | E53: =D53*$D$30 -> 4050 | F53: 0 | G53: =$K$42*F53 -> 0 | H53: =IF($C$23>$E$42,($C$23-$E$42)*$G$42,0) -> 29.77 | I53: =IF($C$24>$F$42,($C$24-$F$42)*$H$42,0) -> 9.3 | J53: =$C$25*$I$42 -> 0.0207 | K53: =IF($E$42>$C$23,($E$42-$C$23)*$C$8,0) -> 0 | L53: =IF($F$42>$C$24,($F$42-$C$24)*$C$9,0) -> 0 | M53: 0 | N53: =$C$2+($E$42*$C$8)+($F$42*$C$9) -> 5.27 | O53: =$C$11*G53+$C$11*P53 -> 2.201835 | P53: =IF($C$23>$E$42,($C$23-$E$42)*$C$8,0) -> 14.6789 | Q53: =IF($C$24>$F$42,($C$24-$F$42)*$C$9,0) -> 3.72 | R53: =$C$25*($C$10*10000/1000000) -> 0.00414 | S53: 0 | T53: 0 | U53: 0 | V53: =F53-N53 -> -5.27 | W53: =H53-P53-O53 -> 12.889265 | X53: =I53-Q53 -> 5.58 | Y53: =J53-R53 -> 0.01656 | Z53: =K53-S53 -> 0 | AA53: =L53-T53 -> 0 | AB53: =M53-U53 -> 0 | AC53: =$E53*F53 -> 0 | AD53: =E53*H53 -> 120568.5 | AE53: =E53*I53 -> 37665 | AF53: =E53*J53 -> 83.835 | AG53: =E53*K53 -> 0 | AH53: =E53*L53 -> 0 | AI53: =E53*M53 -> 0 | AJ53: =$E53*N53 -> 21343.5 | AK53: =E53*O53 -> 8917.4317 | AL53: =E53*P53 -> 59449.545 | AM53: =E53*Q53 -> 15066 | AN53: =E53*R53 -> 16.767 | AO53: =E53*Z53 -> 0 | AP53: =E53*T53 -> 0 | AQ53: =E53*U53 -> 0 | AR53: =AC53-AJ53 -> -21343.5 | AS53: =AD53-AK53-AL53 -> 52201.523 | AT53: =AE53-AM53 -> 22599 | AU53: =AF53-AN53 -> 67.068 | AV53: =AG53-AO53 -> 0 | AW53: =AH53-AP53 -> 0 | AX53: =AI53-AQ53 -> 0 | AY53: =E53*$C$23 -> 927450 | AZ53: =E53*$C$24 -> 376650 | BA53: =E53*$C$25 -> 838.35 | BB53: =$K$42*AR53 -> 0 | BC53: =$L$42*AR53 -> 0
C54: =$C$43 -> Program 2 | D54: 0.4 | E54: =D54*$D$30 -> 6000 | F54: 0 | G54: =$K$43*F54 -> 0 | H54: =IF($C$23>$E$43,($C$23-$E$43)*$G$43,0) -> 38.93 | I54: =IF($C$24>$F$43,($C$24-$F$43)*$H$43,0) -> 12.09 | J54: =$C$25*$I$43 -> 0.0207 | K54: =IF($E$43>$C$23,($E$43-$C$23)*$C$8,0) -> 0 | L54: =IF($F$43>$C$24,($F$43-$C$24)*$C$9,0) -> 0 | M54: 4.2 | N54: =$C$2+($E$43*$C$8)+($F$43*$C$9) -> 5.27 | O54: =$C$11*G54+$C$11*P54 -> 2.201835 | P54: =IF($C$23>$E$43,($C$23-$E$43)*$C$8,0) -> 14.6789 | Q54: =IF($C$24>$F$43,($C$24-$F$43)*$C$9,0) -> 3.72 | R54: =$C$25*($C$10*10000/1000000) -> 0.00414 | S54: 0 | T54: 0 | U54: 0 | V54: =F54-N54 -> -5.27 | W54: =H54-P54-O54 -> 22.049265 | X54: =I54-Q54 -> 8.37 | Y54: =J54-R54 -> 0.01656 | Z54: =K54-S54 -> 0 | AA54: =L54-T54 -> 0 | AB54: =M54-U54 -> 4.2 | AC54: =$E54*F54 -> 0 | AD54: =E54*H54 -> 233580 | AE54: =E54*I54 -> 72540 | AF54: =E54*J54 -> 124.2 | AG54: =E54*K54 -> 0 | AH54: =E54*L54 -> 0 | AI54: =E54*M54 -> 25200 | AJ54: =$E54*N54 -> 31620 | AK54: =E54*O54 -> 13211.01 | AL54: =E54*P54 -> 88073.4 | AM54: =E54*Q54 -> 22320 | AN54: =E54*R54 -> 24.84 | AO54: =E54*Z54 -> 0 | AP54: =E54*T54 -> 0 | AQ54: =E54*U54 -> 0 | AR54: =AC54-AJ54 -> -31620 | AS54: =AD54-AK54-AL54 -> 132295.59 | AT54: =AE54-AM54 -> 50220 | AU54: =AF54-AN54 -> 99.36 | AV54: =AG54-AO54 -> 0 | AW54: =AH54-AP54 -> 0 | AX54: =AI54-AQ54 -> 25200 | AY54: =E54*$C$23 -> 1374000 | AZ54: =E54*$C$24 -> 558000 | BA54: =E54*$C$25 -> 1242 | BB54: =$K$43*AR54 -> 0 | BC54: =$L$43*AR54 -> 0
C55: =$C$44 -> Program 3 | D55: 0.17 | E55: =D55*$D$30 -> 2550 | F55: 6 | G55: =$K$44*F55 -> 6 | H55: =IF($C$23>$E$44,($C$23-$E$44)*$G$44,0) -> 23.1 | I55: =IF($C$24>$F$44,($C$24-$F$44)*$H$44,0) -> 9.3 | J55: =$C$25*$I$44 -> 0.0207 | K55: =IF($E$44>$C$23,($E$44-$C$23)*$C$8,0) -> 0 | L55: =IF($F$44>$C$24,($F$44-$C$24)*$C$9,0) -> 0 | M55: 2.8 | N55: =$C$2+($E$44*$C$8)+($F$44*$C$9) -> 10.0775 | O55: =$C$11*G55+$C$11*P55 -> 2.38071 | P55: =IF($C$23>$E$44,($C$23-$E$44)*$C$8,0) -> 9.8714 | Q55: =IF($C$24>$F$44,($C$24-$F$44)*$C$9,0) -> 3.72 | R55: =$C$25*($C$10*10000/1000000) -> 0.00414 | S55: 0 | T55: 0 | U55: 0 | V55: =F55-N55 -> -4.0775 | W55: =H55-P55-O55 -> 10.84789 | X55: =I55-Q55 -> 5.58 | Y55: =J55-R55 -> 0.01656 | Z55: =K55-S55 -> 0 | AA55: =L55-T55 -> 0 | AB55: =M55-U55 -> 2.8 | AC55: =$E55*F55 -> 15300 | AD55: =E55*H55 -> 58905 | AE55: =E55*I55 -> 23715 | AF55: =E55*J55 -> 52.785 | AG55: =E55*K55 -> 0 | AH55: =E55*L55 -> 0 | AI55: =E55*M55 -> 7140 | AJ55: =$E55*N55 -> 25697.625 | AK55: =E55*O55 -> 6070.8105 | AL55: =E55*P55 -> 25172.07 | AM55: =E55*Q55 -> 9486 | AN55: =E55*R55 -> 10.557 | AO55: =E55*Z55 -> 0 | AP55: =E55*T55 -> 0 | AQ55: =E55*U55 -> 0 | AR55: =AC55-AJ55 -> -10397.625 | AS55: =AD55-AK55-AL55 -> 27662.12 | AT55: =AE55-AM55 -> 14229 | AU55: =AF55-AN55 -> 42.228 | AV55: =AG55-AO55 -> 0 | AW55: =AH55-AP55 -> 0 | AX55: =AI55-AQ55 -> 7140 | AY55: =E55*$C$23 -> 583950 | AZ55: =E55*$C$24 -> 237150 | BA55: =E55*$C$25 -> 527.85 | BB55: =$K$44*AR55 -> -10397.625 | BC55: =$L$44*AR55 -> 0
C56: =$C$45 -> Program 4 | D56: 0.1 | E56: =D56*$D$30 -> 1500 | F56: 15 | G56: =$K$45*F56 -> 15 | H56: =IF($C$23>$E$45,($C$23-$E$45)*$G$45,0) -> 3.77 | I56: =IF($C$24>$F$45,($C$24-$F$45)*$H$45,0) -> 9.3 | J56: =$C$25*$I$45 -> 0.0207 | K56: =IF($E$45>$C$23,($E$45-$C$23)*$C$8,0) -> 0 | L56: =IF($F$45>$C$24,($F$45-$C$24)*$C$9,0) -> 0 | M56: 0 | N56: =$C$2+($E$45*$C$8)+($F$45*$C$9) -> 18.09 | O56: =$C$11*G56+$C$11*P56 -> 2.528835 | P56: =IF($C$23>$E$45,($C$23-$E$45)*$C$8,0) -> 1.8589 | Q56: =IF($C$24>$F$45,($C$24-$F$45)*$C$9,0) -> 3.72 | R56: =$C$25*($C$10*10000/1000000) -> 0.00414 | S56: 0 | T56: 0 | U56: 0 | V56: =F56-N56 -> -3.09 | W56: =H56-P56-O56 -> -0.617735 | X56: =I56-Q56 -> 5.58 | Y56: =J56-R56 -> 0.01656 | Z56: =K56-S56 -> 0 | AA56: =L56-T56 -> 0 | AB56: =M56-U56 -> 0 | AC56: =$E56*F56 -> 22500 | AD56: =E56*H56 -> 5655 | AE56: =E56*I56 -> 13950 | AF56: =E56*J56 -> 31.05 | AG56: =E56*K56 -> 0 | AH56: =E56*L56 -> 0 | AI56: =E56*M56 -> 0 | AJ56: =$E56*N56 -> 27135 | AK56: =E56*O56 -> 3793.2525 | AL56: =E56*P56 -> 2788.35 | AM56: =E56*Q56 -> 5580 | AN56: =E56*R56 -> 6.21 | AO56: =E56*Z56 -> 0 | AP56: =E56*T56 -> 0 | AQ56: =E56*U56 -> 0 | AR56: =AC56-AJ56 -> -4635 | AS56: =AD56-AK56-AL56 -> -926.6025 | AT56: =AE56-AM56 -> 8370 | AU56: =AF56-AN56 -> 24.84 | AV56: =AG56-AO56 -> 0 | AW56: =AH56-AP56 -> 0 | AX56: =AI56-AQ56 -> 0 | AY56: =E56*$C$23 -> 343500 | AZ56: =E56*$C$24 -> 139500 | BA56: =E56*$C$25 -> 310.5 | BB56: =$K$45*AR56 -> -4635 | BC56: =$L$45*AR56 -> 0
C57: =$C$46 -> Program 5 | D57: 0.05 | E57: =D57*$D$30 -> 750 | F57: 25 | G57: =$K$46*F57 -> 25 | H57: =IF($C$23>$E$46,($C$23-$E$46)*$G$46,0) -> 0 | I57: =IF($C$24>$F$46,($C$24-$F$46)*$H$46,0) -> 9.3 | J57: =$C$25*$I$46 -> 0.0207 | K57: =IF($E$46>$C$23,($E$46-$C$23)*$C$8,0) -> 14.1661 | L57: =IF($F$46>$C$24,($F$46-$C$24)*$C$9,0) -> 0 | M57: 0 | N57: =$C$2+($E$46*$C$8)+($F$46*$C$9) -> 34.115 | O57: =$C$11*G57+$C$11*P57 -> 3.75 | P57: =IF($C$23>$E$46,($C$23-$E$46)*$C$8,0) -> 0 | Q57: =IF($C$24>$F$46,($C$24-$F$46)*$C$9,0) -> 3.72 | R57: =$C$25*($C$10*10000/1000000) -> 0.00414 | S57: 0 | T57: 0 | U57: 0 | V57: =F57-N57 -> -9.115 | W57: =H57-P57-O57 -> -3.75 | X57: =I57-Q57 -> 5.58 | Y57: =J57-R57 -> 0.01656 | Z57: =K57-S57 -> 14.1661 | AA57: =L57-T57 -> 0 | AB57: =M57-U57 -> 0 | AC57: =$E57*F57 -> 18750 | AD57: =E57*H57 -> 0 | AE57: =E57*I57 -> 6975 | AF57: =E57*J57 -> 15.525 | AG57: =E57*K57 -> 10624.575 | AH57: =E57*L57 -> 0 | AI57: =E57*M57 -> 0 | AJ57: =$E57*N57 -> 25586.25 | AK57: =E57*O57 -> 2812.5 | AL57: =E57*P57 -> 0 | AM57: =E57*Q57 -> 2790 | AN57: =E57*R57 -> 3.105 | AO57: =E57*Z57 -> 10624.575 | AP57: =E57*T57 -> 0 | AQ57: =E57*U57 -> 0 | AR57: =AC57-AJ57 -> -6836.25 | AS57: =AD57-AK57-AL57 -> -2812.5 | AT57: =AE57-AM57 -> 4185 | AU57: =AF57-AN57 -> 12.42 | AV57: =AG57-AO57 -> 0 | AW57: =AH57-AP57 -> 0 | AX57: =AI57-AQ57 -> 0 | AY57: =E57*$C$23 -> 171750 | AZ57: =E57*$C$24 -> 69750 | BA57: =E57*$C$25 -> 155.25 | BB57: =$K$46*AR57 -> -6836.25 | BC57: =$L$46*AR57 -> 0
C58: =$C$47 -> Program 6 | D58: 0.01 | E58: =D58*$D$30 -> 150 | F58: 25 | G58: =$K$46*F58 -> 25 | H58: =IF($C$23>$E$46,($C$23-$E$46)*$G$46,0) -> 0 | I58: =IF($C$24>$F$46,($C$24-$F$46)*$H$46,0) -> 9.3 | J58: =$C$25*$I$46 -> 0.0207 | K58: =IF($E$46>$C$23,($E$46-$C$23)*$C$8,0) -> 14.1661 | L58: =IF($F$46>$C$24,($F$46-$C$24)*$C$9,0) -> 0 | M58: 0 | N58: =$C$2+($E$46*$C$8)+($F$46*$C$9) -> 34.115 | O58: =$C$11*G58+$C$11*P58 -> 3.75 | P58: =IF($C$23>$E$46,($C$23-$E$46)*$C$8,0) -> 0 | Q58: =IF($C$24>$F$46,($C$24-$F$46)*$C$9,0) -> 3.72 | R58: =$C$25*($C$10*10000/1000000) -> 0.00414 | S58: 0 | T58: 0 | U58: 0 | V58: =F58-N58 -> -9.115 | W58: =H58-P58-O58 -> -3.75 | X58: =I58-Q58 -> 5.58 | Y58: =J58-R58 -> 0.01656 | Z58: =K58-S58 -> 14.1661 | AA58: =L58-T58 -> 0 | AB58: =M58-U58 -> 0 | AC58: =$E58*F58 -> 3750 | AD58: =E58*H58 -> 0 | AE58: =E58*I58 -> 1395 | AF58: =E58*J58 -> 3.105 | AG58: =E58*K58 -> 2124.915 | AH58: =E58*L58 -> 0 | AI58: =E58*M58 -> 0 | AJ58: =$E58*N58 -> 5117.25 | AK58: =E58*O58 -> 562.5 | AL58: =E58*P58 -> 0 | AM58: =E58*Q58 -> 558 | AN58: =E58*R58 -> 0.621 | AO58: =E58*Z58 -> 2124.915 | AP58: =E58*T58 -> 0 | AQ58: =E58*U58 -> 0 | AR58: =AC58-AJ58 -> -1367.25 | AS58: =AD58-AK58-AL58 -> -562.5 | AT58: =AE58-AM58 -> 837 | AU58: =AF58-AN58 -> 2.484 | AV58: =AG58-AO58 -> 0 | AW58: =AH58-AP58 -> 0 | AX58: =AI58-AQ58 -> 0 | AY58: =E58*$C$23 -> 34350 | AZ58: =E58*$C$24 -> 13950 | BA58: =E58*$C$25 -> 31.05 | BB58: =$K$46*AR58 -> -1367.25 | BC58: =$L$46*AR58 -> 0
C59: =$C$48 -> 0 | D59: 0 | E59: =D59*$D$30 -> 0 | F59: 35 | G59: =$K$48*F59 -> 35 | H59: =IF($C$23>$E$48,($C$23-$E$48)*$G$48,0) -> 0 | I59: =IF($C$24>$F$48,($C$24-$F$48)*$H$48,0) -> 0 | J59: =$C$25*$I$48 -> 0 | K59: =IF($E$48>$C$23,($E$48-$C$23)*$C$8,0) -> 0 | L59: =IF($F$48>$C$24,($F$48-$C$24)*$C$9,0) -> 0 | M59: 0 | N59: =$C$2+($E$48*$C$8)+($F$48*$C$9) -> 5.27 | O59: =$C$11*G59+$C$11*P59 -> 7.451835 | P59: =IF($C$23>$E$48,($C$23-$E$48)*$C$8,0) -> 14.6789 | Q59: =IF($C$24>$F$48,($C$24-$F$48)*$C$9,0) -> 3.72 | R59: =$C$25*($C$10*10000/1000000) -> 0.00414 | S59: 0 | T59: 0 | U59: 0 | V59: =F59-N59 -> 29.73 | W59: =H59-P59-O59 -> -22.130735 | X59: =I59-Q59 -> -3.72 | Y59: =J59-R59 -> -0.00414 | Z59: =K59-S59 -> 0 | AA59: =L59-T59 -> 0 | AB59: =M59-U59 -> 0 | AC59: =$E59*F59 -> 0 | AD59: =E59*H59 -> 0 | AE59: =E59*I59 -> 0 | AF59: =E59*J59 -> 0 | AG59: =E59*K59 -> 0 | AH59: =E59*L59 -> 0 | AI59: =E59*M59 -> 0 | AJ59: =$E59*N59 -> 0 | AK59: =E59*O59 -> 0 | AL59: =E59*P59 -> 0 | AM59: =E59*Q59 -> 0 | AN59: =E59*R59 -> 0 | AO59: =E59*Z59 -> 0 | AP59: =E59*T59 -> 0 | AQ59: =E59*U59 -> 0 | AR59: =AC59-AJ59 -> 0 | AS59: =AD59-AK59-AL59 -> 0 | AT59: =AE59-AM59 -> 0 | AU59: =AF59-AN59 -> 0 | AV59: =AG59-AO59 -> 0 | AW59: =AH59-AP59 -> 0 | AX59: =AI59-AQ59 -> 0 | AY59: =E59*$C$23 -> 0 | AZ59: =E59*$C$24 -> 0 | BA59: =E59*$C$25 -> 0 | BB59: =$K$48*AR59 -> 0 | BC59: =$L$48*AR59 -> 0
C60: Weighted Average | F60: =(($E53*F53)+($E54*F54)+($E55*F55)+($E56*F56)+($E57*F57)+($E59*F59))/($E61) -> 3.77 | G60: =(($E53*G53)+($E54*G54)+($E55*G55)+($E56*G56)+($E57*G57)+($E59*G59))/($E61) -> 3.77 | H60: =(($E53*H53)+($E54*H54)+($E55*H55)+($E56*H56)+($E57*H57)+($E59*H59))/($E61) -> 27.9139 | I60: =(($E53*I53)+($E54*I54)+($E55*I55)+($E56*I56)+($E57*I57)+($E59*I59))/($E61) -> 10.323 | J60: =(($E53*J53)+($E54*J54)+($E55*J55)+($E56*J56)+($E57*J57)+($E59*J59))/($E61) -> 0.020493 | K60: =(($E53*K53)+($E54*K54)+($E55*K55)+($E56*K56)+($E57*K57)+($E59*K59))/($E61) -> 0.708305 | L60: =(($E53*L53)+($E54*L54)+($E55*L55)+($E56*L56)+($E57*L57)+($E59*L59))/($E61) -> 0 | M60: =(($E53*M53)+($E54*M54)+($E55*M55)+($E56*M56)+($E57*M57)+($E59*M59))/($E61) -> 2.156 | ... AB60: =(($E53*AB53)+($E54*AB54)+($E55*AB55)+($E56*AB56)+($E57*AB57)+($E59*AB59))/($E61) -> 2.156 | AC60: =SUM(AC53:AC59)/$E61 -> 4.02 | AD60: =SUM(AD53:AD59)/$E61 -> 27.9139 | AE60: =SUM(AE53:AE59)/$E61 -> 10.416 | AF60: =SUM(AF53:AF59)/$E61 -> 0.0207 | AG60: =SUM(AG53:AG59)/$E61 -> 0.849966 | AH60: =SUM(AH53:AH59)/$E61 -> 0 | AI60: =SUM(AI53:AI59)/$E61 -> 2.156 | AJ60: =SUM(AJ53:AJ59)/$E61 -> 9.099975 | ... BC60: =SUM(BC53:BC59)/$E61 -> 0
C61: Totals | D61: =SUM(D53:D59) -> 1 | E61: =SUM(E53:E59) -> 15000 | AC61: =SUM(AC53:AC59) -> 60300 | AD61: =SUM(AD53:AD59) -> 418708.5 | AE61: =SUM(AE53:AE59) -> 156240 | AF61: =SUM(AF53:AF59) -> 310.5 | AG61: =SUM(AG53:AG59) -> 12749.49 | AH61: =SUM(AH53:AH59) -> 0 | AI61: =SUM(AI53:AI59) -> 32340 | AJ61: =SUM(AJ53:AJ59) -> 136499.62 | ... BC61: =SUM(BC53:BC59) -> 0
B62: =B31 -> Brand 2 | C62: =$C$42 -> Program 1 | D62: 0.27 | E62: =D62*$D$31 -> 2700 | F62: 0 | G62: =$K$42*F62 -> 0 | H62: =IF($C$23>$E$42,($C$23-$E$42)*$G$42,0) -> 29.77 | I62: =IF($C$24>$F$42,($C$24-$F$42)*$H$42,0) -> 9.3 | J62: =$C$25*$I$42 -> 0.0207 | K62: =IF($E$42>$C$23,($E$42-$C$23)*$C$8,0) -> 0 | L62: =IF($F$42>$C$24,($F$42-$C$24)*$C$9,0) -> 0 | M62: 0 | N62: =$C$2+($E$42*$C$8)+($F$42*$C$9) -> 5.27 | O62: =$C$11*G62+$C$11*P62 -> 2.201835 | P62: =IF($C$23>$E$42,($C$23-$E$42)*$C$8,0) -> 14.6789 | Q62: =IF($C$24>$F$42,($C$24-$F$42)*$C$9,0) -> 3.72 | R62: =$C$25*($C$10*10000/1000000) -> 0.00414 | S62: 0 | T62: 0 | U62: 0 | V62: =F62-N62 -> -5.27 | W62: =H62-P62-O62 -> 12.889265 | X62: =I62-Q62 -> 5.58 | Y62: =J62-R62 -> 0.01656 | Z62: =K62-S62 -> 0 | AA62: =L62-T62 -> 0 | AB62: =M62-U62 -> 0 | AC62: =$E62*F62 -> 0 | AD62: =E62*H62 -> 80379 | AE62: =E62*I62 -> 25110 | AF62: =E62*J62 -> 55.89 | AG62: =E62*K62 -> 0 | AH62: =E62*L62 -> 0 | AI62: =E62*M62 -> 0 | AJ62: =$E62*N62 -> 14229 | AK62: =E62*O62 -> 5944.9545 | AL62: =E62*P62 -> 39633.03 | AM62: =E62*Q62 -> 10044 | AN62: =E62*R62 -> 11.178 | AO62: =E62*Z62 -> 0 | AP62: =E62*T62 -> 0 | AQ62: =E62*U62 -> 0 | AR62: =AC62-AJ62 -> -14229 | AS62: =AD62-AK62-AL62 -> 34801.016 | AT62: =AE62-AM62 -> 15066 | AU62: =AF62-AN62 -> 44.712 | AV62: =AG62-AO62 -> 0 | AW62: =AH62-AP62 -> 0 | AX62: =AI62-AQ62 -> 0 | AY62: =E62*$C$23 -> 618300 | AZ62: =E62*$C$24 -> 251100 | BA62: =E62*$C$25 -> 558.9 | BB62: =$K$42*AR62 -> 0 | BC62: =$L$42*AR62 -> 0
C63: =$C$43 -> Program 2 | D63: 0.4 | E63: =D63*$D$31 -> 4000 | F63: 0 | G63: =$K$43*F63 -> 0 | H63: =IF($C$23>$E$43,($C$23-$E$43)*$G$43,0) -> 38.93 | I63: =IF($C$24>$F$43,($C$24-$F$43)*$H$43,0) -> 12.09 | J63: =$C$25*$I$43 -> 0.0207 | K63: =IF($E$43>$C$23,($E$43-$C$23)*$C$8,0) -> 0 | L63: =IF($F$43>$C$24,($F$43-$C$24)*$C$9,0) -> 0 | M63: 4.2 | N63: =$C$2+($E$43*$C$8)+($F$43*$C$9) -> 5.27 | O63: =$C$11*G63+$C$11*P63 -> 2.201835 | P63: =IF($C$23>$E$43,($C$23-$E$43)*$C$8,0) -> 14.6789 | Q63: =IF($C$24>$F$43,($C$24-$F$43)*$C$9,0) -> 3.72 | R63: =$C$25*($C$10*10000/1000000) -> 0.00414 | S63: 0 | T63: 0 | U63: 0 | V63: =F63-N63 -> -5.27 | W63: =H63-P63-O63 -> 22.049265 | X63: =I63-Q63 -> 8.37 | Y63: =J63-R63 -> 0.01656 | Z63: =K63-S63 -> 0 | AA63: =L63-T63 -> 0 | AB63: =M63-U63 -> 4.2 | AC63: =$E63*F63 -> 0 | AD63: =E63*H63 -> 155720 | AE63: =E63*I63 -> 48360 | AF63: =E63*J63 -> 82.8 | AG63: =E63*K63 -> 0 | AH63: =E63*L63 -> 0 | AI63: =E63*M63 -> 16800 | AJ63: =$E63*N63 -> 21080 | AK63: =E63*O63 -> 8807.34 | AL63: =E63*P63 -> 58715.6 | AM63: =E63*Q63 -> 14880 | AN63: =E63*R63 -> 16.56 | AO63: =E63*Z63 -> 0 | AP63: =E63*T63 -> 0 | AQ63: =E63*U63 -> 0 | AR63: =AC63-AJ63 -> -21080 | AS63: =AD63-AK63-AL63 -> 88197.06 | AT63: =AE63-AM63 -> 33480 | AU63: =AF63-AN63 -> 66.24 | AV63: =AG63-AO63 -> 0 | AW63: =AH63-AP63 -> 0 | AX63: =AI63-AQ63 -> 16800 | AY63: =E63*$C$23 -> 916000 | AZ63: =E63*$C$24 -> 372000 | BA63: =E63*$C$25 -> 828 | BB63: =$K$43*AR63 -> 0 | BC63: =$L$43*AR63 -> 0
C64: =$C$44 -> Program 3 | D64: =D55 -> 0.17 | E64: =D64*$D$31 -> 1700 | F64: 6 | G64: =$K$44*F64 -> 6 | H64: =IF($C$23>$E$44,($C$23-$E$44)*$G$44,0) -> 23.1 | I64: =IF($C$24>$F$44,($C$24-$F$44)*$H$44,0) -> 9.3 | J64: =$C$25*$I$44 -> 0.0207 | K64: =IF($E$44>$C$23,($E$44-$C$23)*$C$8,0) -> 0 | L64: =IF($F$44>$C$24,($F$44-$C$24)*$C$9,0) -> 0 | M64: 2.8 | N64: =$C$2+($E$44*$C$8)+($F$44*$C$9) -> 10.0775 | O64: =$C$11*G64+$C$11*P64 -> 2.38071 | P64: =IF($C$23>$E$44,($C$23-$E$44)*$C$8,0) -> 9.8714 | Q64: =IF($C$24>$F$44,($C$24-$F$44)*$C$9,0) -> 3.72 | R64: =$C$25*($C$10*10000/1000000) -> 0.00414 | S64: 0 | T64: 0 | U64: 0 | V64: =F64-N64 -> -4.0775 | W64: =H64-P64-O64 -> 10.84789 | X64: =I64-Q64 -> 5.58 | Y64: =J64-R64 -> 0.01656 | Z64: =K64-S64 -> 0 | AA64: =L64-T64 -> 0 | AB64: =M64-U64 -> 2.8 | AC64: =$E64*F64 -> 10200 | AD64: =E64*H64 -> 39270 | AE64: =E64*I64 -> 15810 | AF64: =E64*J64 -> 35.19 | AG64: =E64*K64 -> 0 | AH64: =E64*L64 -> 0 | AI64: =E64*M64 -> 4760 | AJ64: =$E64*N64 -> 17131.75 | AK64: =E64*O64 -> 4047.207 | AL64: =E64*P64 -> 16781.38 | AM64: =E64*Q64 -> 6324 | AN64: =E64*R64 -> 7.038 | AO64: =E64*Z64 -> 0 | AP64: =E64*T64 -> 0 | AQ64: =E64*U64 -> 0 | AR64: =AC64-AJ64 -> -6931.75 | AS64: =AD64-AK64-AL64 -> 18441.413 | AT64: =AE64-AM64 -> 9486 | AU64: =AF64-AN64 -> 28.152 | AV64: =AG64-AO64 -> 0 | AW64: =AH64-AP64 -> 0 | AX64: =AI64-AQ64 -> 4760 | AY64: =E64*$C$23 -> 389300 | AZ64: =E64*$C$24 -> 158100 | BA64: =E64*$C$25 -> 351.9 | BB64: =$K$44*AR64 -> -6931.75 | BC64: =$L$44*AR64 -> 0
C65: =$C$45 -> Program 4 | D65: =D56 -> 0.1 | E65: =D65*$D$31 -> 1000 | F65: 15 | G65: =$K$45*F65 -> 15 | H65: =IF($C$23>$E$45,($C$23-$E$45)*$G$45,0) -> 3.77 | I65: =IF($C$24>$F$45,($C$24-$F$45)*$H$45,0) -> 9.3 | J65: =$C$25*$I$45 -> 0.0207 | K65: =IF($E$45>$C$23,($E$45-$C$23)*$C$8,0) -> 0 | L65: =IF($F$45>$C$24,($F$45-$C$24)*$C$9,0) -> 0 | M65: 0 | N65: =$C$2+($E$45*$C$8)+($F$45*$C$9) -> 18.09 | O65: =$C$11*G65+$C$11*P65 -> 2.528835 | P65: =IF($C$23>$E$45,($C$23-$E$45)*$C$8,0) -> 1.8589 | Q65: =IF($C$24>$F$45,($C$24-$F$45)*$C$9,0) -> 3.72 | R65: =$C$25*($C$10*10000/1000000) -> 0.00414 | S65: 0 | T65: 0 | U65: 0 | V65: =F65-N65 -> -3.09 | W65: =H65-P65-O65 -> -0.617735 | X65: =I65-Q65 -> 5.58 | Y65: =J65-R65 -> 0.01656 | Z65: =K65-S65 -> 0 | AA65: =L65-T65 -> 0 | AB65: =M65-U65 -> 0 | AC65: =$E65*F65 -> 15000 | AD65: =E65*H65 -> 3770 | AE65: =E65*I65 -> 9300 | AF65: =E65*J65 -> 20.7 | AG65: =E65*K65 -> 0 | AH65: =E65*L65 -> 0 | AI65: =E65*M65 -> 0 | AJ65: =$E65*N65 -> 18090 | AK65: =E65*O65 -> 2528.835 | AL65: =E65*P65 -> 1858.9 | AM65: =E65*Q65 -> 3720 | AN65: =E65*R65 -> 4.14 | AO65: =E65*Z65 -> 0 | AP65: =E65*T65 -> 0 | AQ65: =E65*U65 -> 0 | AR65: =AC65-AJ65 -> -3090 | AS65: =AD65-AK65-AL65 -> -617.735 | AT65: =AE65-AM65 -> 5580 | AU65: =AF65-AN65 -> 16.56 | AV65: =AG65-AO65 -> 0 | AW65: =AH65-AP65 -> 0 | AX65: =AI65-AQ65 -> 0 | AY65: =E65*$C$23 -> 229000 | AZ65: =E65*$C$24 -> 93000 | BA65: =E65*$C$25 -> 207 | BB65: =$K$45*AR65 -> -3090 | BC65: =$L$45*AR65 -> 0
C66: =$C$46 -> Program 5 | D66: =D57 -> 0.05 | E66: =D66*$D$31 -> 500 | F66: 25 | G66: =$K$46*F66 -> 25 | H66: =IF($C$23>$E$46,($C$23-$E$46)*$G$46,0) -> 0 | I66: =IF($C$24>$F$46,($C$24-$F$46)*$H$46,0) -> 9.3 | J66: =$C$25*$I$46 -> 0.0207 | K66: =IF($E$46>$C$23,($E$46-$C$23)*$C$8,0) -> 14.1661 | L66: =IF($F$46>$C$24,($F$46-$C$24)*$C$9,0) -> 0 | M66: 0 | N66: =$C$2+($E$46*$C$8)+($F$46*$C$9) -> 34.115 | O66: =$C$11*G66+$C$11*P66 -> 3.75 | P66: =IF($C$23>$E$46,($C$23-$E$46)*$C$8,0) -> 0 | Q66: =IF($C$24>$F$46,($C$24-$F$46)*$C$9,0) -> 3.72 | R66: =$C$25*($C$10*10000/1000000) -> 0.00414 | S66: 0 | T66: 0 | U66: 0 | V66: =F66-N66 -> -9.115 | W66: =H66-P66-O66 -> -3.75 | X66: =I66-Q66 -> 5.58 | Y66: =J66-R66 -> 0.01656 | Z66: =K66-S66 -> 14.1661 | AA66: =L66-T66 -> 0 | AB66: =M66-U66 -> 0 | AC66: =$E66*F66 -> 12500 | AD66: =E66*H66 -> 0 | AE66: =E66*I66 -> 4650 | AF66: =E66*J66 -> 10.35 | AG66: =E66*K66 -> 7083.05 | AH66: =E66*L66 -> 0 | AI66: =E66*M66 -> 0 | AJ66: =$E66*N66 -> 17057.5 | AK66: =E66*O66 -> 1875 | AL66: =E66*P66 -> 0 | AM66: =E66*Q66 -> 1860 | AN66: =E66*R66 -> 2.07 | AO66: =E66*Z66 -> 7083.05 | AP66: =E66*T66 -> 0 | AQ66: =E66*U66 -> 0 | AR66: =AC66-AJ66 -> -4557.5 | AS66: =AD66-AK66-AL66 -> -1875 | AT66: =AE66-AM66 -> 2790 | AU66: =AF66-AN66 -> 8.28 | AV66: =AG66-AO66 -> 0 | AW66: =AH66-AP66 -> 0 | AX66: =AI66-AQ66 -> 0 | AY66: =E66*$C$23 -> 114500 | AZ66: =E66*$C$24 -> 46500 | BA66: =E66*$C$25 -> 103.5 | BB66: =$K$46*AR66 -> -4557.5 | BC66: =$L$46*AR66 -> 0
C67: =$C$47 -> Program 6 | D67: =D58 -> 0.01 | E67: =D67*$D$30 -> 150 | F67: 25 | G67: =$K$46*F67 -> 25 | H67: =IF($C$23>$E$46,($C$23-$E$46)*$G$46,0) -> 0 | I67: =IF($C$24>$F$46,($C$24-$F$46)*$H$46,0) -> 9.3 | J67: =$C$25*$I$46 -> 0.0207 | K67: =IF($E$46>$C$23,($E$46-$C$23)*$C$8,0) -> 14.1661 | L67: =IF($F$46>$C$24,($F$46-$C$24)*$C$9,0) -> 0 | M67: 0 | N67: =$C$2+($E$46*$C$8)+($F$46*$C$9) -> 34.115 | O67: =$C$11*G67+$C$11*P67 -> 3.75 | P67: =IF($C$23>$E$46,($C$23-$E$46)*$C$8,0) -> 0 | Q67: =IF($C$24>$F$46,($C$24-$F$46)*$C$9,0) -> 3.72 | R67: =$C$25*($C$10*10000/1000000) -> 0.00414 | S67: 0 | T67: 0 | U67: 0 | V67: =F67-N67 -> -9.115 | W67: =H67-P67-O67 -> -3.75 | X67: =I67-Q67 -> 5.58 | Y67: =J67-R67 -> 0.01656 | Z67: =K67-S67 -> 14.1661 | AA67: =L67-T67 -> 0 | AB67: =M67-U67 -> 0 | AC67: =$E67*F67 -> 3750 | AD67: =E67*H67 -> 0 | AE67: =E67*I67 -> 1395 | AF67: =E67*J67 -> 3.105 | AG67: =E67*K67 -> 2124.915 | AH67: =E67*L67 -> 0 | AI67: =E67*M67 -> 0 | AJ67: =$E67*N67 -> 5117.25 | AK67: =E67*O67 -> 562.5 | AL67: =E67*P67 -> 0 | AM67: =E67*Q67 -> 558 | AN67: =E67*R67 -> 0.621 | AO67: =E67*Z67 -> 2124.915 | AP67: =E67*T67 -> 0 | AQ67: =E67*U67 -> 0 | AR67: =AC67-AJ67 -> -1367.25 | AS67: =AD67-AK67-AL67 -> -562.5 | AT67: =AE67-AM67 -> 837 | AU67: =AF67-AN67 -> 2.484 | AV67: =AG67-AO67 -> 0 | AW67: =AH67-AP67 -> 0 | AX67: =AI67-AQ67 -> 0 | AY67: =E67*$C$23 -> 34350 | AZ67: =E67*$C$24 -> 13950 | BA67: =E67*$C$25 -> 31.05 | BB67: =$K$46*AR67 -> -1367.25 | BC67: =$L$46*AR67 -> 0
C68: =$C$48 -> 0 | D68: 0 | E68: =D68*$D$31 -> 0 | F68: 35 | G68: =$K$48*F68 -> 35 | H68: =IF($C$23>$E$48,($C$23-$E$48)*$G$48,0) -> 0 | I68: =IF($C$24>$F$48,($C$24-$F$48)*$H$48,0) -> 0 | J68: =$C$25*$I$48 -> 0 | K68: =IF($E$48>$C$23,($E$48-$C$23)*$C$8,0) -> 0 | L68: =IF($F$48>$C$24,($F$48-$C$24)*$C$9,0) -> 0 | M68: 0 | N68: =$C$2+($E$48*$C$8)+($F$48*$C$9) -> 5.27 | O68: =$C$11*G68+$C$11*P68 -> 7.451835 | P68: =IF($C$23>$E$48,($C$23-$E$48)*$C$8,0) -> 14.6789 | Q68: =IF($C$24>$F$48,($C$24-$F$48)*$C$9,0) -> 3.72 | R68: =$C$25*($C$10*10000/1000000) -> 0.00414 | S68: 0 | T68: 0 | U68: 0 | V68: =F68-N68 -> 29.73 | W68: =H68-P68-O68 -> -22.130735 | X68: =I68-Q68 -> -3.72 | Y68: =J68-R68 -> -0.00414 | Z68: =K68-S68 -> 0 | AA68: =L68-T68 -> 0 | AB68: =M68-U68 -> 0 | AC68: =$E68*F68 -> 0 | AD68: =E68*H68 -> 0 | AE68: =E68*I68 -> 0 | AF68: =E68*J68 -> 0 | AG68: =E68*K68 -> 0 | AH68: =E68*L68 -> 0 | AI68: =E68*M68 -> 0 | AJ68: =$E68*N68 -> 0 | AK68: =E68*O68 -> 0 | AL68: =E68*P68 -> 0 | AM68: =E68*Q68 -> 0 | AN68: =E68*R68 -> 0 | AO68: =E68*Z68 -> 0 | AP68: =E68*T68 -> 0 | AQ68: =E68*U68 -> 0 | AR68: =AC68-AJ68 -> 0 | AS68: =AD68-AK68-AL68 -> 0 | AT68: =AE68-AM68 -> 0 | AU68: =AF68-AN68 -> 0 | AV68: =AG68-AO68 -> 0 | AW68: =AH68-AP68 -> 0 | AX68: =AI68-AQ68 -> 0 | AY68: =E68*$C$23 -> 0 | AZ68: =E68*$C$24 -> 0 | BA68: =E68*$C$25 -> 0 | BB68: =$K$48*AR68 -> 0 | BC68: =$L$48*AR68 -> 0
C69: Weighted Average | F69: =(($E62*F62)+($E63*F63)+($E64*F64)+($E65*F65)+($E66*F66)+($E68*F68))/($E70) -> 3.7512438 | G69: =(($E62*G62)+($E63*G63)+($E64*G64)+($E65*G65)+($E66*G66)+($E68*G68))/($E70) -> 3.7512438 | H69: =(($E62*H62)+($E63*H63)+($E64*H64)+($E65*H65)+($E66*H66)+($E68*H68))/($E70) -> 27.775025 | I69: =(($E62*I62)+($E63*I63)+($E64*I64)+($E65*I65)+($E66*I66)+($E68*I68))/($E70) -> 10.271642 | J69: =(($E62*J62)+($E63*J63)+($E64*J64)+($E65*J65)+($E66*J66)+($E68*J68))/($E70) -> 0.020391045 | K69: =(($E62*K62)+($E63*K63)+($E64*K64)+($E65*K65)+($E66*K66)+($E68*K68))/($E70) -> 0.70478109 | L69: =(($E62*L62)+($E63*L63)+($E64*L64)+($E65*L65)+($E66*L66)+($E68*L68))/($E70) -> 0 | M69: =(($E62*M62)+($E63*M63)+($E64*M64)+($E65*M65)+($E66*M66)+($E68*M68))/($E70) -> 2.1452736 | ... AB69: =(($E62*AB62)+($E63*AB63)+($E64*AB64)+($E65*AB65)+($E66*AB66)+($E68*AB68))/($E70) -> 2.1452736 | AC69: =SUM(AC62:AC68)/$E70 -> 4.1243781 | AD69: =SUM(AD62:AD68)/$E70 -> 27.775025 | AE69: =SUM(AE62:AE68)/$E70 -> 10.410448 | AF69: =SUM(AF62:AF68)/$E70 -> 0.0207 | AG69: =SUM(AG62:AG68)/$E70 -> 0.91621542 | AH69: =SUM(AH62:AH68)/$E70 -> 0 | AI69: =SUM(AI62:AI68)/$E70 -> 2.1452736 | AJ69: =SUM(AJ62:AJ68)/$E70 -> 9.2244279 | ... BC69: =SUM(BC62:BC68)/$E70 -> 0
C70: Totals | D70: =SUM(D62:D68) -> 1 | E70: =SUM(E62:E68) -> 10050 | AC70: =SUM(AC62:AC68) -> 41450 | AD70: =SUM(AD62:AD68) -> 279139 | AE70: =SUM(AE62:AE68) -> 104625 | AF70: =SUM(AF62:AF68) -> 208.035 | AG70: =SUM(AG62:AG68) -> 9207.965 | AH70: =SUM(AH62:AH68) -> 0 | AI70: =SUM(AI62:AI68) -> 21560 | AJ70: =SUM(AJ62:AJ68) -> 92705.5 | ... BC70: =SUM(BC62:BC68) -> 0
B71: =B32 -> Brand 3 | C71: =$C$42 -> Program 1 | D71: =D62 -> 0.27 | E71: =D71*$D$32 -> 1350 | F71: 0 | G71: =$K$42*F71 -> 0 | H71: =IF($C$23>$E$42,($C$23-$E$42)*$G$42,0) -> 29.77 | I71: =IF($C$24>$F$42,($C$24-$F$42)*$H$42,0) -> 9.3 | J71: =$C$25*$I$42 -> 0.0207 | K71: =IF($E$42>$C$23,($E$42-$C$23)*$C$8,0) -> 0 | L71: =IF($F$42>$C$24,($F$42-$C$24)*$C$9,0) -> 0 | M71: 0 | N71: =$C$2+($E$42*$C$8)+($F$42*$C$9) -> 5.27 | O71: =$C$11*G71+$C$11*P71 -> 2.201835 | P71: =IF($C$23>$E$42,($C$23-$E$42)*$C$8,0) -> 14.6789 | Q71: =IF($C$24>$F$42,($C$24-$F$42)*$C$9,0) -> 3.72 | R71: =$C$25*($C$10*10000/1000000) -> 0.00414 | S71: 0 | T71: 0 | U71: 0 | V71: =F71-N71 -> -5.27 | W71: =H71-P71-O71 -> 12.889265 | X71: =I71-Q71 -> 5.58 | Y71: =J71-R71 -> 0.01656 | Z71: =K71-S71 -> 0 | AA71: =L71-T71 -> 0 | AB71: =M71-U71 -> 0 | AC71: =$E71*F71 -> 0 | AD71: =E71*H71 -> 40189.5 | AE71: =E71*I71 -> 12555 | AF71: =E71*J71 -> 27.945 | AG71: =E71*K71 -> 0 | AH71: =E71*L71 -> 0 | AI71: =E71*M71 -> 0 | AJ71: =$E71*N71 -> 7114.5 | AK71: =E71*O71 -> 2972.4772 | AL71: =E71*P71 -> 19816.515 | AM71: =E71*Q71 -> 5022 | AN71: =E71*R71 -> 5.589 | AO71: =E71*Z71 -> 0 | AP71: =E71*T71 -> 0 | AQ71: =E71*U71 -> 0 | AR71: =AC71-AJ71 -> -7114.5 | AS71: =AD71-AK71-AL71 -> 17400.508 | AT71: =AE71-AM71 -> 7533 | AU71: =AF71-AN71 -> 22.356 | AV71: =AG71-AO71 -> 0 | AW71: =AH71-AP71 -> 0 | AX71: =AI71-AQ71 -> 0 | AY71: =E71*$C$23 -> 309150 | AZ71: =E71*$C$24 -> 125550 | BA71: =E71*$C$25 -> 279.45 | BB71: =$K$42*AR71 -> 0 | BC71: =$L$42*AR71 -> 0
C72: =$C$43 -> Program 2 | D72: =D63 -> 0.4 | E72: =D72*$D$32 -> 2000 | F72: 0 | G72: =$K$43*F72 -> 0 | H72: =IF($C$23>$E$43,($C$23-$E$43)*$G$43,0) -> 38.93 | I72: =IF($C$24>$F$43,($C$24-$F$43)*$H$43,0) -> 12.09 | J72: =$C$25*$I$43 -> 0.0207 | K72: =IF($E$43>$C$23,($E$43-$C$23)*$C$8,0) -> 0 | L72: =IF($F$43>$C$24,($F$43-$C$24)*$C$9,0) -> 0 | M72: 4.2 | N72: =$C$2+($E$43*$C$8)+($F$43*$C$9) -> 5.27 | O72: =$C$11*G72+$C$11*P72 -> 2.201835 | P72: =IF($C$23>$E$43,($C$23-$E$43)*$C$8,0) -> 14.6789 | Q72: =IF($C$24>$F$43,($C$24-$F$43)*$C$9,0) -> 3.72 | R72: =$C$25*($C$10*10000/1000000) -> 0.00414 | S72: 0 | T72: 0 | U72: 0 | V72: =F72-N72 -> -5.27 | W72: =H72-P72-O72 -> 22.049265 | X72: =I72-Q72 -> 8.37 | Y72: =J72-R72 -> 0.01656 | Z72: =K72-S72 -> 0 | AA72: =L72-T72 -> 0 | AB72: =M72-U72 -> 4.2 | AC72: =$E72*F72 -> 0 | AD72: =E72*H72 -> 77860 | AE72: =E72*I72 -> 24180 | AF72: =E72*J72 -> 41.4 | AG72: =E72*K72 -> 0 | AH72: =E72*L72 -> 0 | AI72: =E72*M72 -> 8400 | AJ72: =$E72*N72 -> 10540 | AK72: =E72*O72 -> 4403.67 | AL72: =E72*P72 -> 29357.8 | AM72: =E72*Q72 -> 7440 | AN72: =E72*R72 -> 8.28 | AO72: =E72*Z72 -> 0 | AP72: =E72*T72 -> 0 | AQ72: =E72*U72 -> 0 | AR72: =AC72-AJ72 -> -10540 | AS72: =AD72-AK72-AL72 -> 44098.53 | AT72: =AE72-AM72 -> 16740 | AU72: =AF72-AN72 -> 33.12 | AV72: =AG72-AO72 -> 0 | AW72: =AH72-AP72 -> 0 | AX72: =AI72-AQ72 -> 8400 | AY72: =E72*$C$23 -> 458000 | AZ72: =E72*$C$24 -> 186000 | BA72: =E72*$C$25 -> 414 | BB72: =$K$43*AR72 -> 0 | BC72: =$L$43*AR72 -> 0
C73: =$C$44 -> Program 3 | D73: =D64 -> 0.17 | E73: =D73*$D$32 -> 850 | F73: 6 | G73: =$K$44*F73 -> 6 | H73: =IF($C$23>$E$44,($C$23-$E$44)*$G$44,0) -> 23.1 | I73: =IF($C$24>$F$44,($C$24-$F$44)*$H$44,0) -> 9.3 | J73: =$C$25*$I$44 -> 0.0207 | K73: =IF($E$44>$C$23,($E$44-$C$23)*$C$8,0) -> 0 | L73: =IF($F$44>$C$24,($F$44-$C$24)*$C$9,0) -> 0 | M73: 2.8 | N73: =$C$2+($E$44*$C$8)+($F$44*$C$9) -> 10.0775 | O73: =$C$11*G73+$C$11*P73 -> 2.38071 | P73: =IF($C$23>$E$44,($C$23-$E$44)*$C$8,0) -> 9.8714 | Q73: =IF($C$24>$F$44,($C$24-$F$44)*$C$9,0) -> 3.72 | R73: =$C$25*($C$10*10000/1000000) -> 0.00414 | S73: 0 | T73: 0 | U73: 0 | V73: =F73-N73 -> -4.0775 | W73: =H73-P73-O73 -> 10.84789 | X73: =I73-Q73 -> 5.58 | Y73: =J73-R73 -> 0.01656 | Z73: =K73-S73 -> 0 | AA73: =L73-T73 -> 0 | AB73: =M73-U73 -> 2.8 | AC73: =$E73*F73 -> 5100 | AD73: =E73*H73 -> 19635 | AE73: =E73*I73 -> 7905 | AF73: =E73*J73 -> 17.595 | AG73: =E73*K73 -> 0 | AH73: =E73*L73 -> 0 | AI73: =E73*M73 -> 2380 | AJ73: =$E73*N73 -> 8565.875 | AK73: =E73*O73 -> 2023.6035 | AL73: =E73*P73 -> 8390.69 | AM73: =E73*Q73 -> 3162 | AN73: =E73*R73 -> 3.519 | AO73: =E73*Z73 -> 0 | AP73: =E73*T73 -> 0 | AQ73: =E73*U73 -> 0 | AR73: =AC73-AJ73 -> -3465.875 | AS73: =AD73-AK73-AL73 -> 9220.7065 | AT73: =AE73-AM73 -> 4743 | AU73: =AF73-AN73 -> 14.076 | AV73: =AG73-AO73 -> 0 | AW73: =AH73-AP73 -> 0 | AX73: =AI73-AQ73 -> 2380 | AY73: =E73*$C$23 -> 194650 | AZ73: =E73*$C$24 -> 79050 | BA73: =E73*$C$25 -> 175.95 | BB73: =$K$44*AR73 -> -3465.875 | BC73: =$L$44*AR73 -> 0
C74: =$C$45 -> Program 4 | D74: =D65 -> 0.1 | E74: =D74*$D$32 -> 500 | F74: 15 | G74: =$K$45*F74 -> 15 | H74: =IF($C$23>$E$45,($C$23-$E$45)*$G$45,0) -> 3.77 | I74: =IF($C$24>$F$45,($C$24-$F$45)*$H$45,0) -> 9.3 | J74: =$C$25*$I$45 -> 0.0207 | K74: =IF($E$45>$C$23,($E$45-$C$23)*$C$8,0) -> 0 | L74: =IF($F$45>$C$24,($F$45-$C$24)*$C$9,0) -> 0 | M74: 0 | N74: =$C$2+($E$45*$C$8)+($F$45*$C$9) -> 18.09 | O74: =$C$11*G74+$C$11*P74 -> 2.528835 | P74: =IF($C$23>$E$45,($C$23-$E$45)*$C$8,0) -> 1.8589 | Q74: =IF($C$24>$F$45,($C$24-$F$45)*$C$9,0) -> 3.72 | R74: =$C$25*($C$10*10000/1000000) -> 0.00414 | S74: 0 | T74: 0 | U74: 0 | V74: =F74-N74 -> -3.09 | W74: =H74-P74-O74 -> -0.617735 | X74: =I74-Q74 -> 5.58 | Y74: =J74-R74 -> 0.01656 | Z74: =K74-S74 -> 0 | AA74: =L74-T74 -> 0 | AB74: =M74-U74 -> 0 | AC74: =$E74*F74 -> 7500 | AD74: =E74*H74 -> 1885 | AE74: =E74*I74 -> 4650 | AF74: =E74*J74 -> 10.35 | AG74: =E74*K74 -> 0 | AH74: =E74*L74 -> 0 | AI74: =E74*M74 -> 0 | AJ74: =$E74*N74 -> 9045 | AK74: =E74*O74 -> 1264.4175 | AL74: =E74*P74 -> 929.45 | AM74: =E74*Q74 -> 1860 | AN74: =E74*R74 -> 2.07 | AO74: =E74*Z74 -> 0 | AP74: =E74*T74 -> 0 | AQ74: =E74*U74 -> 0 | AR74: =AC74-AJ74 -> -1545 | AS74: =AD74-AK74-AL74 -> -308.8675 | AT74: =AE74-AM74 -> 2790 | AU74: =AF74-AN74 -> 8.28 | AV74: =AG74-AO74 -> 0 | AW74: =AH74-AP74 -> 0 | AX74: =AI74-AQ74 -> 0 | AY74: =E74*$C$23 -> 114500 | AZ74: =E74*$C$24 -> 46500 | BA74: =E74*$C$25 -> 103.5 | BB74: =$K$45*AR74 -> -1545 | BC74: =$L$45*AR74 -> 0
C75: =$C$46 -> Program 5 | D75: =D66 -> 0.05 | E75: =D75*$D$32 -> 250 | F75: 25 | G75: =$K$46*F75 -> 25 | H75: =IF($C$23>$E$46,($C$23-$E$46)*$G$46,0) -> 0 | I75: =IF($C$24>$F$46,($C$24-$F$46)*$H$46,0) -> 9.3 | J75: =$C$25*$I$46 -> 0.0207 | K75: =IF($E$46>$C$23,($E$46-$C$23)*$C$8,0) -> 14.1661 | L75: =IF($F$46>$C$24,($F$46-$C$24)*$C$9,0) -> 0 | M75: 0 | N75: =$C$2+($E$46*$C$8)+($F$46*$C$9) -> 34.115 | O75: =$C$11*G75+$C$11*P75 -> 3.75 | P75: =IF($C$23>$E$46,($C$23-$E$46)*$C$8,0) -> 0 | Q75: =IF($C$24>$F$46,($C$24-$F$46)*$C$9,0) -> 3.72 | R75: =$C$25*($C$10*10000/1000000) -> 0.00414 | S75: 0 | T75: 0 | U75: 0 | V75: =F75-N75 -> -9.115 | W75: =H75-P75-O75 -> -3.75 | X75: =I75-Q75 -> 5.58 | Y75: =J75-R75 -> 0.01656 | Z75: =K75-S75 -> 14.1661 | AA75: =L75-T75 -> 0 | AB75: =M75-U75 -> 0 | AC75: =$E75*F75 -> 6250 | AD75: =E75*H75 -> 0 | AE75: =E75*I75 -> 2325 | AF75: =E75*J75 -> 5.175 | AG75: =E75*K75 -> 3541.525 | AH75: =E75*L75 -> 0 | AI75: =E75*M75 -> 0 | AJ75: =$E75*N75 -> 8528.75 | AK75: =E75*O75 -> 937.5 | AL75: =E75*P75 -> 0 | AM75: =E75*Q75 -> 930 | AN75: =E75*R75 -> 1.035 | AO75: =E75*Z75 -> 3541.525 | AP75: =E75*T75 -> 0 | AQ75: =E75*U75 -> 0 | AR75: =AC75-AJ75 -> -2278.75 | AS75: =AD75-AK75-AL75 -> -937.5 | AT75: =AE75-AM75 -> 1395 | AU75: =AF75-AN75 -> 4.14 | AV75: =AG75-AO75 -> 0 | AW75: =AH75-AP75 -> 0 | AX75: =AI75-AQ75 -> 0 | AY75: =E75*$C$23 -> 57250 | AZ75: =E75*$C$24 -> 23250 | BA75: =E75*$C$25 -> 51.75 | BB75: =$K$46*AR75 -> -2278.75 | BC75: =$L$46*AR75 -> 0
C76: =$C$47 -> Program 6 | D76: =D67 -> 0.01 | E76: =D76*$D$30 -> 150 | F76: 25 | G76: =$K$46*F76 -> 25 | H76: =IF($C$23>$E$46,($C$23-$E$46)*$G$46,0) -> 0 | I76: =IF($C$24>$F$46,($C$24-$F$46)*$H$46,0) -> 9.3 | J76: =$C$25*$I$46 -> 0.0207 | K76: =IF($E$46>$C$23,($E$46-$C$23)*$C$8,0) -> 14.1661 | L76: =IF($F$46>$C$24,($F$46-$C$24)*$C$9,0) -> 0 | M76: 0 | N76: =$C$2+($E$46*$C$8)+($F$46*$C$9) -> 34.115 | O76: =$C$11*G76+$C$11*P76 -> 3.75 | P76: =IF($C$23>$E$46,($C$23-$E$46)*$C$8,0) -> 0 | Q76: =IF($C$24>$F$46,($C$24-$F$46)*$C$9,0) -> 3.72 | R76: =$C$25*($C$10*10000/1000000) -> 0.00414 | S76: 0 | T76: 0 | U76: 0 | V76: =F76-N76 -> -9.115 | W76: =H76-P76-O76 -> -3.75 | X76: =I76-Q76 -> 5.58 | Y76: =J76-R76 -> 0.01656 | Z76: =K76-S76 -> 14.1661 | AA76: =L76-T76 -> 0 | AB76: =M76-U76 -> 0 | AC76: =$E76*F76 -> 3750 | AD76: =E76*H76 -> 0 | AE76: =E76*I76 -> 1395 | AF76: =E76*J76 -> 3.105 | AG76: =E76*K76 -> 2124.915 | AH76: =E76*L76 -> 0 | AI76: =E76*M76 -> 0 | AJ76: =$E76*N76 -> 5117.25 | AK76: =E76*O76 -> 562.5 | AL76: =E76*P76 -> 0 | AM76: =E76*Q76 -> 558 | AN76: =E76*R76 -> 0.621 | AO76: =E76*Z76 -> 2124.915 | AP76: =E76*T76 -> 0 | AQ76: =E76*U76 -> 0 | AR76: =AC76-AJ76 -> -1367.25 | AS76: =AD76-AK76-AL76 -> -562.5 | AT76: =AE76-AM76 -> 837 | AU76: =AF76-AN76 -> 2.484 | AV76: =AG76-AO76 -> 0 | AW76: =AH76-AP76 -> 0 | AX76: =AI76-AQ76 -> 0 | AY76: =E76*$C$23 -> 34350 | AZ76: =E76*$C$24 -> 13950 | BA76: =E76*$C$25 -> 31.05 | BB76: =$K$46*AR76 -> -1367.25 | BC76: =$L$46*AR76 -> 0
C77: =$C$48 -> 0 | D77: =D68 -> 0 | E77: =D77*$D$32 -> 0 | F77: 35 | G77: =$K$48*F77 -> 35 | H77: =IF($C$23>$E$48,($C$23-$E$48)*$G$48,0) -> 0 | I77: =IF($C$24>$F$48,($C$24-$F$48)*$H$48,0) -> 0 | J77: =$C$25*$I$48 -> 0 | K77: =IF($E$48>$C$23,($E$48-$C$23)*$C$8,0) -> 0 | L77: =IF($F$48>$C$24,($F$48-$C$24)*$C$9,0) -> 0 | M77: 0 | N77: =$C$2+($E$48*$C$8)+($F$48*$C$9) -> 5.27 | O77: =$C$11*G77+$C$11*P77 -> 7.451835 | P77: =IF($C$23>$E$48,($C$23-$E$48)*$C$8,0) -> 14.6789 | Q77: =IF($C$24>$F$48,($C$24-$F$48)*$C$9,0) -> 3.72 | R77: =$C$25*($C$10*10000/1000000) -> 0.00414 | S77: 0 | T77: 0 | U77: 0 | V77: =F77-N77 -> 29.73 | W77: =H77-P77-O77 -> -22.130735 | X77: =I77-Q77 -> -3.72 | Y77: =J77-R77 -> -0.00414 | Z77: =K77-S77 -> 0 | AA77: =L77-T77 -> 0 | AB77: =M77-U77 -> 0 | AC77: =$E77*F77 -> 0 | AD77: =E77*H77 -> 0 | AE77: =E77*I77 -> 0 | AF77: =E77*J77 -> 0 | AG77: =E77*K77 -> 0 | AH77: =E77*L77 -> 0 | AI77: =E77*M77 -> 0 | AJ77: =$E77*N77 -> 0 | AK77: =E77*O77 -> 0 | AL77: =E77*P77 -> 0 | AM77: =E77*Q77 -> 0 | AN77: =E77*R77 -> 0 | AO77: =E77*Z77 -> 0 | AP77: =E77*T77 -> 0 | AQ77: =E77*U77 -> 0 | AR77: =AC77-AJ77 -> 0 | AS77: =AD77-AK77-AL77 -> 0 | AT77: =AE77-AM77 -> 0 | AU77: =AF77-AN77 -> 0 | AV77: =AG77-AO77 -> 0 | AW77: =AH77-AP77 -> 0 | AX77: =AI77-AQ77 -> 0 | AY77: =E77*$C$23 -> 0 | AZ77: =E77*$C$24 -> 0 | BA77: =E77*$C$25 -> 0 | BB77: =$K$48*AR77 -> 0 | BC77: =$L$48*AR77 -> 0
C78: Weighted Average | F78: =(($E71*F71)+($E72*F72)+($E73*F73)+($E74*F74)+($E75*F75)+($E77*F77))/($E79) -> 3.6960784 | G78: =(($E71*G71)+($E72*G72)+($E73*G73)+($E74*G74)+($E75*G75)+($E77*G77))/($E79) -> 3.6960784 | H78: =(($E71*H71)+($E72*H72)+($E73*H73)+($E74*H74)+($E75*H75)+($E77*H77))/($E79) -> 27.366569 | I78: =(($E71*I71)+($E72*I72)+($E73*I73)+($E74*I74)+($E75*I75)+($E77*I77))/($E79) -> 10.120588 | J78: =(($E71*J71)+($E72*J72)+($E73*J73)+($E74*J74)+($E75*J75)+($E77*J77))/($E79) -> 0.020091176 | K78: =(($E71*K71)+($E72*K72)+($E73*K73)+($E74*K74)+($E75*K75)+($E77*K77))/($E79) -> 0.69441667 | L78: =(($E71*L71)+($E72*L72)+($E73*L73)+($E74*L74)+($E75*L75)+($E77*L77))/($E79) -> 0 | M78: =(($E71*M71)+($E72*M72)+($E73*M73)+($E74*M74)+($E75*M75)+($E77*M77))/($E79) -> 2.1137255 | ... AB78: =(($E71*AB71)+($E72*AB72)+($E73*AB73)+($E74*AB74)+($E75*AB75)+($E77*AB77))/($E79) -> 2.1137255 | AC78: =SUM(AC71:AC77)/$E79 -> 4.4313725 | AD78: =SUM(AD71:AD77)/$E79 -> 27.366569 | AE78: =SUM(AE71:AE77)/$E79 -> 10.394118 | AF78: =SUM(AF71:AF77)/$E79 -> 0.0207 | AG78: =SUM(AG71:AG77)/$E79 -> 1.1110667 | AH78: =SUM(AH71:AH77)/$E79 -> 0 | AI78: =SUM(AI71:AI77)/$E79 -> 2.1137255 | AJ78: =SUM(AJ71:AJ77)/$E79 -> 9.5904657 | ... BC78: =SUM(BC71:BC77)/$E79 -> 0
C79: Totals | D79: =SUM(D71:D77) -> 1 | E79: =SUM(E71:E77) -> 5100 | AC79: =SUM(AC71:AC77) -> 22600 | AD79: =SUM(AD71:AD77) -> 139569.5 | AE79: =SUM(AE71:AE77) -> 53010 | AF79: =SUM(AF71:AF77) -> 105.57 | AG79: =SUM(AG71:AG77) -> 5666.44 | AH79: =SUM(AH71:AH77) -> 0 | AI79: =SUM(AI71:AI77) -> 10780 | AJ79: =SUM(AJ71:AJ77) -> 48911.375 | ... BC79: =SUM(BC71:BC77) -> 0
B80: =B33 -> Brand 4 | C80: =$C$42 -> Program 1 | D80: =D71 -> 0.27 | E80: =D80*$D$33 -> 1350 | F80: 0 | G80: =$K$42*F80 -> 0 | H80: =IF($C$23>$E$42,($C$23-$E$42)*$G$42,0) -> 29.77 | I80: =IF($C$24>$F$42,($C$24-$F$42)*$H$42,0) -> 9.3 | J80: =$C$25*$I$42 -> 0.0207 | K80: =IF($E$42>$C$23,($E$42-$C$23)*$C$8,0) -> 0 | L80: =IF($F$42>$C$24,($F$42-$C$24)*$C$9,0) -> 0 | M80: 0 | N80: =$C$2+($E$42*$C$8)+($F$42*$C$9) -> 5.27 | O80: =$C$11*G80+$C$11*P80 -> 2.201835 | P80: =IF($C$23>$E$42,($C$23-$E$42)*$C$8,0) -> 14.6789 | Q80: =IF($C$24>$F$42,($C$24-$F$42)*$C$9,0) -> 3.72 | R80: =$C$25*($C$10*10000/1000000) -> 0.00414 | S80: 0 | T80: 0 | U80: 0 | V80: =F80-N80 -> -5.27 | W80: =H80-P80-O80 -> 12.889265 | X80: =I80-Q80 -> 5.58 | Y80: =J80-R80 -> 0.01656 | Z80: =K80-S80 -> 0 | AA80: =L80-T80 -> 0 | AB80: =M80-U80 -> 0 | AC80: =$E80*F80 -> 0 | AD80: =E80*H80 -> 40189.5 | AE80: =E80*I80 -> 12555 | AF80: =E80*J80 -> 27.945 | AG80: =E80*K80 -> 0 | AH80: =E80*L80 -> 0 | AI80: =E80*M80 -> 0 | AJ80: =$E80*N80 -> 7114.5 | AK80: =E80*O80 -> 2972.4772 | AL80: =E80*P80 -> 19816.515 | AM80: =E80*Q80 -> 5022 | AN80: =E80*R80 -> 5.589 | AO80: =E80*Z80 -> 0 | AP80: =E80*T80 -> 0 | AQ80: =E80*U80 -> 0 | AR80: =AC80-AJ80 -> -7114.5 | AS80: =AD80-AK80-AL80 -> 17400.508 | AT80: =AE80-AM80 -> 7533 | AU80: =AF80-AN80 -> 22.356 | AV80: =AG80-AO80 -> 0 | AW80: =AH80-AP80 -> 0 | AX80: =AI80-AQ80 -> 0 | AY80: =E80*$C$23 -> 309150 | AZ80: =E80*$C$24 -> 125550 | BA80: =E80*$C$25 -> 279.45 | BB80: =$K$42*AR80 -> 0 | BC80: =$L$42*AR80 -> 0
C81: =$C$43 -> Program 2 | D81: =D72 -> 0.4 | E81: =D81*$D$33 -> 2000 | F81: 0 | G81: =$K$43*F81 -> 0 | H81: =IF($C$23>$E$43,($C$23-$E$43)*$G$43,0) -> 38.93 | I81: =IF($C$24>$F$43,($C$24-$F$43)*$H$43,0) -> 12.09 | J81: =$C$25*$I$43 -> 0.0207 | K81: =IF($E$43>$C$23,($E$43-$C$23)*$C$8,0) -> 0 | L81: =IF($F$43>$C$24,($F$43-$C$24)*$C$9,0) -> 0 | M81: 4.2 | N81: =$C$2+($E$43*$C$8)+($F$43*$C$9) -> 5.27 | O81: =$C$11*G81+$C$11*P81 -> 2.201835 | P81: =IF($C$23>$E$43,($C$23-$E$43)*$C$8,0) -> 14.6789 | Q81: =IF($C$24>$F$43,($C$24-$F$43)*$C$9,0) -> 3.72 | R81: =$C$25*($C$10*10000/1000000) -> 0.00414 | S81: 0 | T81: 0 | U81: 0 | V81: =F81-N81 -> -5.27 | W81: =H81-P81-O81 -> 22.049265 | X81: =I81-Q81 -> 8.37 | Y81: =J81-R81 -> 0.01656 | Z81: =K81-S81 -> 0 | AA81: =L81-T81 -> 0 | AB81: =M81-U81 -> 4.2 | AC81: =$E81*F81 -> 0 | AD81: =E81*H81 -> 77860 | AE81: =E81*I81 -> 24180 | AF81: =E81*J81 -> 41.4 | AG81: =E81*K81 -> 0 | AH81: =E81*L81 -> 0 | AI81: =E81*M81 -> 8400 | AJ81: =$E81*N81 -> 10540 | AK81: =E81*O81 -> 4403.67 | AL81: =E81*P81 -> 29357.8 | AM81: =E81*Q81 -> 7440 | AN81: =E81*R81 -> 8.28 | AO81: =E81*Z81 -> 0 | AP81: =E81*T81 -> 0 | AQ81: =E81*U81 -> 0 | AR81: =AC81-AJ81 -> -10540 | AS81: =AD81-AK81-AL81 -> 44098.53 | AT81: =AE81-AM81 -> 16740 | AU81: =AF81-AN81 -> 33.12 | AV81: =AG81-AO81 -> 0 | AW81: =AH81-AP81 -> 0 | AX81: =AI81-AQ81 -> 8400 | AY81: =E81*$C$23 -> 458000 | AZ81: =E81*$C$24 -> 186000 | BA81: =E81*$C$25 -> 414 | BB81: =$K$43*AR81 -> 0 | BC81: =$L$43*AR81 -> 0
C82: =$C$44 -> Program 3 | D82: =D73 -> 0.17 | E82: =D82*$D$33 -> 850 | F82: 6 | G82: =$K$44*F82 -> 6 | H82: =IF($C$23>$E$44,($C$23-$E$44)*$G$44,0) -> 23.1 | I82: =IF($C$24>$F$44,($C$24-$F$44)*$H$44,0) -> 9.3 | J82: =$C$25*$I$44 -> 0.0207 | K82: =IF($E$44>$C$23,($E$44-$C$23)*$C$8,0) -> 0 | L82: =IF($F$44>$C$24,($F$44-$C$24)*$C$9,0) -> 0 | M82: 2.8 | N82: =$C$2+($E$44*$C$8)+($F$44*$C$9) -> 10.0775 | O82: =$C$11*G82+$C$11*P82 -> 2.38071 | P82: =IF($C$23>$E$44,($C$23-$E$44)*$C$8,0) -> 9.8714 | Q82: =IF($C$24>$F$44,($C$24-$F$44)*$C$9,0) -> 3.72 | R82: =$C$25*($C$10*10000/1000000) -> 0.00414 | S82: 0 | T82: 0 | U82: 0 | V82: =F82-N82 -> -4.0775 | W82: =H82-P82-O82 -> 10.84789 | X82: =I82-Q82 -> 5.58 | Y82: =J82-R82 -> 0.01656 | Z82: =K82-S82 -> 0 | AA82: =L82-T82 -> 0 | AB82: =M82-U82 -> 2.8 | AC82: =$E82*F82 -> 5100 | AD82: =E82*H82 -> 19635 | AE82: =E82*I82 -> 7905 | AF82: =E82*J82 -> 17.595 | AG82: =E82*K82 -> 0 | AH82: =E82*L82 -> 0 | AI82: =E82*M82 -> 2380 | AJ82: =$E82*N82 -> 8565.875 | AK82: =E82*O82 -> 2023.6035 | AL82: =E82*P82 -> 8390.69 | AM82: =E82*Q82 -> 3162 | AN82: =E82*R82 -> 3.519 | AO82: =E82*Z82 -> 0 | AP82: =E82*T82 -> 0 | AQ82: =E82*U82 -> 0 | AR82: =AC82-AJ82 -> -3465.875 | AS82: =AD82-AK82-AL82 -> 9220.7065 | AT82: =AE82-AM82 -> 4743 | AU82: =AF82-AN82 -> 14.076 | AV82: =AG82-AO82 -> 0 | AW82: =AH82-AP82 -> 0 | AX82: =AI82-AQ82 -> 2380 | AY82: =E82*$C$23 -> 194650 | AZ82: =E82*$C$24 -> 79050 | BA82: =E82*$C$25 -> 175.95 | BB82: =$K$44*AR82 -> -3465.875 | BC82: =$L$44*AR82 -> 0
C83: =$C$45 -> Program 4 | D83: =D74 -> 0.1 | E83: =D83*$D$33 -> 500 | F83: 15 | G83: =$K$45*F83 -> 15 | H83: =IF($C$23>$E$45,($C$23-$E$45)*$G$45,0) -> 3.77 | I83: =IF($C$24>$F$45,($C$24-$F$45)*$H$45,0) -> 9.3 | J83: =$C$25*$I$45 -> 0.0207 | K83: =IF($E$45>$C$23,($E$45-$C$23)*$C$8,0) -> 0 | L83: =IF($F$45>$C$24,($F$45-$C$24)*$C$9,0) -> 0 | M83: 0 | N83: =$C$2+($E$45*$C$8)+($F$45*$C$9) -> 18.09 | O83: =$C$11*G83+$C$11*P83 -> 2.528835 | P83: =IF($C$23>$E$45,($C$23-$E$45)*$C$8,0) -> 1.8589 | Q83: =IF($C$24>$F$45,($C$24-$F$45)*$C$9,0) -> 3.72 | R83: =$C$25*($C$10*10000/1000000) -> 0.00414 | S83: 0 | T83: 0 | U83: 0 | V83: =F83-N83 -> -3.09 | W83: =H83-P83-O83 -> -0.617735 | X83: =I83-Q83 -> 5.58 | Y83: =J83-R83 -> 0.01656 | Z83: =K83-S83 -> 0 | AA83: =L83-T83 -> 0 | AB83: =M83-U83 -> 0 | AC83: =$E83*F83 -> 7500 | AD83: =E83*H83 -> 1885 | AE83: =E83*I83 -> 4650 | AF83: =E83*J83 -> 10.35 | AG83: =E83*K83 -> 0 | AH83: =E83*L83 -> 0 | AI83: =E83*M83 -> 0 | AJ83: =$E83*N83 -> 9045 | AK83: =E83*O83 -> 1264.4175 | AL83: =E83*P83 -> 929.45 | AM83: =E83*Q83 -> 1860 | AN83: =E83*R83 -> 2.07 | AO83: =E83*Z83 -> 0 | AP83: =E83*T83 -> 0 | AQ83: =E83*U83 -> 0 | AR83: =AC83-AJ83 -> -1545 | AS83: =AD83-AK83-AL83 -> -308.8675 | AT83: =AE83-AM83 -> 2790 | AU83: =AF83-AN83 -> 8.28 | AV83: =AG83-AO83 -> 0 | AW83: =AH83-AP83 -> 0 | AX83: =AI83-AQ83 -> 0 | AY83: =E83*$C$23 -> 114500 | AZ83: =E83*$C$24 -> 46500 | BA83: =E83*$C$25 -> 103.5 | BB83: =$K$45*AR83 -> -1545 | BC83: =$L$45*AR83 -> 0
C84: =$C$46 -> Program 5 | D84: =D75 -> 0.05 | E84: =D84*$D$33 -> 250 | F84: 25 | G84: =$K$46*F84 -> 25 | H84: =IF($C$23>$E$46,($C$23-$E$46)*$G$46,0) -> 0 | I84: =IF($C$24>$F$46,($C$24-$F$46)*$H$46,0) -> 9.3 | J84: =$C$25*$I$46 -> 0.0207 | K84: =IF($E$46>$C$23,($E$46-$C$23)*$C$8,0) -> 14.1661 | L84: =IF($F$46>$C$24,($F$46-$C$24)*$C$9,0) -> 0 | M84: 0 | N84: =$C$2+($E$46*$C$8)+($F$46*$C$9) -> 34.115 | O84: =$C$11*G84+$C$11*P84 -> 3.75 | P84: =IF($C$23>$E$46,($C$23-$E$46)*$C$8,0) -> 0 | Q84: =IF($C$24>$F$46,($C$24-$F$46)*$C$9,0) -> 3.72 | R84: =$C$25*($C$10*10000/1000000) -> 0.00414 | S84: 0 | T84: 0 | U84: 0 | V84: =F84-N84 -> -9.115 | W84: =H84-P84-O84 -> -3.75 | X84: =I84-Q84 -> 5.58 | Y84: =J84-R84 -> 0.01656 | Z84: =K84-S84 -> 14.1661 | AA84: =L84-T84 -> 0 | AB84: =M84-U84 -> 0 | AC84: =$E84*F84 -> 6250 | AD84: =E84*H84 -> 0 | AE84: =E84*I84 -> 2325 | AF84: =E84*J84 -> 5.175 | AG84: =E84*K84 -> 3541.525 | AH84: =E84*L84 -> 0 | AI84: =E84*M84 -> 0 | AJ84: =$E84*N84 -> 8528.75 | AK84: =E84*O84 -> 937.5 | AL84: =E84*P84 -> 0 | AM84: =E84*Q84 -> 930 | AN84: =E84*R84 -> 1.035 | AO84: =E84*Z84 -> 3541.525 | AP84: =E84*T84 -> 0 | AQ84: =E84*U84 -> 0 | AR84: =AC84-AJ84 -> -2278.75 | AS84: =AD84-AK84-AL84 -> -937.5 | AT84: =AE84-AM84 -> 1395 | AU84: =AF84-AN84 -> 4.14 | AV84: =AG84-AO84 -> 0 | AW84: =AH84-AP84 -> 0 | AX84: =AI84-AQ84 -> 0 | AY84: =E84*$C$23 -> 57250 | AZ84: =E84*$C$24 -> 23250 | BA84: =E84*$C$25 -> 51.75 | BB84: =$K$46*AR84 -> -2278.75 | BC84: =$L$46*AR84 -> 0
C85: =$C$47 -> Program 6 | D85: =D76 -> 0.01 | E85: =D85*$D$30 -> 150 | F85: 25 | G85: =$K$46*F85 -> 25 | H85: =IF($C$23>$E$46,($C$23-$E$46)*$G$46,0) -> 0 | I85: =IF($C$24>$F$46,($C$24-$F$46)*$H$46,0) -> 9.3 | J85: =$C$25*$I$46 -> 0.0207 | K85: =IF($E$46>$C$23,($E$46-$C$23)*$C$8,0) -> 14.1661 | L85: =IF($F$46>$C$24,($F$46-$C$24)*$C$9,0) -> 0 | M85: 0 | N85: =$C$2+($E$46*$C$8)+($F$46*$C$9) -> 34.115 | O85: =$C$11*G85+$C$11*P85 -> 3.75 | P85: =IF($C$23>$E$46,($C$23-$E$46)*$C$8,0) -> 0 | Q85: =IF($C$24>$F$46,($C$24-$F$46)*$C$9,0) -> 3.72 | R85: =$C$25*($C$10*10000/1000000) -> 0.00414 | S85: 0 | T85: 0 | U85: 0 | V85: =F85-N85 -> -9.115 | W85: =H85-P85-O85 -> -3.75 | X85: =I85-Q85 -> 5.58 | Y85: =J85-R85 -> 0.01656 | Z85: =K85-S85 -> 14.1661 | AA85: =L85-T85 -> 0 | AB85: =M85-U85 -> 0 | AC85: =$E85*F85 -> 3750 | AD85: =E85*H85 -> 0 | AE85: =E85*I85 -> 1395 | AF85: =E85*J85 -> 3.105 | AG85: =E85*K85 -> 2124.915 | AH85: =E85*L85 -> 0 | AI85: =E85*M85 -> 0 | AJ85: =$E85*N85 -> 5117.25 | AK85: =E85*O85 -> 562.5 | AL85: =E85*P85 -> 0 | AM85: =E85*Q85 -> 558 | AN85: =E85*R85 -> 0.621 | AO85: =E85*Z85 -> 2124.915 | AP85: =E85*T85 -> 0 | AQ85: =E85*U85 -> 0 | AR85: =AC85-AJ85 -> -1367.25 | AS85: =AD85-AK85-AL85 -> -562.5 | AT85: =AE85-AM85 -> 837 | AU85: =AF85-AN85 -> 2.484 | AV85: =AG85-AO85 -> 0 | AW85: =AH85-AP85 -> 0 | AX85: =AI85-AQ85 -> 0 | AY85: =E85*$C$23 -> 34350 | AZ85: =E85*$C$24 -> 13950 | BA85: =E85*$C$25 -> 31.05 | BB85: =$K$46*AR85 -> -1367.25 | BC85: =$L$46*AR85 -> 0
C86: =$C$48 -> 0 | D86: =D77 -> 0 | E86: =D86*$D$33 -> 0 | F86: 35 | G86: =$K$48*F86 -> 35 | H86: =IF($C$23>$E$48,($C$23-$E$48)*$G$48,0) -> 0 | I86: =IF($C$24>$F$48,($C$24-$F$48)*$H$48,0) -> 0 | J86: =$C$25*$I$48 -> 0 | K86: =IF($E$48>$C$23,($E$48-$C$23)*$C$8,0) -> 0 | L86: =IF($F$48>$C$24,($F$48-$C$24)*$C$9,0) -> 0 | M86: 0 | N86: =$C$2+($E$48*$C$8)+($F$48*$C$9) -> 5.27 | O86: =$C$11*G86+$C$11*P86 -> 7.451835 | P86: =IF($C$23>$E$48,($C$23-$E$48)*$C$8,0) -> 14.6789 | Q86: =IF($C$24>$F$48,($C$24-$F$48)*$C$9,0) -> 3.72 | R86: =$C$25*($C$10*10000/1000000) -> 0.00414 | S86: 0 | T86: 0 | U86: 0 | V86: =F86-N86 -> 29.73 | W86: =H86-P86-O86 -> -22.130735 | X86: =I86-Q86 -> -3.72 | Y86: =J86-R86 -> -0.00414 | Z86: =K86-S86 -> 0 | AA86: =L86-T86 -> 0 | AB86: =M86-U86 -> 0 | AC86: =$E86*F86 -> 0 | AD86: =E86*H86 -> 0 | AE86: =E86*I86 -> 0 | AF86: =E86*J86 -> 0 | AG86: =E86*K86 -> 0 | AH86: =E86*L86 -> 0 | AI86: =E86*M86 -> 0 | AJ86: =$E86*N86 -> 0 | AK86: =E86*O86 -> 0 | AL86: =E86*P86 -> 0 | AM86: =E86*Q86 -> 0 | AN86: =E86*R86 -> 0 | AO86: =E86*Z86 -> 0 | AP86: =E86*T86 -> 0 | AQ86: =E86*U86 -> 0 | AR86: =AC86-AJ86 -> 0 | AS86: =AD86-AK86-AL86 -> 0 | AT86: =AE86-AM86 -> 0 | AU86: =AF86-AN86 -> 0 | AV86: =AG86-AO86 -> 0 | AW86: =AH86-AP86 -> 0 | AX86: =AI86-AQ86 -> 0 | AY86: =E86*$C$23 -> 0 | AZ86: =E86*$C$24 -> 0 | BA86: =E86*$C$25 -> 0 | BB86: =$K$48*AR86 -> 0 | BC86: =$L$48*AR86 -> 0
C87: Weighted Average | F87: =(($E80*F80)+($E81*F81)+($E82*F82)+($E83*F83)+($E84*F84)+($E86*F86))/($E88) -> 3.6960784 | G87: =(($E80*G80)+($E81*G81)+($E82*G82)+($E83*G83)+($E84*G84)+($E86*G86))/($E88) -> 3.6960784 | H87: =(($E80*H80)+($E81*H81)+($E82*H82)+($E83*H83)+($E84*H84)+($E86*H86))/($E88) -> 27.366569 | I87: =(($E80*I80)+($E81*I81)+($E82*I82)+($E83*I83)+($E84*I84)+($E86*I86))/($E88) -> 10.120588 | J87: =(($E80*J80)+($E81*J81)+($E82*J82)+($E83*J83)+($E84*J84)+($E86*J86))/($E88) -> 0.020091176 | K87: =(($E80*K80)+($E81*K81)+($E82*K82)+($E83*K83)+($E84*K84)+($E86*K86))/($E88) -> 0.69441667 | L87: =(($E80*L80)+($E81*L81)+($E82*L82)+($E83*L83)+($E84*L84)+($E86*L86))/($E88) -> 0 | M87: =(($E80*M80)+($E81*M81)+($E82*M82)+($E83*M83)+($E84*M84)+($E86*M86))/($E88) -> 2.1137255 | ... AB87: =(($E80*AB80)+($E81*AB81)+($E82*AB82)+($E83*AB83)+($E84*AB84)+($E86*AB86))/($E88) -> 2.1137255 | AC87: =SUM(AC80:AC86)/$E88 -> 4.4313725 | AD87: =SUM(AD80:AD86)/$E88 -> 27.366569 | AE87: =SUM(AE80:AE86)/$E88 -> 10.394118 | AF87: =SUM(AF80:AF86)/$E88 -> 0.0207 | AG87: =SUM(AG80:AG86)/$E88 -> 1.1110667 | AH87: =SUM(AH80:AH86)/$E88 -> 0 | AI87: =SUM(AI80:AI86)/$E88 -> 2.1137255 | AJ87: =SUM(AJ80:AJ86)/$E88 -> 9.5904657 | ... BC87: =SUM(BC80:BC86)/$E88 -> 0
C88: Totals | D88: =SUM(D80:D86) -> 1 | E88: =SUM(E80:E86) -> 5100 | AC88: =SUM(AC80:AC86) -> 22600 | AD88: =SUM(AD80:AD86) -> 139569.5 | AE88: =SUM(AE80:AE86) -> 53010 | AF88: =SUM(AF80:AF86) -> 105.57 | AG88: =SUM(AG80:AG86) -> 5666.44 | AH88: =SUM(AH80:AH86) -> 0 | AI88: =SUM(AI80:AI86) -> 10780 | AJ88: =SUM(AJ80:AJ86) -> 48911.375 | ... BC88: =SUM(BC80:BC86) -> 0
B89: =B34 -> Brand 5 | C89: =$C$42 -> Program 1 | D89: =D80 -> 0.27 | E89: =D89*$D$34 -> 1350 | F89: 0 | G89: =$K$42*F89 -> 0 | H89: =IF($C$23>$E$42,($C$23-$E$42)*$G$42,0) -> 29.77 | I89: =IF($C$24>$F$42,($C$24-$F$42)*$H$42,0) -> 9.3 | J89: =$C$25*$I$42 -> 0.0207 | K89: =IF($E$42>$C$23,($E$42-$C$23)*$C$8,0) -> 0 | L89: =IF($F$42>$C$24,($F$42-$C$24)*$C$9,0) -> 0 | M89: 0 | N89: =$C$2+($E$42*$C$8)+($F$42*$C$9) -> 5.27 | O89: =$C$11*G89+$C$11*P89 -> 2.201835 | P89: =IF($C$23>$E$42,($C$23-$E$42)*$C$8,0) -> 14.6789 | Q89: =IF($C$24>$F$42,($C$24-$F$42)*$C$9,0) -> 3.72 | R89: =$C$25*($C$10*10000/1000000) -> 0.00414 | S89: 0 | T89: 0 | U89: 0 | V89: =F89-N89 -> -5.27 | W89: =H89-P89-O89 -> 12.889265 | X89: =I89-Q89 -> 5.58 | Y89: =J89-R89 -> 0.01656 | Z89: =K89-S89 -> 0 | AA89: =L89-T89 -> 0 | AB89: =M89-U89 -> 0 | AC89: =$E89*F89 -> 0 | AD89: =E89*H89 -> 40189.5 | AE89: =E89*I89 -> 12555 | AF89: =E89*J89 -> 27.945 | AG89: =E89*K89 -> 0 | AH89: =E89*L89 -> 0 | AI89: =E89*M89 -> 0 | AJ89: =$E89*N89 -> 7114.5 | AK89: =E89*O89 -> 2972.4772 | AL89: =E89*P89 -> 19816.515 | AM89: =E89*Q89 -> 5022 | AN89: =E89*R89 -> 5.589 | AO89: =E89*Z89 -> 0 | AP89: =E89*T89 -> 0 | AQ89: =E89*U89 -> 0 | AR89: =AC89-AJ89 -> -7114.5 | AS89: =AD89-AK89-AL89 -> 17400.508 | AT89: =AE89-AM89 -> 7533 | AU89: =AF89-AN89 -> 22.356 | AV89: =AG89-AO89 -> 0 | AW89: =AH89-AP89 -> 0 | AX89: =AI89-AQ89 -> 0 | AY89: =E89*$C$23 -> 309150 | AZ89: =E89*$C$24 -> 125550 | BA89: =E89*$C$25 -> 279.45 | BB89: =$K$42*AR89 -> 0 | BC89: =$L$42*AR89 -> 0
C90: =$C$43 -> Program 2 | D90: =D81 -> 0.4 | E90: =D90*$D$34 -> 2000 | F90: 0 | G90: =$K$43*F90 -> 0 | H90: =IF($C$23>$E$43,($C$23-$E$43)*$G$43,0) -> 38.93 | I90: =IF($C$24>$F$43,($C$24-$F$43)*$H$43,0) -> 12.09 | J90: =$C$25*$I$43 -> 0.0207 | K90: =IF($E$43>$C$23,($E$43-$C$23)*$C$8,0) -> 0 | L90: =IF($F$43>$C$24,($F$43-$C$24)*$C$9,0) -> 0 | M90: 4.2 | N90: =$C$2+($E$43*$C$8)+($F$43*$C$9) -> 5.27 | O90: =$C$11*G90+$C$11*P90 -> 2.201835 | P90: =IF($C$23>$E$43,($C$23-$E$43)*$C$8,0) -> 14.6789 | Q90: =IF($C$24>$F$43,($C$24-$F$43)*$C$9,0) -> 3.72 | R90: =$C$25*($C$10*10000/1000000) -> 0.00414 | S90: 0 | T90: 0 | U90: 0 | V90: =F90-N90 -> -5.27 | W90: =H90-P90-O90 -> 22.049265 | X90: =I90-Q90 -> 8.37 | Y90: =J90-R90 -> 0.01656 | Z90: =K90-S90 -> 0 | AA90: =L90-T90 -> 0 | AB90: =M90-U90 -> 4.2 | AC90: =$E90*F90 -> 0 | AD90: =E90*H90 -> 77860 | AE90: =E90*I90 -> 24180 | AF90: =E90*J90 -> 41.4 | AG90: =E90*K90 -> 0 | AH90: =E90*L90 -> 0 | AI90: =E90*M90 -> 8400 | AJ90: =$E90*N90 -> 10540 | AK90: =E90*O90 -> 4403.67 | AL90: =E90*P90 -> 29357.8 | AM90: =E90*Q90 -> 7440 | AN90: =E90*R90 -> 8.28 | AO90: =E90*Z90 -> 0 | AP90: =E90*T90 -> 0 | AQ90: =E90*U90 -> 0 | AR90: =AC90-AJ90 -> -10540 | AS90: =AD90-AK90-AL90 -> 44098.53 | AT90: =AE90-AM90 -> 16740 | AU90: =AF90-AN90 -> 33.12 | AV90: =AG90-AO90 -> 0 | AW90: =AH90-AP90 -> 0 | AX90: =AI90-AQ90 -> 8400 | AY90: =E90*$C$23 -> 458000 | AZ90: =E90*$C$24 -> 186000 | BA90: =E90*$C$25 -> 414 | BB90: =$K$43*AR90 -> 0 | BC90: =$L$43*AR90 -> 0
C91: =$C$44 -> Program 3 | D91: =D82 -> 0.17 | E91: =D91*$D$34 -> 850 | F91: 6 | G91: =$K$44*F91 -> 6 | H91: =IF($C$23>$E$44,($C$23-$E$44)*$G$44,0) -> 23.1 | I91: =IF($C$24>$F$44,($C$24-$F$44)*$H$44,0) -> 9.3 | J91: =$C$25*$I$44 -> 0.0207 | K91: =IF($E$44>$C$23,($E$44-$C$23)*$C$8,0) -> 0 | L91: =IF($F$44>$C$24,($F$44-$C$24)*$C$9,0) -> 0 | M91: 2.8 | N91: =$C$2+($E$44*$C$8)+($F$44*$C$9) -> 10.0775 | O91: =$C$11*G91+$C$11*P91 -> 2.38071 | P91: =IF($C$23>$E$44,($C$23-$E$44)*$C$8,0) -> 9.8714 | Q91: =IF($C$24>$F$44,($C$24-$F$44)*$C$9,0) -> 3.72 | R91: =$C$25*($C$10*10000/1000000) -> 0.00414 | S91: 0 | T91: 0 | U91: 0 | V91: =F91-N91 -> -4.0775 | W91: =H91-P91-O91 -> 10.84789 | X91: =I91-Q91 -> 5.58 | Y91: =J91-R91 -> 0.01656 | Z91: =K91-S91 -> 0 | AA91: =L91-T91 -> 0 | AB91: =M91-U91 -> 2.8 | AC91: =$E91*F91 -> 5100 | AD91: =E91*H91 -> 19635 | AE91: =E91*I91 -> 7905 | AF91: =E91*J91 -> 17.595 | AG91: =E91*K91 -> 0 | AH91: =E91*L91 -> 0 | AI91: =E91*M91 -> 2380 | AJ91: =$E91*N91 -> 8565.875 | AK91: =E91*O91 -> 2023.6035 | AL91: =E91*P91 -> 8390.69 | AM91: =E91*Q91 -> 3162 | AN91: =E91*R91 -> 3.519 | AO91: =E91*Z91 -> 0 | AP91: =E91*T91 -> 0 | AQ91: =E91*U91 -> 0 | AR91: =AC91-AJ91 -> -3465.875 | AS91: =AD91-AK91-AL91 -> 9220.7065 | AT91: =AE91-AM91 -> 4743 | AU91: =AF91-AN91 -> 14.076 | AV91: =AG91-AO91 -> 0 | AW91: =AH91-AP91 -> 0 | AX91: =AI91-AQ91 -> 2380 | AY91: =E91*$C$23 -> 194650 | AZ91: =E91*$C$24 -> 79050 | BA91: =E91*$C$25 -> 175.95 | BB91: =$K$44*AR91 -> -3465.875 | BC91: =$L$44*AR91 -> 0
C92: =$C$45 -> Program 4 | D92: =D83 -> 0.1 | E92: =D92*$D$34 -> 500 | F92: 15 | G92: =$K$45*F92 -> 15 | H92: =IF($C$23>$E$45,($C$23-$E$45)*$G$45,0) -> 3.77 | I92: =IF($C$24>$F$45,($C$24-$F$45)*$H$45,0) -> 9.3 | J92: =$C$25*$I$45 -> 0.0207 | K92: =IF($E$45>$C$23,($E$45-$C$23)*$C$8,0) -> 0 | L92: =IF($F$45>$C$24,($F$45-$C$24)*$C$9,0) -> 0 | M92: 0 | N92: =$C$2+($E$45*$C$8)+($F$45*$C$9) -> 18.09 | O92: =$C$11*G92+$C$11*P92 -> 2.528835 | P92: =IF($C$23>$E$45,($C$23-$E$45)*$C$8,0) -> 1.8589 | Q92: =IF($C$24>$F$45,($C$24-$F$45)*$C$9,0) -> 3.72 | R92: =$C$25*($C$10*10000/1000000) -> 0.00414 | S92: 0 | T92: 0 | U92: 0 | V92: =F92-N92 -> -3.09 | W92: =H92-P92-O92 -> -0.617735 | X92: =I92-Q92 -> 5.58 | Y92: =J92-R92 -> 0.01656 | Z92: =K92-S92 -> 0 | AA92: =L92-T92 -> 0 | AB92: =M92-U92 -> 0 | AC92: =$E92*F92 -> 7500 | AD92: =E92*H92 -> 1885 | AE92: =E92*I92 -> 4650 | AF92: =E92*J92 -> 10.35 | AG92: =E92*K92 -> 0 | AH92: =E92*L92 -> 0 | AI92: =E92*M92 -> 0 | AJ92: =$E92*N92 -> 9045 | AK92: =E92*O92 -> 1264.4175 | AL92: =E92*P92 -> 929.45 | AM92: =E92*Q92 -> 1860 | AN92: =E92*R92 -> 2.07 | AO92: =E92*Z92 -> 0 | AP92: =E92*T92 -> 0 | AQ92: =E92*U92 -> 0 | AR92: =AC92-AJ92 -> -1545 | AS92: =AD92-AK92-AL92 -> -308.8675 | AT92: =AE92-AM92 -> 2790 | AU92: =AF92-AN92 -> 8.28 | AV92: =AG92-AO92 -> 0 | AW92: =AH92-AP92 -> 0 | AX92: =AI92-AQ92 -> 0 | AY92: =E92*$C$23 -> 114500 | AZ92: =E92*$C$24 -> 46500 | BA92: =E92*$C$25 -> 103.5 | BB92: =$K$45*AR92 -> -1545 | BC92: =$L$45*AR92 -> 0
C93: =$C$46 -> Program 5 | D93: =D84 -> 0.05 | E93: =D93*$D$34 -> 250 | F93: 25 | G93: =$K$46*F93 -> 25 | H93: =IF($C$23>$E$46,($C$23-$E$46)*$G$46,0) -> 0 | I93: =IF($C$24>$F$46,($C$24-$F$46)*$H$46,0) -> 9.3 | J93: =$C$25*$I$46 -> 0.0207 | K93: =IF($E$46>$C$23,($E$46-$C$23)*$C$8,0) -> 14.1661 | L93: =IF($F$46>$C$24,($F$46-$C$24)*$C$9,0) -> 0 | M93: 0 | N93: =$C$2+($E$46*$C$8)+($F$46*$C$9) -> 34.115 | O93: =$C$11*G93+$C$11*P93 -> 3.75 | P93: =IF($C$23>$E$46,($C$23-$E$46)*$C$8,0) -> 0 | Q93: =IF($C$24>$F$46,($C$24-$F$46)*$C$9,0) -> 3.72 | R93: =$C$25*($C$10*10000/1000000) -> 0.00414 | S93: 0 | T93: 0 | U93: 0 | V93: =F93-N93 -> -9.115 | W93: =H93-P93-O93 -> -3.75 | X93: =I93-Q93 -> 5.58 | Y93: =J93-R93 -> 0.01656 | Z93: =K93-S93 -> 14.1661 | AA93: =L93-T93 -> 0 | AB93: =M93-U93 -> 0 | AC93: =$E93*F93 -> 6250 | AD93: =E93*H93 -> 0 | AE93: =E93*I93 -> 2325 | AF93: =E93*J93 -> 5.175 | AG93: =E93*K93 -> 3541.525 | AH93: =E93*L93 -> 0 | AI93: =E93*M93 -> 0 | AJ93: =$E93*N93 -> 8528.75 | AK93: =E93*O93 -> 937.5 | AL93: =E93*P93 -> 0 | AM93: =E93*Q93 -> 930 | AN93: =E93*R93 -> 1.035 | AO93: =E93*Z93 -> 3541.525 | AP93: =E93*T93 -> 0 | AQ93: =E93*U93 -> 0 | AR93: =AC93-AJ93 -> -2278.75 | AS93: =AD93-AK93-AL93 -> -937.5 | AT93: =AE93-AM93 -> 1395 | AU93: =AF93-AN93 -> 4.14 | AV93: =AG93-AO93 -> 0 | AW93: =AH93-AP93 -> 0 | AX93: =AI93-AQ93 -> 0 | AY93: =E93*$C$23 -> 57250 | AZ93: =E93*$C$24 -> 23250 | BA93: =E93*$C$25 -> 51.75 | BB93: =$K$46*AR93 -> -2278.75 | BC93: =$L$46*AR93 -> 0
C94: =$C$47 -> Program 6 | D94: =D85 -> 0.01 | E94: =D94*$D$30 -> 150 | F94: 25 | G94: =$K$46*F94 -> 25 | H94: =IF($C$23>$E$46,($C$23-$E$46)*$G$46,0) -> 0 | I94: =IF($C$24>$F$46,($C$24-$F$46)*$H$46,0) -> 9.3 | J94: =$C$25*$I$46 -> 0.0207 | K94: =IF($E$46>$C$23,($E$46-$C$23)*$C$8,0) -> 14.1661 | L94: =IF($F$46>$C$24,($F$46-$C$24)*$C$9,0) -> 0 | M94: 0 | N94: =$C$2+($E$46*$C$8)+($F$46*$C$9) -> 34.115 | O94: =$C$11*G94+$C$11*P94 -> 3.75 | P94: =IF($C$23>$E$46,($C$23-$E$46)*$C$8,0) -> 0 | Q94: =IF($C$24>$F$46,($C$24-$F$46)*$C$9,0) -> 3.72 | R94: =$C$25*($C$10*10000/1000000) -> 0.00414 | S94: 0 | T94: 0 | U94: 0 | V94: =F94-N94 -> -9.115 | W94: =H94-P94-O94 -> -3.75 | X94: =I94-Q94 -> 5.58 | Y94: =J94-R94 -> 0.01656 | Z94: =K94-S94 -> 14.1661 | AA94: =L94-T94 -> 0 | AB94: =M94-U94 -> 0 | AC94: =$E94*F94 -> 3750 | AD94: =E94*H94 -> 0 | AE94: =E94*I94 -> 1395 | AF94: =E94*J94 -> 3.105 | AG94: =E94*K94 -> 2124.915 | AH94: =E94*L94 -> 0 | AI94: =E94*M94 -> 0 | AJ94: =$E94*N94 -> 5117.25 | AK94: =E94*O94 -> 562.5 | AL94: =E94*P94 -> 0 | AM94: =E94*Q94 -> 558 | AN94: =E94*R94 -> 0.621 | AO94: =E94*Z94 -> 2124.915 | AP94: =E94*T94 -> 0 | AQ94: =E94*U94 -> 0 | AR94: =AC94-AJ94 -> -1367.25 | AS94: =AD94-AK94-AL94 -> -562.5 | AT94: =AE94-AM94 -> 837 | AU94: =AF94-AN94 -> 2.484 | AV94: =AG94-AO94 -> 0 | AW94: =AH94-AP94 -> 0 | AX94: =AI94-AQ94 -> 0 | AY94: =E94*$C$23 -> 34350 | AZ94: =E94*$C$24 -> 13950 | BA94: =E94*$C$25 -> 31.05 | BB94: =$K$46*AR94 -> -1367.25 | BC94: =$L$46*AR94 -> 0
C95: =$C$48 -> 0 | D95: =D86 -> 0 | E95: =D95*$D$34 -> 0 | F95: 35 | G95: =$K$48*F95 -> 35 | H95: =IF($C$23>$E$48,($C$23-$E$48)*$G$48,0) -> 0 | I95: =IF($C$24>$F$48,($C$24-$F$48)*$H$48,0) -> 0 | J95: =$C$25*$I$48 -> 0 | K95: =IF($E$48>$C$23,($E$48-$C$23)*$C$8,0) -> 0 | L95: =IF($F$48>$C$24,($F$48-$C$24)*$C$9,0) -> 0 | M95: 0 | N95: =$C$2+($E$48*$C$8)+($F$48*$C$9) -> 5.27 | O95: =$C$11*G95+$C$11*P95 -> 7.451835 | P95: =IF($C$23>$E$48,($C$23-$E$48)*$C$8,0) -> 14.6789 | Q95: =IF($C$24>$F$48,($C$24-$F$48)*$C$9,0) -> 3.72 | R95: =$C$25*($C$10*10000/1000000) -> 0.00414 | S95: 0 | T95: 0 | U95: 0 | V95: =F95-N95 -> 29.73 | W95: =H95-P95-O95 -> -22.130735 | X95: =I95-Q95 -> -3.72 | Y95: =J95-R95 -> -0.00414 | Z95: =K95-S95 -> 0 | AA95: =L95-T95 -> 0 | AB95: =M95-U95 -> 0 | AC95: =$E95*F95 -> 0 | AD95: =E95*H95 -> 0 | AE95: =E95*I95 -> 0 | AF95: =E95*J95 -> 0 | AG95: =E95*K95 -> 0 | AH95: =E95*L95 -> 0 | AI95: =E95*M95 -> 0 | AJ95: =$E95*N95 -> 0 | AK95: =E95*O95 -> 0 | AL95: =E95*P95 -> 0 | AM95: =E95*Q95 -> 0 | AN95: =E95*R95 -> 0 | AO95: =E95*Z95 -> 0 | AP95: =E95*T95 -> 0 | AQ95: =E95*U95 -> 0 | AR95: =AC95-AJ95 -> 0 | AS95: =AD95-AK95-AL95 -> 0 | AT95: =AE95-AM95 -> 0 | AU95: =AF95-AN95 -> 0 | AV95: =AG95-AO95 -> 0 | AW95: =AH95-AP95 -> 0 | AX95: =AI95-AQ95 -> 0 | AY95: =E95*$C$23 -> 0 | AZ95: =E95*$C$24 -> 0 | BA95: =E95*$C$25 -> 0 | BB95: =$K$48*AR95 -> 0 | BC95: =$L$48*AR95 -> 0
C96: Weighted Average | F96: =(($E89*F89)+($E90*F90)+($E91*F91)+($E92*F92)+($E93*F93)+($E95*F95))/($E97) -> 3.6960784 | G96: =(($E89*G89)+($E90*G90)+($E91*G91)+($E92*G92)+($E93*G93)+($E95*G95))/($E97) -> 3.6960784 | H96: =(($E89*H89)+($E90*H90)+($E91*H91)+($E92*H92)+($E93*H93)+($E95*H95))/($E97) -> 27.366569 | I96: =(($E89*I89)+($E90*I90)+($E91*I91)+($E92*I92)+($E93*I93)+($E95*I95))/($E97) -> 10.120588 | J96: =(($E89*J89)+($E90*J90)+($E91*J91)+($E92*J92)+($E93*J93)+($E95*J95))/($E97) -> 0.020091176 | K96: =(($E89*K89)+($E90*K90)+($E91*K91)+($E92*K92)+($E93*K93)+($E95*K95))/($E97) -> 0.69441667 | L96: =(($E89*L89)+($E90*L90)+($E91*L91)+($E92*L92)+($E93*L93)+($E95*L95))/($E97) -> 0 | M96: =(($E89*M89)+($E90*M90)+($E91*M91)+($E92*M92)+($E93*M93)+($E95*M95))/($E97) -> 2.1137255 | ... AB96: =(($E89*AB89)+($E90*AB90)+($E91*AB91)+($E92*AB92)+($E93*AB93)+($E95*AB95))/($E97) -> 2.1137255 | AC96: =SUM(AC89:AC95)/$E97 -> 4.4313725 | AD96: =SUM(AD89:AD95)/$E97 -> 27.366569 | AE96: =SUM(AE89:AE95)/$E97 -> 10.394118 | AF96: =SUM(AF89:AF95)/$E97 -> 0.0207 | AG96: =SUM(AG89:AG95)/$E97 -> 1.1110667 | AH96: =SUM(AH89:AH95)/$E97 -> 0 | AI96: =SUM(AI89:AI95)/$E97 -> 2.1137255 | AJ96: =SUM(AJ89:AJ95)/$E97 -> 9.5904657 | ... BC96: =SUM(BC89:BC95)/$E97 -> 0
C97: Totals | D97: =SUM(D89:D95) -> 1 | E97: =SUM(E89:E95) -> 5100 | AC97: =SUM(AC89:AC95) -> 22600 | AD97: =SUM(AD89:AD95) -> 139569.5 | AE97: =SUM(AE89:AE95) -> 53010 | AF97: =SUM(AF89:AF95) -> 105.57 | AG97: =SUM(AG89:AG95) -> 5666.44 | AH97: =SUM(AH89:AH95) -> 0 | AI97: =SUM(AI89:AI95) -> 10780 | AJ97: =SUM(AJ89:AJ95) -> 48911.375 | ... BC97: =SUM(BC89:BC95) -> 0
B98: =B35 -> Brand 6 | C98: =$C$42 -> Program 1 | D98: =D89 -> 0.27 | E98: =D98*$D$35 -> 1350 | F98: 0 | G98: =$K$42*F98 -> 0 | H98: =IF($C$23>$E$42,($C$23-$E$42)*$G$42,0) -> 29.77 | I98: =IF($C$24>$F$42,($C$24-$F$42)*$H$42,0) -> 9.3 | J98: =$C$25*$I$42 -> 0.0207 | K98: =IF($E$42>$C$23,($E$42-$C$23)*$C$8,0) -> 0 | L98: =IF($F$42>$C$24,($F$42-$C$24)*$C$9,0) -> 0 | M98: 0 | N98: =$C$2+($E$42*$C$8)+($F$42*$C$9) -> 5.27 | O98: =$C$11*G98+$C$11*P98 -> 2.201835 | P98: =IF($C$23>$E$42,($C$23-$E$42)*$C$8,0) -> 14.6789 | Q98: =IF($C$24>$F$42,($C$24-$F$42)*$C$9,0) -> 3.72 | R98: =$C$25*($C$10*10000/1000000) -> 0.00414 | S98: 0 | T98: 0 | U98: 0 | V98: =F98-N98 -> -5.27 | W98: =H98-P98-O98 -> 12.889265 | X98: =I98-Q98 -> 5.58 | Y98: =J98-R98 -> 0.01656 | Z98: =K98-S98 -> 0 | AA98: =L98-T98 -> 0 | AB98: =M98-U98 -> 0 | AC98: =$E98*F98 -> 0 | AD98: =E98*H98 -> 40189.5 | AE98: =E98*I98 -> 12555 | AF98: =E98*J98 -> 27.945 | AG98: =E98*K98 -> 0 | AH98: =E98*L98 -> 0 | AI98: =E98*M98 -> 0 | AJ98: =$E98*N98 -> 7114.5 | AK98: =E98*O98 -> 2972.4772 | AL98: =E98*P98 -> 19816.515 | AM98: =E98*Q98 -> 5022 | AN98: =E98*R98 -> 5.589 | AO98: =E98*Z98 -> 0 | AP98: =E98*T98 -> 0 | AQ98: =E98*U98 -> 0 | AR98: =AC98-AJ98 -> -7114.5 | AS98: =AD98-AK98-AL98 -> 17400.508 | AT98: =AE98-AM98 -> 7533 | AU98: =AF98-AN98 -> 22.356 | AV98: =AG98-AO98 -> 0 | AW98: =AH98-AP98 -> 0 | AX98: =AI98-AQ98 -> 0 | AY98: =E98*$C$23 -> 309150 | AZ98: =E98*$C$24 -> 125550 | BA98: =E98*$C$25 -> 279.45 | BB98: =$K$42*AR98 -> 0 | BC98: =$L$42*AR98 -> 0
C99: =$C$43 -> Program 2 | D99: =D90 -> 0.4 | E99: =D99*$D$35 -> 2000 | F99: 0 | G99: =$K$43*F99 -> 0 | H99: =IF($C$23>$E$43,($C$23-$E$43)*$G$43,0) -> 38.93 | I99: =IF($C$24>$F$43,($C$24-$F$43)*$H$43,0) -> 12.09 | J99: =$C$25*$I$43 -> 0.0207 | K99: =IF($E$43>$C$23,($E$43-$C$23)*$C$8,0) -> 0 | L99: =IF($F$43>$C$24,($F$43-$C$24)*$C$9,0) -> 0 | M99: 4.2 | N99: =$C$2+($E$43*$C$8)+($F$43*$C$9) -> 5.27 | O99: =$C$11*G99+$C$11*P99 -> 2.201835 | P99: =IF($C$23>$E$43,($C$23-$E$43)*$C$8,0) -> 14.6789 | Q99: =IF($C$24>$F$43,($C$24-$F$43)*$C$9,0) -> 3.72 | R99: =$C$25*($C$10*10000/1000000) -> 0.00414 | S99: 0 | T99: 0 | U99: 0 | V99: =F99-N99 -> -5.27 | W99: =H99-P99-O99 -> 22.049265 | X99: =I99-Q99 -> 8.37 | Y99: =J99-R99 -> 0.01656 | Z99: =K99-S99 -> 0 | AA99: =L99-T99 -> 0 | AB99: =M99-U99 -> 4.2 | AC99: =$E99*F99 -> 0 | AD99: =E99*H99 -> 77860 | AE99: =E99*I99 -> 24180 | AF99: =E99*J99 -> 41.4 | AG99: =E99*K99 -> 0 | AH99: =E99*L99 -> 0 | AI99: =E99*M99 -> 8400 | AJ99: =$E99*N99 -> 10540 | AK99: =E99*O99 -> 4403.67 | AL99: =E99*P99 -> 29357.8 | AM99: =E99*Q99 -> 7440 | AN99: =E99*R99 -> 8.28 | AO99: =E99*Z99 -> 0 | AP99: =E99*T99 -> 0 | AQ99: =E99*U99 -> 0 | AR99: =AC99-AJ99 -> -10540 | AS99: =AD99-AK99-AL99 -> 44098.53 | AT99: =AE99-AM99 -> 16740 | AU99: =AF99-AN99 -> 33.12 | AV99: =AG99-AO99 -> 0 | AW99: =AH99-AP99 -> 0 | AX99: =AI99-AQ99 -> 8400 | AY99: =E99*$C$23 -> 458000 | AZ99: =E99*$C$24 -> 186000 | BA99: =E99*$C$25 -> 414 | BB99: =$K$43*AR99 -> 0 | BC99: =$L$43*AR99 -> 0
C100: =$C$44 -> Program 3 | D100: =D91 -> 0.17 | E100: =D100*$D$35 -> 850 | F100: 6 | G100: =$K$44*F100 -> 6 | H100: =IF($C$23>$E$44,($C$23-$E$44)*$G$44,0) -> 23.1 | I100: =IF($C$24>$F$44,($C$24-$F$44)*$H$44,0) -> 9.3 | J100: =$C$25*$I$44 -> 0.0207 | K100: =IF($E$44>$C$23,($E$44-$C$23)*$C$8,0) -> 0 | L100: =IF($F$44>$C$24,($F$44-$C$24)*$C$9,0) -> 0 | M100: 2.8 | N100: =$C$2+($E$44*$C$8)+($F$44*$C$9) -> 10.0775 | O100: =$C$11*G100+$C$11*P100 -> 2.38071 | P100: =IF($C$23>$E$44,($C$23-$E$44)*$C$8,0) -> 9.8714 | Q100: =IF($C$24>$F$44,($C$24-$F$44)*$C$9,0) -> 3.72 | R100: =$C$25*($C$10*10000/1000000) -> 0.00414 | S100: 0 | T100: 0 | U100: 0 | V100: =F100-N100 -> -4.0775 | W100: =H100-P100-O100 -> 10.84789 | X100: =I100-Q100 -> 5.58 | Y100: =J100-R100 -> 0.01656 | Z100: =K100-S100 -> 0 | AA100: =L100-T100 -> 0 | AB100: =M100-U100 -> 2.8 | AC100: =$E100*F100 -> 5100 | AD100: =E100*H100 -> 19635 | AE100: =E100*I100 -> 7905 | AF100: =E100*J100 -> 17.595 | AG100: =E100*K100 -> 0 | AH100: =E100*L100 -> 0 | AI100: =E100*M100 -> 2380 | AJ100: =$E100*N100 -> 8565.875 | AK100: =E100*O100 -> 2023.6035 | AL100: =E100*P100 -> 8390.69 | AM100: =E100*Q100 -> 3162 | AN100: =E100*R100 -> 3.519 | AO100: =E100*Z100 -> 0 | AP100: =E100*T100 -> 0 | AQ100: =E100*U100 -> 0 | AR100: =AC100-AJ100 -> -3465.875 | AS100: =AD100-AK100-AL100 -> 9220.7065 | AT100: =AE100-AM100 -> 4743 | AU100: =AF100-AN100 -> 14.076 | AV100: =AG100-AO100 -> 0 | AW100: =AH100-AP100 -> 0 | AX100: =AI100-AQ100 -> 2380 | AY100: =E100*$C$23 -> 194650 | AZ100: =E100*$C$24 -> 79050 | BA100: =E100*$C$25 -> 175.95 | BB100: =$K$44*AR100 -> -3465.875 | BC100: =$L$44*AR100 -> 0
C101: =$C$45 -> Program 4 | D101: =D92 -> 0.1 | E101: =D101*$D$35 -> 500 | F101: 15 | G101: =$K$45*F101 -> 15 | H101: =IF($C$23>$E$45,($C$23-$E$45)*$G$45,0) -> 3.77 | I101: =IF($C$24>$F$45,($C$24-$F$45)*$H$45,0) -> 9.3 | J101: =$C$25*$I$45 -> 0.0207 | K101: =IF($E$45>$C$23,($E$45-$C$23)*$C$8,0) -> 0 | L101: =IF($F$45>$C$24,($F$45-$C$24)*$C$9,0) -> 0 | M101: 0 | N101: =$C$2+($E$45*$C$8)+($F$45*$C$9) -> 18.09 | O101: =$C$11*G101+$C$11*P101 -> 2.528835 | P101: =IF($C$23>$E$45,($C$23-$E$45)*$C$8,0) -> 1.8589 | Q101: =IF($C$24>$F$45,($C$24-$F$45)*$C$9,0) -> 3.72 | R101: =$C$25*($C$10*10000/1000000) -> 0.00414 | S101: 0 | T101: 0 | U101: 0 | V101: =F101-N101 -> -3.09 | W101: =H101-P101-O101 -> -0.617735 | X101: =I101-Q101 -> 5.58 | Y101: =J101-R101 -> 0.01656 | Z101: =K101-S101 -> 0 | AA101: =L101-T101 -> 0 | AB101: =M101-U101 -> 0 | AC101: =$E101*F101 -> 7500 | AD101: =E101*H101 -> 1885 | AE101: =E101*I101 -> 4650 | AF101: =E101*J101 -> 10.35 | AG101: =E101*K101 -> 0 | AH101: =E101*L101 -> 0 | AI101: =E101*M101 -> 0 | AJ101: =$E101*N101 -> 9045 | AK101: =E101*O101 -> 1264.4175 | AL101: =E101*P101 -> 929.45 | AM101: =E101*Q101 -> 1860 | AN101: =E101*R101 -> 2.07 | AO101: =E101*Z101 -> 0 | AP101: =E101*T101 -> 0 | AQ101: =E101*U101 -> 0 | AR101: =AC101-AJ101 -> -1545 | AS101: =AD101-AK101-AL101 -> -308.8675 | AT101: =AE101-AM101 -> 2790 | AU101: =AF101-AN101 -> 8.28 | AV101: =AG101-AO101 -> 0 | AW101: =AH101-AP101 -> 0 | AX101: =AI101-AQ101 -> 0 | AY101: =E101*$C$23 -> 114500 | AZ101: =E101*$C$24 -> 46500 | BA101: =E101*$C$25 -> 103.5 | BB101: =$K$45*AR101 -> -1545 | BC101: =$L$45*AR101 -> 0
C102: =$C$46 -> Program 5 | D102: =D93 -> 0.05 | E102: =D102*$D$35 -> 250 | F102: 25 | G102: =$K$46*F102 -> 25 | H102: =IF($C$23>$E$46,($C$23-$E$46)*$G$46,0) -> 0 | I102: =IF($C$24>$F$46,($C$24-$F$46)*$H$46,0) -> 9.3 | J102: =$C$25*$I$46 -> 0.0207 | K102: =IF($E$46>$C$23,($E$46-$C$23)*$C$8,0) -> 14.1661 | L102: =IF($F$46>$C$24,($F$46-$C$24)*$C$9,0) -> 0 | M102: 0 | N102: =$C$2+($E$46*$C$8)+($F$46*$C$9) -> 34.115 | O102: =$C$11*G102+$C$11*P102 -> 3.75 | P102: =IF($C$23>$E$46,($C$23-$E$46)*$C$8,0) -> 0 | Q102: =IF($C$24>$F$46,($C$24-$F$46)*$C$9,0) -> 3.72 | R102: =$C$25*($C$10*10000/1000000) -> 0.00414 | S102: 0 | T102: 0 | U102: 0 | V102: =F102-N102 -> -9.115 | W102: =H102-P102-O102 -> -3.75 | X102: =I102-Q102 -> 5.58 | Y102: =J102-R102 -> 0.01656 | Z102: =K102-S102 -> 14.1661 | AA102: =L102-T102 -> 0 | AB102: =M102-U102 -> 0 | AC102: =$E102*F102 -> 6250 | AD102: =E102*H102 -> 0 | AE102: =E102*I102 -> 2325 | AF102: =E102*J102 -> 5.175 | AG102: =E102*K102 -> 3541.525 | AH102: =E102*L102 -> 0 | AI102: =E102*M102 -> 0 | AJ102: =$E102*N102 -> 8528.75 | AK102: =E102*O102 -> 937.5 | AL102: =E102*P102 -> 0 | AM102: =E102*Q102 -> 930 | AN102: =E102*R102 -> 1.035 | AO102: =E102*Z102 -> 3541.525 | AP102: =E102*T102 -> 0 | AQ102: =E102*U102 -> 0 | AR102: =AC102-AJ102 -> -2278.75 | AS102: =AD102-AK102-AL102 -> -937.5 | AT102: =AE102-AM102 -> 1395 | AU102: =AF102-AN102 -> 4.14 | AV102: =AG102-AO102 -> 0 | AW102: =AH102-AP102 -> 0 | AX102: =AI102-AQ102 -> 0 | AY102: =E102*$C$23 -> 57250 | AZ102: =E102*$C$24 -> 23250 | BA102: =E102*$C$25 -> 51.75 | BB102: =$K$46*AR102 -> -2278.75 | BC102: =$L$46*AR102 -> 0
C103: =$C$47 -> Program 6 | D103: =D94 -> 0.01 | E103: =D103*$D$30 -> 150 | F103: 25 | G103: =$K$46*F103 -> 25 | H103: =IF($C$23>$E$46,($C$23-$E$46)*$G$46,0) -> 0 | I103: =IF($C$24>$F$46,($C$24-$F$46)*$H$46,0) -> 9.3 | J103: =$C$25*$I$46 -> 0.0207 | K103: =IF($E$46>$C$23,($E$46-$C$23)*$C$8,0) -> 14.1661 | L103: =IF($F$46>$C$24,($F$46-$C$24)*$C$9,0) -> 0 | M103: 0 | N103: =$C$2+($E$46*$C$8)+($F$46*$C$9) -> 34.115 | O103: =$C$11*G103+$C$11*P103 -> 3.75 | P103: =IF($C$23>$E$46,($C$23-$E$46)*$C$8,0) -> 0 | Q103: =IF($C$24>$F$46,($C$24-$F$46)*$C$9,0) -> 3.72 | R103: =$C$25*($C$10*10000/1000000) -> 0.00414 | S103: 0 | T103: 0 | U103: 0 | V103: =F103-N103 -> -9.115 | W103: =H103-P103-O103 -> -3.75 | X103: =I103-Q103 -> 5.58 | Y103: =J103-R103 -> 0.01656 | Z103: =K103-S103 -> 14.1661 | AA103: =L103-T103 -> 0 | AB103: =M103-U103 -> 0 | AC103: =$E103*F103 -> 3750 | AD103: =E103*H103 -> 0 | AE103: =E103*I103 -> 1395 | AF103: =E103*J103 -> 3.105 | AG103: =E103*K103 -> 2124.915 | AH103: =E103*L103 -> 0 | AI103: =E103*M103 -> 0 | AJ103: =$E103*N103 -> 5117.25 | AK103: =E103*O103 -> 562.5 | AL103: =E103*P103 -> 0 | AM103: =E103*Q103 -> 558 | AN103: =E103*R103 -> 0.621 | AO103: =E103*Z103 -> 2124.915 | AP103: =E103*T103 -> 0 | AQ103: =E103*U103 -> 0 | AR103: =AC103-AJ103 -> -1367.25 | AS103: =AD103-AK103-AL103 -> -562.5 | AT103: =AE103-AM103 -> 837 | AU103: =AF103-AN103 -> 2.484 | AV103: =AG103-AO103 -> 0 | AW103: =AH103-AP103 -> 0 | AX103: =AI103-AQ103 -> 0 | AY103: =E103*$C$23 -> 34350 | AZ103: =E103*$C$24 -> 13950 | BA103: =E103*$C$25 -> 31.05 | BB103: =$K$46*AR103 -> -1367.25 | BC103: =$L$46*AR103 -> 0
...

Sheet Entity 1 Outputs
A1: Revenues and Costs Based on Plan-Pricing | I1: Fixed Costs and Aggregated Per-Unit Costs | Q1: Itemized Costs | Y1: Loaded Per Unit Costs
A2: Entity 1 | I2: =A2 -> Entity 1 | Q2: =I2 -> Entity 1 | Y2: =Q2 -> Entity 1
A3: Customer Revenue and Costs | I3: =A3 -> Customer Revenue and Costs | Q3: =I3 -> Customer Revenue and Costs | Y3: =Q3 -> Customer Revenue and Costs
A4: Base Case Projection | I4: Base Case Projection | Q4: Base Case Projection | Y4: Base Case Projection
D5: ="Assumes a customer growth rate of "&(Inputs!E11-1)*100&"%" -> Assumes a customer growth rate of 50% | L5: ="Assumes a customer growth rate of "&(Inputs!E11-1)*100&"%" -> Assumes a customer growth rate of 50% | T5: =L5 -> Assumes a customer growth rate of 50% | AB5: =T5 -> Assumes a customer growth rate of 50%
A6: Customers | D6: Year 1 | E6: Year 2 | F6: Year 3 | G6: Year 4 | I6: =A6 -> Customers | L6: =D6 -> Year 1 | M6: =E6 -> Year 2 | N6: =F6 -> Year 3 | O6: =G6 -> Year 4 | Q6: =I6 -> Customers | T6: =L6 -> Year 1 | U6: =M6 -> Year 2 | V6: =N6 -> Year 3 | W6: =O6 -> Year 4 | Y6: =Q6 -> Customers | AB6: =T6 -> Year 1 | AC6: =U6 -> Year 2 | AD6: =V6 -> Year 3 | AE6: =W6 -> Year 4
A7: =Inputs!B30 -> Brand 1 | D7: =Inputs!D30 -> 15000 | E7: =D7*Inputs!$E$11-Inputs!$E$9*D7 -> 21750 | F7: =E7*Inputs!$E$11-Inputs!$E$9*E7 -> 31537.5 | G7: =F7*Inputs!$E$11-Inputs!$E$9*F7 -> 45729.375 | I7: =A7 -> Brand 1 | L7: =Inputs!D30 -> 15000 | M7: =L7*Inputs!$E$11-Inputs!$E$9*L7 -> 21750 | N7: =M7*Inputs!$E$11-Inputs!$E$9*M7 -> 31537.5 | O7: =N7*Inputs!$E$11-Inputs!$E$9*N7 -> 45729.375 | Q7: =I7 -> Brand 1 | T7: =L7 -> 15000 | U7: =M7 -> 21750 | V7: =N7 -> 31537.5 | W7: =O7 -> 45729.375 | Y7: =Q7 -> Brand 1 | AB7: =T7 -> 15000 | AC7: =U7 -> 21750 | AD7: =V7 -> 31537.5 | AE7: =W7 -> 45729.375
A8: =Inputs!B31 -> Brand 2 | D8: =Inputs!D31 -> 10000 | E8: =D8*Inputs!$E$11-Inputs!$E$9*D8 -> 14500 | F8: =E8*Inputs!$E$11-Inputs!$E$9*E8 -> 21025 | G8: =F8*Inputs!$E$11-Inputs!$E$9*F8 -> 30486.25 | I8: =A8 -> Brand 2 | L8: =Inputs!D31 -> 10000 | M8: =L8*Inputs!$E$11-Inputs!$E$9*L8 -> 14500 | N8: =M8*Inputs!$E$11-Inputs!$E$9*M8 -> 21025 | O8: =N8*Inputs!$E$11-Inputs!$E$9*N8 -> 30486.25 | Q8: =I8 -> Brand 2 | T8: =L8 -> 10000 | U8: =M8 -> 14500 | V8: =N8 -> 21025 | W8: =O8 -> 30486.25 | Y8: =Q8 -> Brand 2 | AB8: =T8 -> 10000 | AC8: =U8 -> 14500 | AD8: =V8 -> 21025 | AE8: =W8 -> 30486.25
A9: =Inputs!B32 -> Brand 3 | D9: =Inputs!D32 -> 5000 | E9: =D9*Inputs!$E$11-Inputs!$E$9*D9 -> 7250 | F9: =E9*Inputs!$E$11-Inputs!$E$9*E9 -> 10512.5 | G9: =F9*Inputs!$E$11-Inputs!$E$9*F9 -> 15243.125 | I9: =A9 -> Brand 3 | L9: =Inputs!D32 -> 5000 | M9: =L9*Inputs!$E$11-Inputs!$E$9*L9 -> 7250 | N9: =M9*Inputs!$E$11-Inputs!$E$9*M9 -> 10512.5 | O9: =N9*Inputs!$E$11-Inputs!$E$9*N9 -> 15243.125 | Q9: =I9 -> Brand 3 | T9: =L9 -> 5000 | U9: =M9 -> 7250 | V9: =N9 -> 10512.5 | W9: =O9 -> 15243.125 | Y9: =Q9 -> Brand 3 | AB9: =T9 -> 5000 | AC9: =U9 -> 7250 | AD9: =V9 -> 10512.5 | AE9: =W9 -> 15243.125
A10: =Inputs!B33 -> Brand 4 | D10: =Inputs!D33 -> 5000 | E10: =D10*Inputs!$E$11-Inputs!$E$9*D10 -> 7250 | F10: =E10*Inputs!$E$11-Inputs!$E$9*E10 -> 10512.5 | G10: =F10*Inputs!$E$11-Inputs!$E$9*F10 -> 15243.125 | I10: =A10 -> Brand 4 | L10: =Inputs!D33 -> 5000 | M10: =L10*Inputs!$E$11-Inputs!$E$9*L10 -> 7250 | N10: =M10*Inputs!$E$11-Inputs!$E$9*M10 -> 10512.5 | O10: =N10*Inputs!$E$11-Inputs!$E$9*N10 -> 15243.125 | Q10: =I10 -> Brand 4 | T10: =L10 -> 5000 | U10: =M10 -> 7250 | V10: =N10 -> 10512.5 | W10: =O10 -> 15243.125 | Y10: =Q10 -> Brand 4 | AB10: =T10 -> 5000 | AC10: =U10 -> 7250 | AD10: =V10 -> 10512.5 | AE10: =W10 -> 15243.125
A11: =Inputs!B34 -> Brand 5 | D11: =Inputs!D34 -> 5000 | E11: =D11*Inputs!$E$11-Inputs!$E$9*D11 -> 7250 | F11: =E11*Inputs!$E$11-Inputs!$E$9*E11 -> 10512.5 | G11: =F11*Inputs!$E$11-Inputs!$E$9*F11 -> 15243.125 | I11: =A11 -> Brand 5 | L11: =Inputs!D34 -> 5000 | M11: =L11*Inputs!$E$11-Inputs!$E$9*L11 -> 7250 | N11: =M11*Inputs!$E$11-Inputs!$E$9*M11 -> 10512.5 | O11: =N11*Inputs!$E$11-Inputs!$E$9*N11 -> 15243.125 | Q11: =I11 -> Brand 5 | T11: =L11 -> 5000 | U11: =M11 -> 7250 | V11: =N11 -> 10512.5 | W11: =O11 -> 15243.125 | Y11: =Q11 -> Brand 5 | AB11: =T11 -> 5000 | AC11: =U11 -> 7250 | AD11: =V11 -> 10512.5 | AE11: =W11 -> 15243.125
A12: =Inputs!B35 -> Brand 6 | D12: =Inputs!D35 -> 5000 | E12: =D12*Inputs!$E$11-Inputs!$E$9*D12 -> 7250 | F12: =E12*Inputs!$E$11-Inputs!$E$9*E12 -> 10512.5 | G12: =F12*Inputs!$E$11-Inputs!$E$9*F12 -> 15243.125 | I12: =A12 -> Brand 6 | L12: =Inputs!D35 -> 5000 | M12: =L12*Inputs!$E$11-Inputs!$E$9*L12 -> 7250 | N12: =M12*Inputs!$E$11-Inputs!$E$9*M12 -> 10512.5 | O12: =N12*Inputs!$E$11-Inputs!$E$9*N12 -> 15243.125 | Q12: =I12 -> Brand 6 | T12: =L12 -> 5000 | U12: =M12 -> 7250 | V12: =N12 -> 10512.5 | W12: =O12 -> 15243.125 | Y12: =Q12 -> Brand 6 | AB12: =T12 -> 5000 | AC12: =U12 -> 7250 | AD12: =V12 -> 10512.5 | AE12: =W12 -> 15243.125
A13: =Inputs!B36 -> Brand 7 | D13: =Inputs!D36 -> 869.18 | E13: =D13*Inputs!$E$11-Inputs!$E$9*D13 -> 1260.311 | F13: =E13*Inputs!$E$11-Inputs!$E$9*E13 -> 1827.4509 | G13: =F13*Inputs!$E$11-Inputs!$E$9*F13 -> 2649.8039 | I13: =A13 -> Brand 7 | L13: =Inputs!D36 -> 869.18 | M13: =L13*Inputs!$E$11-Inputs!$E$9*L13 -> 1260.311 | N13: =M13*Inputs!$E$11-Inputs!$E$9*M13 -> 1827.4509 | O13: =N13*Inputs!$E$11-Inputs!$E$9*N13 -> 2649.8039 | Q13: =I13 -> Brand 7 | T13: =L13 -> 869.18 | U13: =M13 -> 1260.311 | V13: =N13 -> 1827.4509 | W13: =O13 -> 2649.8039 | Y13: =Q13 -> Brand 7 | AB13: =T13 -> 869.18 | AC13: =U13 -> 1260.311 | AD13: =V13 -> 1827.4509 | AE13: =W13 -> 2649.8039
A14: =Inputs!B37 -> Brand 8 | D14: =Inputs!D37 -> 5000 | E14: =D14*Inputs!$E$11-Inputs!$E$9*D14 -> 7250 | F14: =E14*Inputs!$E$11-Inputs!$E$9*E14 -> 10512.5 | G14: =F14*Inputs!$E$11-Inputs!$E$9*F14 -> 15243.125 | I14: =A14 -> Brand 8 | L14: =Inputs!D37 -> 5000 | M14: =L14*Inputs!$E$11-Inputs!$E$9*L14 -> 7250 | N14: =M14*Inputs!$E$11-Inputs!$E$9*M14 -> 10512.5 | O14: =N14*Inputs!$E$11-Inputs!$E$9*N14 -> 15243.125 | Q14: =I14 -> Brand 8 | T14: =L14 -> 5000 | U14: =M14 -> 7250 | V14: =N14 -> 10512.5 | W14: =O14 -> 15243.125 | Y14: =Q14 -> Brand 8 | AB14: =T14 -> 5000 | AC14: =U14 -> 7250 | AD14: =V14 -> 10512.5 | AE14: =W14 -> 15243.125
A15: =Inputs!B38 -> Brand 9 | D15: =Inputs!D38 -> 5000 | E15: =D15*Inputs!$E$11-Inputs!$E$9*D15 -> 7250 | F15: =E15*Inputs!$E$11-Inputs!$E$9*E15 -> 10512.5 | G15: =F15*Inputs!$E$11-Inputs!$E$9*F15 -> 15243.125 | I15: =A15 -> Brand 9 | L15: =Inputs!D38 -> 5000 | M15: =L15*Inputs!$E$11-Inputs!$E$9*L15 -> 7250 | N15: =M15*Inputs!$E$11-Inputs!$E$9*M15 -> 10512.5 | O15: =N15*Inputs!$E$11-Inputs!$E$9*N15 -> 15243.125 | Q15: =I15 -> Brand 9 | T15: =L15 -> 5000 | U15: =M15 -> 7250 | V15: =N15 -> 10512.5 | W15: =O15 -> 15243.125 | Y15: =Q15 -> Brand 9 | AB15: =T15 -> 5000 | AC15: =U15 -> 7250 | AD15: =V15 -> 10512.5 | AE15: =W15 -> 15243.125
A16: Total Subscribers* | D16: =ROUNDUP(SUM(D7:D15),0) -> 55870 | E16: =SUM(E7:E15) -> 81010.311 | F16: =SUM(F7:F15) -> 117464.95 | G16: =SUM(G7:G15) -> 170324.18 | I16: Total Subscribers* | L16: =ROUNDUP(SUM(L7:L15),0) -> 55870 | M16: =SUM(M7:M15) -> 81010.311 | N16: =SUM(N7:N15) -> 117464.95 | O16: =SUM(O7:O15) -> 170324.18 | Q16: =I16 -> Total Subscribers* | T16: =SUM(T7:T15) -> 55869.18 | U16: =SUM(U7:U15) -> 81010.311 | V16: =SUM(V7:V15) -> 117464.95 | W16: =SUM(W7:W15) -> 170324.18 | Y16: =Q16 -> Total Subscribers* | AB16: =SUM(AB7:AB15) -> 55869.18 | AC16: =SUM(AC7:AC15) -> 81010.311 | AD16: =SUM(AD7:AD15) -> 117464.95 | AE16: =SUM(AE7:AE15) -> 170324.18
A18: Revenue | B18: NRC | C18: RC | D18: =D6 -> Year 1 | E18: =E6 -> Year 2 | F18: =F6 -> Year 3 | G18: =G6 -> Year 4 | I18: Revenue | J18: NRC | K18: RC | L18: =L6 -> Year 1 | M18: =M6 -> Year 2 | N18: =N6 -> Year 3 | O18: =O6 -> Year 4 | Q18: Revenue | R18: NRC | S18: RC | T18: =T6 -> Year 1 | U18: =U6 -> Year 2 | V18: =V6 -> Year 3 | W18: =W6 -> Year 4 | Y18: Revenue | Z18: NRC | AA18: RC | AB18: =AB6 -> Year 1 | AC18: =AC6 -> Year 2 | AD18: =AD6 -> Year 3 | AE18: =AE6 -> Year 4
A19: Program Fees Revenue** | C19: =Inputs!AC136 -> 4.3130022 | D19: =Inputs!$AC$135/Inputs!$D$39*D16*12 -> 2932564.7 | E19: =Inputs!$AC$135/Inputs!$D$39*E16*12 -> 4252156.5 | F19: =Inputs!$AC$135/Inputs!$D$39*F16*12 -> 6165626.9 | G19: =Inputs!$AC$135/Inputs!$D$39*G16*12 -> 8940159 | I19: =A19 -> Program Fees Revenue** | K19: =C19 -> 4.3130022 | L19: =D19 -> 2932564.7 | M19: =E19 -> 4252156.5 | N19: =F19 -> 6165626.9 | O19: =G19 -> 8940159 | Q19: =I19 -> Program Fees Revenue** | S19: =K19 -> 4.3130022 | T19: =L19 -> 2932564.7 | U19: =M19 -> 4252156.5 | V19: =N19 -> 6165626.9 | W19: =O19 -> 8940159 | Y19: =Q19 -> Program Fees Revenue** | AA19: =S19 -> 4.3130022 | AB19: =T19 -> 2932564.7 | AC19: =U19 -> 4252156.5 | AD19: =V19 -> 6165626.9 | AE19: =W19 -> 8940159
A20: Product 1 Overage Revenue** | C20: =Inputs!AD136 -> 27.52406 | D20: =Inputs!$AD$135/Inputs!$D$39*D16*12 -> 18714595 | E20: =Inputs!$AD$135/Inputs!$D$39*E16*12 -> 27135765 | F20: =Inputs!$AD$135/Inputs!$D$39*F16*12 -> 39346859 | G20: =Inputs!$AD$135/Inputs!$D$39*G16*12 -> 57052945 | I20: =A20 -> Product 1 Overage Revenue** | K20: =C20 -> 27.52406 | L20: =D20 -> 18714595 | M20: =E20 -> 27135765 | N20: =F20 -> 39346859 | O20: =G20 -> 57052945 | Q20: =I20 -> Product 1 Overage Revenue** | S20: =K20 -> 27.52406 | T20: =L20 -> 18714595 | U20: =M20 -> 27135765 | V20: =N20 -> 39346859 | W20: =O20 -> 57052945 | Y20: =Q20 -> Product 1 Overage Revenue** | AA20: =S20 -> 27.52406 | AB20: =T20 -> 18714595 | AC20: =U20 -> 27135765 | AD20: =V20 -> 39346859 | AE20: =W20 -> 57052945
A21: Product 2 Overage Revenue** | C21: =Inputs!AE136 -> 10.400414 | D21: =Inputs!$AE$135/Inputs!$D$39*D16*12 -> 7071614.3 | E21: =Inputs!$AE$135/Inputs!$D$39*E16*12 -> 10253690 | F21: =Inputs!$AE$135/Inputs!$D$39*F16*12 -> 14867851 | G21: =Inputs!$AE$135/Inputs!$D$39*G16*12 -> 21558384 | I21: =A21 -> Product 2 Overage Revenue** | K21: =C21 -> 10.400414 | L21: =D21 -> 7071614.3 | M21: =E21 -> 10253690 | N21: =F21 -> 14867851 | O21: =G21 -> 21558384 | Q21: =I21 -> Product 2 Overage Revenue** | S21: =K21 -> 10.400414 | T21: =L21 -> 7071614.3 | U21: =M21 -> 10253690 | V21: =N21 -> 14867851 | W21: =O21 -> 21558384 | Y21: =Q21 -> Product 2 Overage Revenue** | AA21: =S21 -> 10.400414 | AB21: =T21 -> 7071614.3 | AC21: =U21 -> 10253690 | AD21: =V21 -> 14867851 | AE21: =W21 -> 21558384
A22: Product 3 Usage Revenue** | C22: =Inputs!AF136 -> 0.0207 | D22: =Inputs!$AF$135/Inputs!$D$39*D16*12 -> 14074.672 | E22: =Inputs!$AF$135/Inputs!$D$39*E16*12 -> 20407.975 | F22: =Inputs!$AF$135/Inputs!$D$39*F16*12 -> 29591.563 | G22: =Inputs!$AF$135/Inputs!$D$39*G16*12 -> 42907.767 | I22: =A22 -> Product 3 Usage Revenue** | K22: =C22 -> 0.0207 | L22: =D22 -> 14074.672 | M22: =E22 -> 20407.975 | N22: =F22 -> 29591.563 | O22: =G22 -> 42907.767 | Q22: =I22 -> Product 3 Usage Revenue** | S22: =K22 -> 0.0207 | T22: =L22 -> 14074.672 | U22: =M22 -> 20407.975 | V22: =N22 -> 29591.563 | W22: =O22 -> 42907.767 | Y22: =Q22 -> Product 3 Usage Revenue** | AA22: =S22 -> 0.0207 | AB22: =T22 -> 14074.672 | AC22: =U22 -> 20407.975 | AD22: =V22 -> 29591.563 | AE22: =W22 -> 42907.767
A23: Product 1 "Breakage" Revenue | C23: =Inputs!AG136 -> 1.0359363 | D23: =Inputs!$AG$135/Inputs!$D$39*D16*12 -> 704370.19 | E23: =Inputs!$AG$135/Inputs!$D$39*E16*12 -> 1021321.8 | F23: =Inputs!$AG$135/Inputs!$D$39*F16*12 -> 1480916.6 | G23: =Inputs!$AG$135/Inputs!$D$39*G16*12 -> 2147329.1 | I23: =A23 -> Product 1 "Breakage" Revenue | K23: =C23 -> 1.0359363 | L23: =D23 -> 704370.19 | M23: =E23 -> 1021321.8 | N23: =F23 -> 1480916.6 | O23: =G23 -> 2147329.1 | Q23: =I23 -> Product 1 "Breakage" Revenue | S23: =K23 -> 1.0359363 | T23: =L23 -> 704370.19 | U23: =M23 -> 1021321.8 | V23: =N23 -> 1480916.6 | W23: =O23 -> 2147329.1 | Y23: =Q23 -> Product 1 "Breakage" Revenue | AA23: =S23 -> 1.0359363 | AB23: =T23 -> 704370.19 | AC23: =U23 -> 1021321.8 | AD23: =V23 -> 1480916.6 | AE23: =W23 -> 2147329.1
A24: Product 2 "Breakage" Revenue | C24: =Inputs!AH136 -> 0 | D24: =Inputs!$AH$135/Inputs!$D$39*D16*12 -> 0 | E24: =Inputs!$AH$135/Inputs!$D$39*E16*12 -> 0 | F24: =Inputs!$AH$135/Inputs!$D$39*F16*12 -> 0 | G24: =Inputs!$AH$135/Inputs!$D$39*G16*12 -> 0 | I24: =A24 -> Product 2 "Breakage" Revenue | K24: =C24 -> 0 | L24: =D24 -> 0 | M24: =E24 -> 0 | N24: =F24 -> 0 | O24: =G24 -> 0 | Q24: =I24 -> Product 2 "Breakage" Revenue | S24: =K24 -> 0 | T24: =L24 -> 0 | U24: =M24 -> 0 | V24: =N24 -> 0 | W24: =O24 -> 0 | Y24: =Q24 -> Product 2 "Breakage" Revenue | AA24: =S24 -> 0 | AB24: =T24 -> 0 | AC24: =U24 -> 0 | AD24: =V24 -> 0 | AE24: =W24 -> 0
A25: Daily Charge | C25: =Inputs!AI136 -> 2.1258898 | D25: =Inputs!$AI$135/Inputs!$D$39*D16*12 -> 1445468.6 | E25: =Inputs!$AI$135/Inputs!$D$39*E16*12 -> 2095898.8 | F25: =Inputs!$AI$135/Inputs!$D$39*F16*12 -> 3039053.2 | G25: =Inputs!$AI$135/Inputs!$D$39*G16*12 -> 4406627.2 | I25: =A25 -> Daily Charge | K25: =C25 -> 2.1258898 | L25: =D25 -> 1445468.6 | M25: =E25 -> 2095898.8 | N25: =F25 -> 3039053.2 | O25: =G25 -> 4406627.2 | Q25: =I25 -> Daily Charge | S25: =K25 -> 2.1258898 | T25: =L25 -> 1445468.6 | U25: =M25 -> 2095898.8 | V25: =N25 -> 3039053.2 | W25: =O25 -> 4406627.2 | Y25: =Q25 -> Daily Charge | AA25: =S25 -> 2.1258898 | AB25: =T25 -> 1445468.6 | AC25: =U25 -> 2095898.8 | AD25: =V25 -> 3039053.2 | AE25: =W25 -> 4406627.2
A26: Product 4 | C26: 0.1 | D26: 0 | E26: 0 | F26: 0 | G26: 0 | I26: =A26 -> Product 4 | K26: =C26 -> 0.1 | L26: =D26 -> 0 | M26: =E26 -> 0 | N26: =F26 -> 0 | O26: =G26 -> 0 | Q26: =I26 -> Product 4 | S26: =K26 -> 0.1 | T26: =L26 -> 0 | U26: =M26 -> 0 | V26: =N26 -> 0 | W26: =O26 -> 0 | Y26: =Q26 -> Product 4 | AA26: =S26 -> 0.1 | AB26: =T26 -> 0 | AC26: =U26 -> 0 | AD26: =V26 -> 0 | AE26: =W26 -> 0
A27: Customer Equipment Sales | B27: =Inputs!E15 -> 56.4 | D27: =D$69*$B$27 -> 3151068 | E27: =E69*$B$27 -> 3308554.3 | F27: =F69*$B$27 -> 4797476.5 | G27: =G69*$B$27 -> 6956276.1 | I27: =A27 -> Customer Equipment Sales | J27: =B27 -> 56.4 | L27: =D27 -> 3151068 | M27: =E27 -> 3308554.3 | N27: =F27 -> 4797476.5 | O27: =G27 -> 6956276.1 | Q27: =I27 -> Customer Equipment Sales | R27: =J27 -> 56.4 | T27: =L27 -> 3151068 | U27: =M27 -> 3308554.3 | V27: =N27 -> 4797476.5 | W27: =O27 -> 6956276.1 | Y27: =Q27 -> Customer Equipment Sales | Z27: =R27 -> 56.4 | AB27: =T27 -> 3151068 | AC27: =U27 -> 3308554.3 | AD27: =V27 -> 4797476.5 | AE27: =W27 -> 6956276.1
A28: Customer Activation Fees | B28: =Inputs!E14 -> 0 | D28: =D$69*$B$28 -> 0 | E28: =E$69*$B$28 -> 0 | F28: =F$69*$B$28 -> 0 | G28: =G$69*$B$28 -> 0 | I28: =A28 -> Customer Activation Fees | J28: =B28 -> 0 | L28: =D28 -> 0 | M28: =E28 -> 0 | N28: =F28 -> 0 | O28: =G28 -> 0 | Q28: =I28 -> Customer Activation Fees | R28: =J28 -> 0 | T28: =L28 -> 0 | U28: =M28 -> 0 | V28: =N28 -> 0 | W28: =O28 -> 0 | Y28: =Q28 -> Customer Activation Fees | Z28: =R28 -> 0 | AB28: =T28 -> 0 | AC28: =U28 -> 0 | AD28: =V28 -> 0 | AE28: =W28 -> 0
A29: Total Revenue | D29: =SUM(D19:D28) -> 34033756 | E29: =SUM(E19:E28) -> 48087794 | F29: =SUM(F19:F28) -> 69727374 | G29: =SUM(G19:G28) -> 1.0110463e+08 | I29: =A29 -> Total Revenue | L29: =D29 -> 34033756 | M29: =E29 -> 48087794 | N29: =F29 -> 69727374 | O29: =G29 -> 1.0110463e+08 | Q29: =I29 -> Total Revenue | T29: =L29 -> 34033756 | U29: =M29 -> 48087794 | V29: =N29 -> 69727374 | W29: =O29 -> 1.0110463e+08 | Y29: =Q29 -> Total Revenue | AB29: =T29 -> 34033756 | AC29: =U29 -> 48087794 | AD29: =V29 -> 69727374 | AE29: =W29 -> 1.0110463e+08
A31: Costs (Averaged per User) | B31: NRC | C31: RC | I31: Costs (Per Unit) | J31: NRC | K31: RC | Q31: Itemized Costs | R31: NRC | S31: RC | Y31: Fully Loaded Unit Costs | Z31: NRC | AA31: RC
A32: Branding License Fee | C32: 0.1 | D32: =$C$32*D66 -> 474566.85 | E32: =$C$32*E66 -> 688121.93 | F32: =$C$32*F66 -> 997776.8 | G32: =$C$32*G66 -> 1446776.4 | I32: =A32 -> Branding License Fee | K32: =C32 -> 0.1 | L32: =D32 -> 474566.85 | M32: =E32 -> 688121.93 | N32: =F32 -> 997776.8 | O32: =G32 -> 1446776.4 | Q32: =I32 -> Branding License Fee | S32: =K32 -> 0.1 | T32: =L32 -> 474566.85 | U32: =M32 -> 688121.93 | V32: =N32 -> 997776.8 | W32: =O32 -> 1446776.4 | Y32: =Q32 -> Branding License Fee | AA32: =S32 -> 0.1 | AB32: =T32 -> 474566.85 | AC32: =U32 -> 688121.93 | AD32: =V32 -> 997776.8 | AE32: =W32 -> 1446776.4
A33: Dealer Product 1 Commission | C33: 0.15 | D33: =$C$33*D75 -> 2638421.8 | E33: =$C$33*E75 -> 3825655.5 | F33: =$C$33*F75 -> 5547200.4 | G33: =$C$33*G75 -> 8043440.6 | I33: =A33 -> Dealer Product 1 Commission | K33: =C33 -> 0.15 | L33: =D33 -> 2638421.8 | M33: =E33 -> 3825655.5 | N33: =F33 -> 5547200.4 | O33: =G33 -> 8043440.6 | Q33: =I33 -> Dealer Product 1 Commission | S33: =K33 -> 0.15 | T33: =L33 -> 2638421.8 | U33: =M33 -> 3825655.5 | V33: =N33 -> 5547200.4 | W33: =O33 -> 8043440.6 | Y33: Loaded Product 1 Cost | AA33: =Inputs!V24 -> 0.096890481 | AB33: =$AA33*D77 -> 15086362 | AC33: =$AA33*E77 -> 21874904 | AD33: =$AA33*F77 -> 31718611 | AE33: =$AA33*G77 -> 45991986
A34: Cost of Subscriber Programs | C34: =Inputs!AJ136 -> 9.4493295 | D34: =$C$34*12*D16 -> 6335208.4 | E34: =$C$34*12*E16 -> 9185917.4 | F34: =$C$34*12*F16 -> 13319580 | G34: =$C$34*12*G16 -> 19313391 | I34: Subscriber Management | K34: =Inputs!C2 -> 5.27 | L34: =$K$34*12*L16 -> 3533218.8 | M34: =$K$34*12*M16 -> 5123092.1 | N34: =$K$34*12*N16 -> 7428483.5 | O34: =$K$34*12*O16 -> 10771301 | Q34: =Inputs!B3 -> Per service component 1 | S34: =Inputs!C3 -> 3.37 | T34: =$S$34*12*T16 -> 2259349.6 | U34: =$S$34*12*U16 -> 3276057 | V34: =$S$34*12*V16 -> 4750282.6 | W34: =$S$34*12*W16 -> 6887909.8 | Y34: Loaded Product 2 Cost | AA34: =Inputs!V25 -> 0.055845511 | AB34: =$AA34*D78 -> 3531336.9 | AC34: =$AA34*E78 -> 5120363.3 | AD34: =$AA34*F78 -> 7424526.8 | AE34: =$AA34*G78 -> 10765564
A35: Product 1 Overage Cost | C35: =Inputs!AL136 -> 11.535507 | D35: =$C$35*12*D16 -> 7733865.2 | E35: =$C$35*12*E16 -> 11213940 | F35: =$C$35*12*F16 -> 16260213 | G35: =$C$35*12*G16 -> 23577309 | I35: Product 1 Cost (per unit) | K35: =Inputs!C8 -> 0.0641 | L35: =$K35*Inputs!$C$23*12*L16*(L$16/$L$16) -> 9841321.7 | M35: =$K35*Inputs!$C$23*12*L16*(M$16/$L$16) -> 14269707 | N35: =$K35*Inputs!$C$23*12*L16*(N$16/$L$16) -> 20691075 | O35: =$K35*Inputs!$C$23*12*L16*(O$16/$L$16) -> 30002059 | Q35: =Inputs!B4 -> Per service component 2 | S35: =Inputs!C4 -> 0.35 | T35: =$S$35*12*T16 -> 234650.56 | U35: =$S$35*12*U16 -> 340243.31 | V35: =$S$35*12*V16 -> 493352.79 | W35: =$S$35*12*W16 -> 715361.55 | Y35: Loaded Product 3 Cost | AA35: =Inputs!V26 -> 0.035845511 | AB35: =$AA35*D79 -> 420.42817 | AC35: =$AA35*E79 -> 609.6119 | AD35: =$AA35*F79 -> 883.93726 | AE35: =$AA35*G79 -> 1281.709
A36: Product 2 Overage Cost | C36: =Inputs!AM136 -> 3.72 | D36: =$C$36*12*D16 -> 2494036.8 | E36: =$C$36*12*E16 -> 3616300.3 | F36: =$C$36*12*F16 -> 5243635.4 | G36: =$C$36*12*G16 -> 7603271.3 | I36: Product 2 Cost (per unit) | K36: =Inputs!C9 -> 0.04 | L36: =$K36*Inputs!$C$24*12*$L16*(L$16/$L$16) -> 2494036.8 | M36: =$K36*Inputs!$C$24*12*$L16*(M$16/$L$16) -> 3616300.3 | N36: =$K36*Inputs!$C$24*12*$L16*(N$16/$L$16) -> 5243635.4 | O36: =$K36*Inputs!$C$24*12*$L16*(O$16/$L$16) -> 7603271.3 | Q36: =Inputs!B5 -> Payment Type Cost | S36: =Inputs!C5 -> 0.58 | T36: =$S$36*12*T16 -> 388849.49 | U36: =$S$36*12*U16 -> 563831.76 | V36: =$S$36*12*V16 -> 817556.06 | W36: =$S$36*12*W16 -> 1185456.3 | Y36: =Q49 -> Total Costs | AB36: =SUM(AB32:AB35) -> 19092686 | AC36: =SUM(AC32:AC35) -> 27683999 | AD36: =SUM(AD32:AD35) -> 40141798 | AE36: =SUM(AE32:AE35) -> 58205608
A37: Product 3 Usage Cost | C37: =Inputs!AN136 -> 0.00414 | D37: =$C$37*12*D16 -> 2775.6216 | E37: =$C$37*12*E16 -> 4024.5923 | F37: =$C$37*12*F16 -> 5835.6588 | G37: =$C$37*12*G16 -> 8461.7052 | I37: Product 3 Cost (per unit) | K37: =Inputs!M23 -> 0.02 | L37: =$K37*Inputs!$C$25*12*$L16*(L$16/$L$16) -> 2775.6216 | M37: =$K37*Inputs!$C$25*12*$L16*(M$16/$L$16) -> 4024.5923 | N37: =$K37*Inputs!$C$25*12*$L16*(N$16/$L$16) -> 5835.6588 | O37: =$K37*Inputs!$C$25*12*$L16*(O$16/$L$16) -> 8461.7052 | Q37: =Inputs!B6 -> Customer Care | S37: =Inputs!C6 -> 0.97 | T37: =$S$37*12*T16 -> 650317.26 | U37: =$S$37*12*U16 -> 942960.02 | V37: =$S$37*12*V16 -> 1367292 | W37: =$S$37*12*W16 -> 1982573.4
A38: Product 1 "Breakage" Cost | C38: =Inputs!AO136 -> 1.0359363 | D38: =$C$38*12*D16 -> 694533.11 | E38: =$C$38*12*E16 -> 1007058.2 | F38: =$C$38*12*F16 -> 1460234.4 | G38: =$C$38*12*G16 -> 2117339.9 | I38: =A38 -> Product 1 "Breakage" Cost | K38: =C38 -> 1.0359363 | L38: =D38 -> 694533.11 | M38: =E38 -> 1007058.2 | N38: =F38 -> 1460234.4 | O38: =G38 -> 2117339.9 | Q38: =Inputs!B8 -> Product 1 | S38: =Inputs!C8 -> 0.0641 | T38: =$S38*D77 -> 9980710.2 | U38: =$S38*E77 -> 14471817 | V38: =$S38*F77 -> 20984135 | W38: =$S38*G77 -> 30426996 | Y38: =Q51 -> Total EBITDA | AB38: =AB29-AB36 -> 14941069 | AC38: =AC29-AC36 -> 20403795 | AD38: =AD29-AD36 -> 29585576 | AE38: =AE29-AE36 -> 42899020
A39: Product 2 "Breakage" Cost | C39: =Inputs!AP136 -> 0 | D39: =$C$39*12*D16 -> 0 | E39: =$C$39*12*E16 -> 0 | F39: =$C$39*12*F16 -> 0 | G39: =$C$39*12*G16 -> 0 | I39: =A39 -> Product 2 "Breakage" Cost | K39: =C39 -> 0 | L39: =D39 -> 0 | M39: =E39 -> 0 | N39: =F39 -> 0 | O39: =G39 -> 0 | Q39: =Inputs!B9 -> Product 2 | S39: =Inputs!C9 -> 0.04 | T39: =$S39*D78 -> 2529361.3 | U39: =$S39*E78 -> 3667520.1 | V39: =$S39*F78 -> 5317904.1 | W39: =$S39*G78 -> 7710961
A40: Daily Charge | C40: =Inputs!AQ136 -> 0 | D40: =$C$40*12*D16 -> 0 | E40: =$C$40*12*E16 -> 0 | F40: =$C$40*12*F16 -> 0 | G40: =$C$40*12*G16 -> 0 | I40: =A40 -> Daily Charge | K40: =C40 -> 0 | L40: =D40 -> 0 | M40: =E40 -> 0 | N40: =F40 -> 0 | O40: =G40 -> 0 | Q40: Product 3 (per 10k) | S40: =Inputs!M23 -> 0.02 | T40: =$S40*D79 -> 234.57786 | U40: =$S40*E79 -> 340.13291 | V40: =$S40*F79 -> 493.19272 | W40: =$S40*G79 -> 715.12944 | AB40: Monthly Figurres
A41: Product 4 | C41: 0 | D41: 0 | E41: 0 | F41: 0 | G41: 0 | I41: =A41 -> Product 4 | K41: =C41 -> 0 | L41: =D41 -> 0 | M41: =E41 -> 0 | N41: =F41 -> 0 | O41: =G41 -> 0 | Q41: =Inputs!B12 -> Monthly Flat Fee | S41: =Inputs!C12 -> 1450 | T41: =$S$41*12 -> 17400 | U41: =$S$41*12 -> 17400 | V41: =$S$41*12 -> 17400 | W41: =$S$41*12 -> 17400 | AB41: ARPU | AC41: AVG COST | AD41: Gross margin | AE41: Margin
A42: Customer Equipment Cost | B42: =Inputs!C19 -> 56.4 | D42: =$B$42*D69 -> 3151068 | E42: =$B$42*E69 -> 3308554.3 | F42: =$B$42*F69 -> 4797476.5 | G42: =$B$42*G69 -> 6956276.1 | I42: =A42 -> Customer Equipment Cost | J42: =B42 -> 56.4 | L42: =D42 -> 3151068 | M42: =E42 -> 3308554.3 | N42: =F42 -> 4797476.5 | O42: =G42 -> 6956276.1 | Q42: =Inputs!B14 -> Activation Cost 1 | R42: =Inputs!C14 -> 0 | T42: =$R$42*D$69 -> 0 | U42: =$R$42*E$69 -> 0 | V42: =$R$42*F$69 -> 0 | W42: =$R$42*G$69 -> 0 | AB42: =SUM(AB29:AE29)/SUM(AB16:AE16)/12 -> 49.637439 | AC42: =SUM(AB36:AE36)/SUM(AB16:AE16)/12 -> 28.477909 | AD42: =AB42-AC42 -> 21.15953 | AE42: =AD42/AB42 -> 0.42628166
A43: Other Activation Costs | B43: =Inputs!C13-Inputs!C19 -> 23.23 | D43: =$B$43*D69 -> 1297860.1 | E43: =$B$43*E69 -> 1362725.5 | F43: =$B$43*F69 -> 1975981.9 | G43: =$B$43*G69 -> 2865147 | I43: =A43 -> Other Activation Costs | J43: =B43 -> 23.23 | L43: =D43 -> 1297860.1 | M43: =E43 -> 1362725.5 | N43: =F43 -> 1975981.9 | O43: =G43 -> 2865147 | Q43: =Inputs!B15 -> Activation Cost 2 | R43: =Inputs!C15 -> 3 | T43: =$R$43*D$69 -> 167610 | U43: =$R$43*E$69 -> 175986.93 | V43: =$R$43*F$69 -> 255184.92 | W43: =$R$43*G$69 -> 370014.68
A44: Fixed Costs | I44: =A44 -> Fixed Costs | Q44: =Inputs!B16 -> Component | R44: =Inputs!C16 -> 3.81 | T44: =$R$44*D$69 -> 212864.7 | U44: =$R$44*E$69 -> 223503.4 | V44: =$R$44*F$69 -> 324084.85 | W44: =$R$44*G$69 -> 469918.65 | Y44: =Q57 -> *Subscriber number assumes a monthly customer churn rate of 5%
A45: Flat Fee Cost | C45: =Inputs!C12 -> 1450 | D45: =$C$45*12 -> 17400 | E45: =$C$45*12 -> 17400 | F45: =$C$45*12 -> 17400 | G45: =$C$45*12 -> 17400 | I45: =A45 -> Flat Fee Cost | K45: =C45 -> 1450 | L45: =D45 -> 17400 | M45: =E45 -> 17400 | N45: =F45 -> 17400 | O45: =G45 -> 17400 | Q45: =Inputs!B17 -> Dealer Commission | R45: =Inputs!C17 -> 15 | T45: =$R$45*D$69 -> 838050 | U45: =$R$45*E$69 -> 879934.67 | V45: =$R$45*F$69 -> 1275924.6 | W45: =$R$45*G$69 -> 1850073.4 | Y45: =Q58 -> ** Based on a weighted average projection of six rate plans and an underlying average consumption rate of 229 Product 1 minutes per user, 93 Product 2 messages per user and 0.207 units of data per user per month.
Q46: =Inputs!B18 -> Payment Processing | R46: =Inputs!C18 -> 1.42 | T46: =$R$46*D$69 -> 79335.4 | U46: =$R$46*E$69 -> 83300.482 | V46: =$R$46*F$69 -> 120787.53 | W46: =$R$46*G$69 -> 175140.28
A47: Total Costs | D47: =SUM(D31:D46) -> 24839736 | E47: =SUM(E31:E42,E44:E46) -> 32866972 | F47: =SUM(F31:F42,F44:F46) -> 47649352 | G47: =SUM(G31:G42,G44:G46) -> 69083666 | I47: Total Costs | L47: =SUM(L33:L44,L45:L46) -> 23670636 | M47: =SUM(M33:M44,M45:M46) -> 32534518 | N47: =SUM(N33:N44,N45:N46) -> 47167323 | O47: =SUM(O33:O44,O45:O46) -> 68384697 | Q47: =Inputs!B19 -> Customer Equipment | R47: =Inputs!C19 -> 56.4 | T47: =$R$47*D$69 -> 3151068 | U47: =$R$47*E$69 -> 3308554.3 | V47: =$R$47*F$69 -> 4797476.5 | W47: =$R$47*G$69 -> 6956276.1
A49: Total EBITDA | D49: =D29-D47 -> 9194019.8 | E49: =E29-E47 -> 15220822 | F49: =F29-F47 -> 22078022 | G49: =G29-G47 -> 32020962 | I49: Total EBITDA | L49: =L29-L47 -> 10363120 | M49: =M29-M47 -> 15553277 | N49: =N29-N47 -> 22560051 | O49: =O29-O47 -> 32719931 | Q49: =I47 -> Total Costs | T49: =SUM(T32:T48) -> 23622790 | U49: =SUM(U32:U46) -> 29156673 | V49: =SUM(V32:V46) -> 42269375 | W49: =SUM(W32:W46) -> 61282737
D51: Monthly Figures | L51: Monthly Figures | Q51: =I49 -> Total EBITDA | T51: =T29-T49 -> 10410966 | U51: =U29-U49 -> 18931122 | V51: =V29-V49 -> 27457999 | W51: =W29-W49 -> 39821891
D52: ARPU | E52: AVG COST | F52: Gross margin | G52: Margin | L52: ARPU | M52: AVG COST | N52: Gross margin | O52: Margin
D53: =SUM(D29:G29)/SUM(D16:G16)/12 -> 49.637343 | E53: =SUM(D47:G47)/SUM(D16:G16)/12 -> 34.230492 | F53: =D53-E53 -> 15.406851 | G53: =F53/D53 -> 0.31038831 | L53: =SUM(L29:O29)/SUM(L16:O16)/12 -> 49.637343 | M53: =SUM(L47:O47)/SUM(L16:O16)/12 -> 33.704092 | N53: =L53-M53 -> 15.933251 | O53: =N53/L53 -> 0.32099323 | T53: Monthly Figurres
T54: ARPU | U54: AVG COST | V54: Gross margin | W54: Margin
A55: ="*Subscriber number assumes a monthly customer churn rate of "&100*Inputs!E9&"%" -> *Subscriber number assumes a monthly customer churn rate of 5% | I55: ="*Subscriber number assumes a monthly customer churn rate of "&100*Inputs!E9&"%" -> *Subscriber number assumes a monthly customer churn rate of 5% | T55: =SUM(T29:W29)/SUM(T16:W16)/12 -> 49.637439 | U55: =SUM(T49:W49)/SUM(T16:W16)/12 -> 30.677169 | V55: =T55-U55 -> 18.960269 | W55: =V55/T55 -> 0.38197518
A56: ="** Based on a weighted average projection of six rate plans and an underlying average consumption rate of "&Inputs!C23&" Product 1 minutes per user, "&Inputs!C24&" Product 2 messages per user and "&Inputs!C25&" units of data per user per month." -> ** Based on a weighted average projection of six rate plans and an underlying average consumption rate of 229 Product 1 minutes per user, 93 Product 2 messages per user and 0.207 units of data per user per month. | I56: ="** Based on a weighted average projection of six rate plans and an underlying average consumption rate of "&Inputs!C23&" Product 1 minutes per user, "&Inputs!C24&" Product 2 messages per user and "&Inputs!C25&" units of data per user per month." -> ** Based on a weighted average projection of six rate plans and an underlying average consumption rate of 229 Product 1 minutes per user, 93 Product 2 messages per user and 0.207 units of data per user per month.
Q57: =I55 -> *Subscriber number assumes a monthly customer churn rate of 5%
Q58: =I56 -> ** Based on a weighted average projection of six rate plans and an underlying average consumption rate of 229 Product 1 minutes per user, 93 Product 2 messages per user and 0.207 units of data per user per month.
A60: Average Revenue from Product 1 Product 1 | B60: =SUM(D19:G20)/SUM(D16:G16)/12 -> 32.28799 | I60: =SUM(D29:G29) -> 2.5295355e+08 | J60: Chart 1 Revenue | M60: Chart 1 Margin | N60: =G53 -> 0.31038831
I61: =SUM(L29:O29) -> 2.5295355e+08 | J61: Chart 2 Revenue | M61: Chart 2 Margin | N61: =O53 -> 0.32099323
I62: =SUM(T29:W29) -> 2.5295355e+08 | J62: Chart 3 Revenue | M62: Chart 3 Margin | N62: =W55 -> 0.38197518
I63: =SUM(AB29:AE29) -> 2.5295355e+08 | J63: Chart 4 Revenue | M63: Chart 4 Margin | N63: =AE42 -> 0.42628166
I64: =MAX(I60:I63)-MIN(I60:I63) -> 0 | J64: Revenue Range | M64: Margin Range | N64: =MAX(N60:N63)-MIN(N60:N63) -> 0.11589335
I65: =AVERAGE(I60:I63) -> 2.5295355e+08 | J65: Average Revenue | M65: Average Margin | N65: =AVERAGE(N60:N63) -> 0.3599096
A66: Brand 1 Annual Revenue from Product 1 | D66: =12*(Inputs!$BB$61+Inputs!$AD$61)/Inputs!$E$61*L7 -> 4745668.5 | E66: =12*(Inputs!$BB$61+Inputs!$AD$61)/Inputs!$E$61*M7 -> 6881219.3 | F66: =12*(Inputs!$BB$61+Inputs!$AD$61)/Inputs!$E$61*N7 -> 9977768 | G66: =12*(Inputs!$BB$61+Inputs!$AD$61)/Inputs!$E$61*O7 -> 14467764 | I66: =MAX(I60:I63)/I65-1 -> 0 | J66: Max to Average % | M66: Max to Average % | N66: =MAX(N60:N63)/N65-1 -> 0.18441316
A67: Sub Growth | D67: =L16-K16 -> 55870 | E67: =M16-L16 -> 25140.311 | F67: =N16-M16 -> 36454.64 | G67: =O16-N16 -> 52859.228 | I67: =MIN(I60:I63)/I65-1 -> 0 | J67: Min to Average % | M67: Min to Average % | N67: =MIN(N60:N63)/N65-1 -> -0.13759368
A68: Sub Churn | D68: =ROUNDUP(K16*Inputs!$E$9*12,0) -> 0 | E68: =ROUNDUP(L16*Inputs!$E$9*12,0) -> 33522 | F68: =ROUNDUP(M16*Inputs!$E$9*12,0) -> 48607 | G68: =ROUNDUP(N16*Inputs!$E$9*12,0) -> 70479 | I68: =I64/I65 -> 0 | J68: Range | M68: Range | N68: =N64/N65 -> 0.32200684
A69: Total New Subs | D69: =D67+D68 -> 55870 | E69: =E67+E68 -> 58662.311 | F69: =F67+F68 -> 85061.64 | G69: =G67+G68 -> 123338.23
I70: =SUM(D47:G47) -> 1.7443973e+08 | J70: Chart 1 Cost | M70: Chart 1 Gr. Margin | N70: =F53 -> 15.406851
B71: AVG Competitor | C71: Us | D71: Difference | I71: =SUM(L47:O47) -> 1.7175717e+08 | J71: Chart 2 Cost | M71: Chart 2 Gr. Margin | N71: =N53 -> 15.933251
A72: ARPU | B72: 53 | C72: =L53 -> 49.637343 | D72: =C72-B72 -> -3.362657 | I72: =SUM(T49:W49) -> 1.5633157e+08 | J72: Chart 3 Cost | M72: Chart 3 Gr. Margin | N72: =V55 -> 18.960269
A73: Rev Pecentage for Products 2 & 3 | B73: 0.2 | C73: =(SUM(D21:G21)+SUM(D22:G22))/SUM(L29:O29) -> 0.21291862 | D73: =ABS(B73-C73) -> 0.01291862 | I73: =SUM(AB36:AE36) -> 1.4512409e+08 | J73: Chart 4 Cost | M73: Chart 4 Gr. Margin | N73: =AD42 -> 21.15953
I74: =MAX(I70:I73)-MIN(I70:I73) -> 29315635 | J74: Cost Range | M74: Gr. Margin Range | N74: =MAX(N70:N73)-MIN(N70:N73) -> 5.7526789
A75: Total Product 1 Usage | D75: =12*(Inputs!$AD$135+Inputs!$BB$135)/Inputs!$D$39*L16 -> 17589479 | E75: =12*(Inputs!$AD$135+Inputs!$BB$135)/Inputs!$D$39*M16 -> 25504370 | F75: =12*(Inputs!$AD$135+Inputs!$BB$135)/Inputs!$D$39*N16 -> 36981336 | G75: =12*(Inputs!$AD$135+Inputs!$BB$135)/Inputs!$D$39*O16 -> 53622938 | I75: =AVERAGE(I70:I73) -> 1.6191314e+08 | J75: Average Cost | M75: Average Gr. Margin | N75: =AVERAGE(N70:N73) -> 17.864975
A76: Total Product 2 Usage | D76: =12*(Inputs!$AE$135+Inputs!$BC$135)/Inputs!$D$39*L16 -> 7071614.3 | E76: =12*(Inputs!$AE$135+Inputs!$BC$135)/Inputs!$D$39*M16 -> 10253690 | F76: =12*(Inputs!$AE$135+Inputs!$BC$135)/Inputs!$D$39*N16 -> 14867851 | G76: =12*(Inputs!$AE$135+Inputs!$BC$135)/Inputs!$D$39*O16 -> 21558384 | I76: =MAX(I70:I73)/I75-1 -> 0.07736608 | J76: Max to Average % | M76: Max to Average % | N76: =MAX(N70:N73)/N75-1 -> 0.18441417
A77: Total Product 1 Units | D77: =Inputs!$AY$135*12/Inputs!$D$39*L16 -> 1.5570531e+08 | E77: =Inputs!$AY$135*12/Inputs!$D$39*M16 -> 2.2576938e+08 | F77: =Inputs!$AY$135*12/Inputs!$D$39*N16 -> 3.273656e+08 | G77: =Inputs!$AY$135*12/Inputs!$D$39*O16 -> 4.7468012e+08 | I77: =MIN(I70:I73)/I75-1 -> -0.10369171 | J77: Min to Average % | M77: Min to Average % | N77: =MIN(N70:N73)/N75-1 -> -0.13759461
A78: Total Product 2 Units | D78: =Inputs!$AZ$135*12/Inputs!$D$39*L16 -> 63234033 | E78: =Inputs!$AZ$135*12/Inputs!$D$39*M16 -> 91688002 | F78: =Inputs!$AZ$135*12/Inputs!$D$39*N16 -> 1.329476e+08 | G78: =Inputs!$AZ$135*12/Inputs!$D$39*O16 -> 1.9277402e+08 | I78: =I74/I75 -> 0.18105779 | J78: Range | M78: Range | N78: =N74/N75 -> 0.32200878
A79: Total Product 3 Units | D79: =Inputs!$BA$135/Inputs!$D$39*L16 -> 11728.893 | E79: =Inputs!$BA$135/Inputs!$D$39*M16 -> 17006.646 | F79: =Inputs!$BA$135/Inputs!$D$39*N16 -> 24659.636 | G79: =Inputs!$BA$135/Inputs!$D$39*O16 -> 35756.472
I80: =SUM(D49:G49) -> 78513826 | J80: Chart 1 Profit
I81: =SUM(L49:O49) -> 81196379 | J81: Chart 2 Profit
I82: =SUM(T51:W51) -> 96621978 | J82: Chart 3 Profit
I83: =SUM(AB38:AE38) -> 1.0782946e+08 | J83: Chart 4 Profit
I84: =MAX(I80:I83)-MIN(I80:I83) -> 29315635 | J84: Profit Range
I85: =AVERAGE(I80:I83) -> 91040411 | J85: Average Profit
I86: =MAX(I80:I83)/I85-1 -> 0.18441316 | J86: Max to Average %
I87: =MIN(I80:I83)/I85-1 -> -0.13759368 | J87: Min to Average %
I88: =I84/I85 -> 0.32200684 | J88: Range

Sheet Entity 2 Out
A1: Fixed Costs and Aggregated Per-Minute Costs | I1: Aggregated Per-Minute Costs | Q1: Itemized Costs
A2: Entity 2 | I2: =A2 -> Entity 2 | Q2: =A2 -> Entity 2
A3: Revenue and Costs | I3: =A3 -> Revenue and Costs | Q3: =A3 -> Revenue and Costs
A4: Base Case Projection | I4: Base Case Projection | Q4: Base Case Projection
D5: ="Assumes a customer growth rate of "&Inputs!E154*100&"%" -> Assumes a customer growth rate of 10% | L5: =D5 -> Assumes a customer growth rate of 10% | T5: =D5 -> Assumes a customer growth rate of 10%
A6: Customers | D6: 2008-2009 | E6: 2009-2010 | F6: 2010-2011 | G6: 2011-2012 | I6: =A6 -> Customers | L6: =D6 -> 2008-2009 | M6: =E6 -> 2009-2010 | N6: =F6 -> 2010-2011 | O6: =G6 -> 2011-2012 | Q6: =I6 -> Customers | T6: 2008-2009 | U6: 2009-2010 | V6: 2010-2011 | W6: 2011-2012
A7: Product 1 | D7: =Inputs!C158 -> 2133333.3 | E7: =D7-E55+E50 -> 2240000 | F7: =E7-F55+F50 -> 2352000 | G7: =F7-G55+G50 -> 2469600 | I7: =A7 -> Product 1 | L7: =D7 -> 2133333.3 | M7: =E7 -> 2240000 | N7: =F7 -> 2352000 | O7: =G7 -> 2469600 | Q7: =I7 -> Product 1 | T7: =D7 -> 2133333.3 | U7: =E7 -> 2240000 | V7: =F7 -> 2352000 | W7: =G7 -> 2469600
A8: Product 2 | D8: =Inputs!D158 -> 266666.67 | E8: =D8-E56+E51 -> 280000 | F8: =E8-F56+F51 -> 294000 | G8: =F8-G56+G51 -> 308700 | I8: =A8 -> Product 2 | L8: =D8 -> 266666.67 | M8: =E8 -> 280000 | N8: =F8 -> 294000 | O8: =G8 -> 308700 | Q8: =I8 -> Product 2 | T8: =D8 -> 266666.67 | U8: =E8 -> 280000 | V8: =F8 -> 294000 | W8: =G8 -> 308700
A9: Product 3 | D9: =Inputs!E158 -> 266666.67 | E9: =D9-E57+E52 -> 280000 | F9: =E9-F57+F52 -> 294000 | G9: =F9-G57+G52 -> 308700 | I9: =A9 -> Product 3 | L9: =D9 -> 266666.67 | M9: =E9 -> 280000 | N9: =F9 -> 294000 | O9: =G9 -> 308700 | Q9: =I9 -> Product 3 | T9: =D9 -> 266666.67 | U9: =E9 -> 280000 | V9: =F9 -> 294000 | W9: =G9 -> 308700
A10: Prodcut 4 | D10: =Inputs!F158 -> 1000000 | E10: =D10-E58+E53 -> 1050000 | F10: =E10-F58+F53 -> 1102500 | G10: =F10-G58+G53 -> 1157625 | I10: =A10 -> Prodcut 4 | L10: =D10 -> 1000000 | M10: =E10 -> 1050000 | N10: =F10 -> 1102500 | O10: =G10 -> 1157625 | Q10: =I10 -> Prodcut 4 | T10: =D10 -> 1000000 | U10: =E10 -> 1050000 | V10: =F10 -> 1102500 | W10: =G10 -> 1157625
A11: Total Subscribers* | D11: =ROUNDUP(SUM(D7:D10),0) -> 3666667 | E11: =SUM(E7:E10) -> 3850000 | F11: =SUM(F7:F10) -> 4042500 | G11: =SUM(G7:G10) -> 4244625 | I11: =A11 -> Total Subscribers* | L11: =ROUNDUP(SUM(L7:L10),0) -> 3666667 | M11: =SUM(M7:M10) -> 3850000 | N11: =SUM(N7:N10) -> 4042500 | O11: =SUM(O7:O10) -> 4244625 | Q11: =I11 -> Total Subscribers* | T11: =SUM(T7:T10) -> 3666666.7 | U11: =SUM(U7:U10) -> 3850000 | V11: =SUM(V7:V10) -> 4042500 | W11: =SUM(W7:W10) -> 4244625
A13: Revenue | B13: NRC | C13: RC | D13: =D6 -> 2008-2009 | E13: =E6 -> 2009-2010 | F13: =F6 -> 2010-2011 | G13: =G6 -> 2011-2012 | I13: =A13 -> Revenue | J13: =B13 -> NRC | K13: =C13 -> RC | L13: =L6 -> 2008-2009 | M13: =M6 -> 2009-2010 | N13: =N6 -> 2010-2011 | O13: =O6 -> 2011-2012 | Q13: =I13 -> Revenue | R13: =B13 -> NRC | S13: =C13 -> RC | T13: =D13 -> 2008-2009 | U13: =E13 -> 2009-2010 | V13: =F13 -> 2010-2011 | W13: =O13 -> 2011-2012
A14: =A7&" Customer Activation" -> Product 1 Customer Activation | B14: =Inputs!C152 -> 29.99 | D14: =D50*$B14 -> 63978667 | E14: =E50*$B14 -> 6397866.7 | F14: =F50*$B14 -> 6717760 | G14: =G50*$B14 -> 7053648 | I14: =A14 -> Product 1 Customer Activation | J14: =B14 -> 29.99 | L14: =D14 -> 63978667 | M14: =E14 -> 6397866.7 | N14: =F14 -> 6717760 | O14: =G14 -> 7053648 | Q14: =I14 -> Product 1 Customer Activation | R14: =B14 -> 29.99 | T14: =D14 -> 63978667 | U14: =E14 -> 6397866.7 | V14: =F14 -> 6717760 | W14: =G14 -> 7053648
A15: =A8&" Customer Activation" -> Product 2 Customer Activation | B15: =Inputs!D152 -> 29.99 | D15: =D51*$B15 -> 7997333.3 | E15: =E51*$B15 -> 799733.33 | F15: =F51*$B15 -> 839720 | G15: =G51*$B15 -> 881706 | I15: =A15 -> Product 2 Customer Activation | J15: =B15 -> 29.99 | L15: =D15 -> 7997333.3 | M15: =E15 -> 799733.33 | N15: =F15 -> 839720 | O15: =G15 -> 881706 | Q15: =I15 -> Product 2 Customer Activation | R15: =B15 -> 29.99 | T15: =D15 -> 7997333.3 | U15: =E15 -> 799733.33 | V15: =F15 -> 839720 | W15: =G15 -> 881706
A16: =A9&" Customer Activation" -> Product 3 Customer Activation | B16: =Inputs!E152 -> 34.99 | D16: =D52*$B16 -> 9330666.7 | E16: =E52*$B16 -> 933066.67 | F16: =F52*$B16 -> 979720 | G16: =G52*$B16 -> 1028706 | I16: =A16 -> Product 3 Customer Activation | J16: =B16 -> 34.99 | L16: =D16 -> 9330666.7 | M16: =E16 -> 933066.67 | N16: =F16 -> 979720 | O16: =G16 -> 1028706 | Q16: =I16 -> Product 3 Customer Activation | R16: =B16 -> 34.99 | T16: =D16 -> 9330666.7 | U16: =E16 -> 933066.67 | V16: =F16 -> 979720 | W16: =G16 -> 1028706
A17: =A10&" Customer Activation" -> Prodcut 4 Customer Activation | B17: =Inputs!F152 -> 44.95 | D17: =D53*$B17 -> 44950000 | E17: =E53*$B17 -> 4495000 | F17: =F53*$B17 -> 4719750 | G17: =G53*$B17 -> 4955737.5 | I17: =A17 -> Prodcut 4 Customer Activation | J17: =B17 -> 44.95 | L17: =D17 -> 44950000 | M17: =E17 -> 4495000 | N17: =F17 -> 4719750 | O17: =G17 -> 4955737.5 | Q17: =I17 -> Prodcut 4 Customer Activation | R17: =B17 -> 44.95 | T17: =D17 -> 44950000 | U17: =E17 -> 4495000 | V17: =F17 -> 4719750 | W17: =G17 -> 4955737.5
A18: =A7&" Usage" -> Product 1 Usage | C18: =Inputs!C153 -> 19.95 | D18: =12*D7*$C18 -> 5.1072e+08 | E18: =12*E7*$C18 -> 5.36256e+08 | F18: =12*F7*$C18 -> 5.630688e+08 | G18: =12*G7*$C18 -> 5.9122224e+08 | I18: =A18 -> Product 1 Usage | K18: =C18 -> 19.95 | L18: =D18 -> 5.1072e+08 | M18: =E18 -> 5.36256e+08 | N18: =F18 -> 5.630688e+08 | O18: =G18 -> 5.9122224e+08 | Q18: =I18 -> Product 1 Usage | S18: =C18 -> 19.95 | T18: =D18 -> 5.1072e+08 | U18: =E18 -> 5.36256e+08 | V18: =F18 -> 5.630688e+08 | W18: =G18 -> 5.9122224e+08
A19: =A8&" Usage" -> Product 2 Usage | C19: =Inputs!D153 -> 14.95 | D19: =12*D8*$C19 -> 47840000 | E19: =12*E8*$C19 -> 50232000 | F19: =12*F8*$C19 -> 52743600 | G19: =12*G8*$C19 -> 55380780 | I19: =A19 -> Product 2 Usage | K19: =C19 -> 14.95 | L19: =D19 -> 47840000 | M19: =E19 -> 50232000 | N19: =F19 -> 52743600 | O19: =G19 -> 55380780 | Q19: =I19 -> Product 2 Usage | S19: =C19 -> 14.95 | T19: =D19 -> 47840000 | U19: =E19 -> 50232000 | V19: =F19 -> 52743600 | W19: =G19 -> 55380780
A20: =A9&" Usage" -> Product 3 Usage | C20: =Inputs!E153 -> 9.95 | D20: =12*D9*$C20 -> 31840000 | E20: =12*E9*$C20 -> 33432000 | F20: =12*F9*$C20 -> 35103600 | G20: =12*G9*$C20 -> 36858780 | I20: =A20 -> Product 3 Usage | K20: =C20 -> 9.95 | L20: =D20 -> 31840000 | M20: =E20 -> 33432000 | N20: =F20 -> 35103600 | O20: =G20 -> 36858780 | Q20: =I20 -> Product 3 Usage | S20: =C20 -> 9.95 | T20: =D20 -> 31840000 | U20: =E20 -> 33432000 | V20: =F20 -> 35103600 | W20: =G20 -> 36858780
A21: =A10&" Usage" -> Prodcut 4 Usage | C21: =Inputs!F153 -> 44.95 | D21: =12*D10*$C21 -> 539400000 | E21: =12*E10*$C21 -> 566370000 | F21: =12*F10*$C21 -> 594688500 | G21: =12*G10*$C21 -> 624422925 | I21: =A21 -> Prodcut 4 Usage | K21: =C21 -> 44.95 | L21: =D21 -> 539400000 | M21: =E21 -> 566370000 | N21: =F21 -> 594688500 | O21: =G21 -> 624422925 | Q21: =I21 -> Prodcut 4 Usage | S21: =C21 -> 44.95 | T21: =D21 -> 539400000 | U21: =E21 -> 566370000 | V21: =F21 -> 594688500 | W21: =G21 -> 624422925
A22: Equipment Sales | D22: =D58*$B22 -> 0 | E22: =E58*$B22 -> 0 | F22: =F58*$B22 -> 0 | G22: =G58*$B22 -> 0 | I22: =A22 -> Equipment Sales | J22: =B22 -> 0 | L22: =D22 -> 0 | M22: =E22 -> 0 | N22: =F22 -> 0 | O22: =G22 -> 0 | Q22: =I22 -> Equipment Sales | R22: =B22 -> 0 | T22: =D22 -> 0 | U22: =E22 -> 0 | V22: =F22 -> 0 | W22: =G22 -> 0
A23: Total Revenue | D23: =SUM(D14:D22) -> 1.2560567e+09 | E23: =SUM(E14:E22) -> 1.1989157e+09 | F23: =SUM(F14:F22) -> 1.2588614e+09 | G23: =SUM(G14:G22) -> 1.3218045e+09 | I23: =A23 -> Total Revenue | L23: =SUM(L14:L22) -> 1.2560567e+09 | M23: =SUM(M14:M22) -> 1.1989157e+09 | N23: =SUM(N14:N22) -> 1.2588614e+09 | O23: =SUM(O14:O22) -> 1.3218045e+09 | Q23: =I23 -> Total Revenue | T23: =SUM(T14:T22) -> 1.2560567e+09 | U23: =SUM(U14:U22) -> 1.1989157e+09 | V23: =SUM(V14:V22) -> 1.2588614e+09 | W23: =SUM(W14:W22) -> 1.3218045e+09
A25: Variable Costs | B25: NRC | C25: RC | I25: =A25 -> Variable Costs | J25: NRC | K25: RC | Q25: =A25 -> Variable Costs | R25: NRC | S25: RC
A26: =A14 -> Product 1 Customer Activation | B26: =SUM(Inputs!C143:C146) -> 69.55 | D26: =(D50+D55)*$B26 -> 1.4837333e+08 | E26: =E60*$B26 -> 38252500 | F26: =F60*$B26 -> 40165125 | G26: =G60*$B26 -> 42173381 | I26: =I7&" Monthly Cost" -> Product 1 Monthly Cost | K26: =Inputs!C165 -> 14.6925 | L26: =12*L7*$K$26 -> 3.76128e+08 | M26: =12*M7*$K$26 -> 3.949344e+08 | N26: =12*N7*$K$26 -> 4.1468112e+08 | O26: =12*O7*$K$26 -> 4.3541518e+08 | Q26: =Q7 -> Product 1
A27: =A15 -> Product 2 Customer Activation | B27: =SUM(Inputs!D143:D146) -> 69.55 | D27: =(D51+D56)*$B27 -> 18546667 | E27: =(E51+E56)*$B27 -> 2782000 | F27: =(F51+F56)*$B27 -> 2921100 | G27: =(G51+G56)*$B27 -> 3067155 | I27: =I8&" Monthly Cost" -> Product 2 Monthly Cost | K27: =Inputs!D165 -> 13.9425 | L27: =12*L8*$K$27 -> 44616000 | M27: =12*M8*$K$27 -> 46846800 | N27: =12*N8*$K$27 -> 49189140 | O27: =12*O8*$K$27 -> 51648597 | Q27: =Inputs!B143 -> Equipment Cost | R27: =Inputs!C143 -> 42 | T27: =(D$50+D$55)*$R$27 -> 89600000 | U27: =(E$50+E$55)*$R$27 -> 13440000 | V27: =(F$50+F$55)*$R$27 -> 14112000 | W27: =(G$50+G$55)*$R$27 -> 14817600
A28: =A16 -> Product 3 Customer Activation | B28: =SUM(Inputs!E143:E146) -> 69.55 | D28: =(D52+D57)*$B28 -> 18546667 | E28: =(E52+E57)*$B28 -> 2782000 | F28: =(F52+F57)*$B28 -> 2921100 | G28: =(G52+G57)*$B28 -> 3067155 | I28: =I9&" Monthly Cost" -> Product 3 Monthly Cost | K28: =Inputs!E165 -> 13.1925 | L28: =12*L9*$K$28 -> 42216000 | M28: =12*M9*$K$28 -> 44326800 | N28: =12*N9*$K$28 -> 46543140 | O28: =12*O9*$K$28 -> 48870297 | Q28: =Inputs!B144 -> Shipping Cost | R28: =Inputs!C144 -> 3 | T28: =(D$50+D$55)*$R$28 -> 6400000 | U28: =(E$50+E$55)*$R$28 -> 960000 | V28: =(F$50+F$55)*$R$28 -> 1008000 | W28: =(G$50+G$55)*$R$28 -> 1058400
A29: =A17 -> Prodcut 4 Customer Activation | B29: =SUM(Inputs!F143:F146) -> 70.92 | D29: =(D53+D58)*$B29 -> 70920000 | E29: =(E53+E58)*$B29 -> 10638000 | F29: =(F53+F58)*$B29 -> 11169900 | G29: =(G53+G58)*$B29 -> 11728395 | I29: =I10&" Monthly Cost" -> Prodcut 4 Monthly Cost | K29: =Inputs!F165 -> 29.646667 | L29: =12*L10*$K$29 -> 3.5576e+08 | M29: =12*M10*$K$29 -> 3.73548e+08 | N29: =12*N10*$K$29 -> 3.922254e+08 | O29: =12*O10*$K$29 -> 4.1183667e+08 | Q29: =Inputs!B145 -> Activation Commission | R29: =Inputs!C145 -> 20 | T29: =(D$50+D$55)*$R$29 -> 42666667 | U29: =(E$50+E$55)*$R$29 -> 6400000 | V29: =(F$50+F$55)*$R$29 -> 6720000 | W29: =(G$50+G$55)*$R$29 -> 7056000
A30: =A7&" Residual Commission" -> Product 1 Residual Commission | C30: =Inputs!C147 -> 0.15 | D30: =$C30*D18 -> 76608000 | E30: =$C30*E18 -> 80438400 | F30: =$C30*F18 -> 84460320 | G30: =$C30*G18 -> 88683336 | I30: Total Costs | L30: =SUM(L26:L29) -> 8.1872e+08 | M30: =SUM(M26:M29) -> 8.59656e+08 | N30: =SUM(N26:N29) -> 9.026388e+08 | O30: =SUM(O26:O29) -> 9.4777074e+08 | Q30: =Inputs!B146 -> Billing, Office, Bad Debt | R30: =Inputs!C146 -> 4.55 | T30: =(D$50+D$55)*$R$30 -> 9706666.7 | U30: =(E$50+E$55)*$R$30 -> 1456000 | V30: =(F$50+F$55)*$R$30 -> 1528800 | W30: =(G$50+G$55)*$R$30 -> 1605240
A31: =A8&" Residual Commission" -> Product 2 Residual Commission | C31: =Inputs!D147 -> 0.15 | D31: =$C31*D19 -> 7176000 | E31: =$C31*E19 -> 7534800 | F31: =$C31*F19 -> 7911540 | G31: =$C31*G19 -> 8307117 | Q31: =Inputs!B147 -> Recurring Commission | S31: =Inputs!C147 -> 0.15 | T31: =$S$31*T18 -> 76608000 | U31: =$S$31*U18 -> 80438400 | V31: =$S$31*V18 -> 84460320 | W31: =$S$31*W18 -> 88683336
A32: =A9&" Residual Commission" -> Product 3 Residual Commission | C32: =Inputs!E147 -> 0.15 | D32: =$C32*D20 -> 4776000 | E32: =$C32*E20 -> 5014800 | F32: =$C32*F20 -> 5265540 | G32: =$C32*G20 -> 5528817 | I32: =A40 -> Total EBITDA | L32: =L23-L30 -> 4.3733667e+08 | M32: =M23-M30 -> 3.3925967e+08 | N32: =N23-N30 -> 3.5622265e+08 | O32: =O23-O30 -> 3.7403378e+08 | Q32: =Inputs!B148 -> Wholesale Provider Cost | S32: =Inputs!C148 -> 5.55 | T32: =$S$32*T7*12 -> 1.4208e+08 | U32: =$S$32*U7*12 -> 1.49184e+08 | V32: =$S$32*V7*12 -> 1.566432e+08 | W32: =$S$32*W7*12 -> 1.6447536e+08
A33: =A10&" Residual Commission" -> Prodcut 4 Residual Commission | C33: =Inputs!F147 -> 0.15 | D33: =$C33*D21 -> 80910000 | E33: =$C33*E21 -> 84955500 | F33: =$C33*F21 -> 89203275 | G33: =$C33*G21 -> 93663439 | Q33: =Inputs!B149 -> Marketing Expense | S33: =Inputs!C149 -> 3 | T33: =$S$33*T7 -> 6400000 | U33: =$S$33*U7 -> 6720000 | V33: =$S$33*V7 -> 7056000 | W33: =$S$33*W7 -> 7408800
A34: =A7&" Operating Cost" -> Product 1 Operating Cost | C34: =Inputs!C163 -> 8.8966667 | D34: =D7*$C$34*12 -> 2.2775467e+08 | E34: =E7*$C$34*12 -> 2.391424e+08 | F34: =F7*$C$34*12 -> 2.5109952e+08 | G34: =G7*$C$34*12 -> 2.636545e+08 | L34: =D42 -> Monthly Figures | Q34: =Inputs!B150 -> Sales and General Administrative | S34: =Inputs!C150 -> 1 | T34: =$S$34*T7 -> 2133333.3 | U34: =$S$34*U7 -> 2240000 | V34: =$S$34*V7 -> 2352000 | W34: =$S$34*W7 -> 2469600
A35: =A8&" Operating Cost" -> Product 2 Operating Cost | C35: =Inputs!D163 -> 8.1466667 | D35: =D8*$C$34*12 -> 28469333 | E35: =E8*$C$34*12 -> 29892800 | F35: =F8*$C$34*12 -> 31387440 | G35: =G8*$C$34*12 -> 32956812 | L35: =D43 -> ARPU | M35: =E43 -> AVG COST | N35: =F43 -> Gross margin | O35: =G43 -> Margin | Q35: =Inputs!B151 -> Occupancy | S35: =Inputs!C151 -> 0.25 | T35: =$S$35*T7 -> 533333.33 | U35: =$S$35*U7 -> 560000 | V35: =$S$35*V7 -> 588000 | W35: =$S$35*W7 -> 617400
A36: =A9&" Operating Cost" -> Product 3 Operating Cost | C36: =Inputs!E163 -> 7.3966667 | D36: =D9*$C$34*12 -> 28469333 | E36: =E9*$C$34*12 -> 29892800 | F36: =F9*$C$34*12 -> 31387440 | G36: =G9*$C$34*12 -> 32956812 | L36: =D44 -> 26.552901 | M36: =(SUM(L30:O30)/4/12)/(SUM(L11:O11)/4) -> 18.607272 | N36: =L36-M36 -> 7.9456287 | O36: =N36/L36 -> 0.29923769 | Q36: =Q8 -> Product 2
A37: =A10&" Operating Cost" -> Prodcut 4 Operating Cost | C37: =Inputs!F163 -> 23.736667 | D37: =D10*$C$34*12 -> 1.0676e+08 | E37: =E10*$C$34*12 -> 1.12098e+08 | F37: =F10*$C$34*12 -> 1.177029e+08 | G37: =G10*$C$34*12 -> 1.2358805e+08 | Q37: =Q27 -> Equipment Cost | R37: =Inputs!D143 -> 42 | T37: =(D$51+D$56)*$R37 -> 11200000 | U37: =(E$51+E$56)*$R37 -> 1680000 | V37: =(F$51+F$56)*$R37 -> 1764000 | W37: =(G$51+G$56)*$R37 -> 1852200
A38: Total Costs | D38: =SUM(D26:D37) -> 8.1731e+08 | E38: =SUM(E26:E37) -> 6.43424e+08 | F38: =SUM(F26:F37) -> 6.755952e+08 | G38: =SUM(G26:G37) -> 7.0937496e+08 | I38: =A46 -> *Subscriber number assumes a monthly customer churn rate of 5% | Q38: =Q28 -> Shipping Cost | R38: =Inputs!D144 -> 3 | T38: =(D$51+D$56)*$R38 -> 800000 | U38: =(E$51+E$56)*$R38 -> 120000 | V38: =(F$51+F$56)*$R38 -> 126000 | W38: =(G$51+G$56)*$R38 -> 132300
Q39: =Q29 -> Activation Commission | R39: =Inputs!D145 -> 20 | T39: =(D$51+D$56)*$R39 -> 5333333.3 | U39: =(E$51+E$56)*$R39 -> 800000 | V39: =(F$51+F$56)*$R39 -> 840000 | W39: =(G$51+G$56)*$R39 -> 882000
A40: Total EBITDA | D40: =D23-D38 -> 4.3874667e+08 | E40: =E23-E38 -> 5.5549167e+08 | F40: =F23-F38 -> 5.8326625e+08 | G40: =G23-G38 -> 6.1242956e+08 | Q40: =Q30 -> Billing, Office, Bad Debt | R40: =Inputs!D146 -> 4.55 | T40: =(D$51+D$56)*$R40 -> 1213333.3 | U40: =(E$51+E$56)*$R40 -> 182000 | V40: =(F$51+F$56)*$R40 -> 191100 | W40: =(G$51+G$56)*$R40 -> 200655
Q41: =Q31 -> Recurring Commission | S41: =Inputs!D147 -> 0.15 | T41: =$S$41*T19 -> 7176000 | U41: =$S$41*U19 -> 7534800 | V41: =$S$41*V19 -> 7911540 | W41: =$S$41*W19 -> 8307117
D42: Monthly Figures | I42: =SUM(D23:G23) -> 5035638306 | J42: Chart 1 Revenue | M42: Chart 1 Margin | N42: =G44 -> 0.4348871 | Q42: =Q32 -> Wholesale Provider Cost | S42: =Inputs!D148 -> 5.55 | T42: =12*T8*$S$42 -> 17760000 | U42: =12*U8*$S$42 -> 18648000 | V42: =12*V8*$S$42 -> 19580400 | W42: =12*W8*$S$42 -> 20559420
D43: ARPU | E43: AVG COST | F43: Gross margin | G43: Margin | I43: =SUM(L23:O23) -> 5035638306 | J43: Chart 2 Revenue | M43: Chart 2 Margin | N43: =O36 -> 0.29923769 | Q43: =Q33 -> Marketing Expense | S43: =Inputs!D149 -> 3 | T43: =T9*$S$43 -> 800000 | U43: =U9*$S$43 -> 840000 | V43: =V9*$S$43 -> 882000 | W43: =W9*$S$43 -> 926100
D44: =(SUM(D23:G23)/12/4)/(SUM(D11:G11)/4) -> 26.552901 | E44: =(SUM(D38:G38)/12/4)/(SUM(D11:G11)/4) -> 15.005387 | F44: =D44-E44 -> 11.547514 | G44: =F44/D44 -> 0.4348871 | I44: =SUM(T23:W23) -> 5035638306 | J44: Chart 3 Revenue | M44: Chart 3 Margin | N44: =W72 -> 0.40460459 | Q44: =Q34 -> Sales and General Administrative | S44: =Inputs!D150 -> 1 | T44: =$S$44*T8 -> 266666.67 | U44: =$S$44*U8 -> 280000 | V44: =$S$44*V8 -> 294000 | W44: =$S$44*W8 -> 308700
I45: =MAX(I42:I44)-MIN(I42:I44) -> 0 | J45: Revenue Range | M45: Margin Range | N45: =MAX(N42:N44)-MIN(N42:N44) -> 0.13564941 | Q45: =Q35 -> Occupancy | S45: =Inputs!D151 -> 0.25 | T45: =$S$45*T8 -> 66666.667 | U45: =$S$45*U8 -> 70000 | V45: =$S$45*V8 -> 73500 | W45: =$S$45*W8 -> 77175
A46: ="*Subscriber number assumes a monthly customer churn rate of "&100*Inputs!C154&"%" -> *Subscriber number assumes a monthly customer churn rate of 5% | I46: =AVERAGE(I42:I44) -> 5035638306 | J46: Average Revenue | M46: Average Margin | N46: =AVERAGE(N42:N44) -> 0.37957646 | Q46: =Q9 -> Product 3
I47: =MAX(I42:I44)/I46-1 -> 0 | J47: Max to Average % | M47: Max to Average % | N47: =MAX(N42:N44)/N46-1 -> 0.14571673 | Q47: =Q27 -> Equipment Cost | R47: =Inputs!E143 -> 42 | T47: =(D$52+D$57)*$R47 -> 11200000 | U47: =(E$52+E$57)*$R47 -> 1680000 | V47: =(F$52+F$57)*$R47 -> 1764000 | W47: =(G$52+G$57)*$R47 -> 1852200
I48: =MIN(I42:I44)/I46-1 -> 0 | J48: Min to Average % | M48: Min to Average % | N48: =MIN(N42:N44)/N46-1 -> -0.21165372 | Q48: =Q28 -> Shipping Cost | R48: =Inputs!E144 -> 3 | T48: =(D$52+D$57)*$R48 -> 800000 | U48: =(E$52+E$57)*$R48 -> 120000 | V48: =(F$52+F$57)*$R48 -> 126000 | W48: =(G$52+G$57)*$R48 -> 132300
I49: =I45/I46 -> 0 | J49: Range | M49: Range | N49: =N45/N46 -> 0.35737046 | Q49: =Q29 -> Activation Commission | R49: =Inputs!E145 -> 20 | T49: =(D$52+D$57)*$R49 -> 5333333.3 | U49: =(E$52+E$57)*$R49 -> 800000 | V49: =(F$52+F$57)*$R49 -> 840000 | W49: =(G$52+G$57)*$R49 -> 882000
A50: =A7&" Subscriber Growth" -> Product 1 Subscriber Growth | D50: =Inputs!$E$154*C7+D7 -> 2133333.3 | E50: =Inputs!$E$154*D7 -> 213333.33 | F50: =Inputs!$E$154*E7 -> 224000 | G50: =Inputs!$E$154*F7 -> 235200 | Q50: =Q30 -> Billing, Office, Bad Debt | R50: =Inputs!E146 -> 4.55 | T50: =(D$52+D$57)*$R50 -> 1213333.3 | U50: =(E$52+E$57)*$R50 -> 182000 | V50: =(F$52+F$57)*$R50 -> 191100 | W50: =(G$52+G$57)*$R50 -> 200655
A51: =A8&" Subscriber Growth" -> Product 2 Subscriber Growth | D51: =Inputs!$E$154*C8+D8 -> 266666.67 | E51: =Inputs!$E$154*D8 -> 26666.667 | F51: =Inputs!$E$154*E8 -> 28000 | G51: =Inputs!$E$154*F8 -> 29400 | I51: =SUM(D38:G38) -> 2845704160 | J51: Chart 1 Cost | M51: Chart 1 Gr. Margin | N51: =F44 -> 11.547514 | Q51: =Q31 -> Recurring Commission | S51: =Inputs!E147 -> 0.15 | T51: =$S$51*T20 -> 4776000 | U51: =$S$51*U20 -> 5014800 | V51: =$S$51*V20 -> 5265540 | W51: =$S$51*W20 -> 5528817
A52: =A9&" Subscriber Growth" -> Product 3 Subscriber Growth | D52: =Inputs!$E$154*C9+D9 -> 266666.67 | E52: =Inputs!$E$154*D9 -> 26666.667 | F52: =Inputs!$E$154*E9 -> 28000 | G52: =Inputs!$E$154*F9 -> 29400 | I52: =SUM(L29:O29) -> 1533370070 | J52: Chart 2 Cost | M52: Chart 2 Gr. Margin | N52: =N36 -> 7.9456287 | Q52: =Q32 -> Wholesale Provider Cost | S52: =Inputs!E148 -> 5.55 | T52: =12*$S$52*T9 -> 17760000 | U52: =12*$S$52*U9 -> 18648000 | V52: =12*$S$52*V9 -> 19580400 | W52: =12*$S$52*W9 -> 20559420
A53: =A10&" Subscriber Growth" -> Prodcut 4 Subscriber Growth | D53: =Inputs!$E$154*C10+D10 -> 1000000 | E53: =Inputs!$E$154*D10 -> 100000 | F53: =Inputs!$E$154*E10 -> 105000 | G53: =Inputs!$E$154*F10 -> 110250 | I53: =SUM(T66:W66) -> 2998195879 | J53: Chart 3 Cost | M53: Chart 3 Gr. Margin | N53: =V72 -> 10.743426 | Q53: =Q33 -> Marketing Expense | S53: =Inputs!E149 -> 3 | T53: =T9*$S53 -> 800000 | U53: =U9*$S53 -> 840000 | V53: =V9*$S53 -> 882000 | W53: =W9*$S53 -> 926100
A54: Total Subscriber Growth | D54: =SUM(D50:D53) -> 3666666.7 | E54: =SUM(E50:E53) -> 366666.67 | F54: =SUM(F50:F53) -> 385000 | G54: =SUM(G50:G53) -> 404250 | I54: =MAX(I51:I53)-MIN(I51:I53) -> 1464825809 | J54: Cost Range | M54: Gr. Margin Range | N54: =MAX(N51:N53)-MIN(N51:N53) -> 3.6018854 | Q54: =Q34 -> Sales and General Administrative | S54: =Inputs!E150 -> 1 | T54: =T9*$S54 -> 266666.67 | U54: =U9*$S54 -> 280000 | V54: =V9*$S54 -> 294000 | W54: =W9*$S54 -> 308700
A55: =A7&" Churn" -> Product 1 Churn | D55: =Inputs!$C$154*C7 -> 0 | E55: =Inputs!$C$154*D7 -> 106666.67 | F55: =Inputs!$C$154*E7 -> 112000 | G55: =Inputs!$C$154*F7 -> 117600 | I55: =AVERAGE(I51:I53) -> 2459090036 | J55: Average Cost | M55: Average Gr. Margin | N55: =AVERAGE(N51:N53) -> 10.078856 | Q55: =Q35 -> Occupancy | S55: =Inputs!E151 -> 0.25 | T55: =T9*$S55 -> 66666.667 | U55: =U9*$S55 -> 70000 | V55: =V9*$S55 -> 73500 | W55: =W9*$S55 -> 77175
A56: =A8&" Churn" -> Product 2 Churn | D56: =Inputs!$C$154*C8 -> 0 | E56: =Inputs!$C$154*D8 -> 13333.333 | F56: =Inputs!$C$154*E8 -> 14000 | G56: =Inputs!$C$154*F8 -> 14700 | I56: =MAX(I51:I53)/I55-1 -> 0.21922981 | J56: Max to Average % | M56: Max to Average % | N56: =MAX(N51:N53)/N55-1 -> 0.14571673 | Q56: =Q10 -> Prodcut 4
A57: =A9&" Churn" -> Product 3 Churn | D57: =Inputs!$C$154*C9 -> 0 | E57: =Inputs!$C$154*D9 -> 13333.333 | F57: =Inputs!$C$154*E9 -> 14000 | G57: =Inputs!$C$154*F9 -> 14700 | I57: =MIN(I51:I53)/I55-1 -> -0.37644818 | J57: Min to Average % | M57: Min to Average % | N57: =MIN(N51:N53)/N55-1 -> -0.21165372 | Q57: =Q27 -> Equipment Cost | R57: =Inputs!F143 -> 42 | T57: =(D$53+D$58)*$R57 -> 42000000 | U57: =(E$53+E$58)*$R57 -> 6300000 | V57: =(F$53+F$58)*$R57 -> 6615000 | W57: =(G$53+G$58)*$R57 -> 6945750
A58: =A10&" Churn" -> Prodcut 4 Churn | D58: =Inputs!$C$154*C10 -> 0 | E58: =Inputs!$C$154*D10 -> 50000 | F58: =Inputs!$C$154*E10 -> 52500 | G58: =Inputs!$C$154*F10 -> 55125 | I58: =I54/I55 -> 0.59567799 | J58: Range | M58: Range | N58: =N54/N55 -> 0.35737046 | Q58: =Q28 -> Shipping Cost | R58: =Inputs!F144 -> 3 | T58: =(D$53+D$58)*$R58 -> 3000000 | U58: =(E$53+E$58)*$R58 -> 450000 | V58: =(F$53+F$58)*$R58 -> 472500 | W58: =(G$53+G$58)*$R58 -> 496125
A59: Total Churn | D59: =SUM(D55:D58) -> 0 | E59: =SUM(E55:E58) -> 183333.33 | F59: =SUM(F55:F58) -> 192500 | G59: =SUM(G55:G58) -> 202125 | Q59: =Q29 -> Activation Commission | R59: =Inputs!F145 -> 20 | T59: =(D$53+D$58)*$R59 -> 20000000 | U59: =(E$53+E$58)*$R59 -> 3000000 | V59: =(F$53+F$58)*$R59 -> 3150000 | W59: =(G$53+G$58)*$R59 -> 3307500
A60: Total New Customers | D60: =SUM(D54,D59) -> 3666666.7 | E60: =SUM(E54,E59) -> 550000 | F60: =SUM(F54,F59) -> 577500 | G60: =SUM(G54,G59) -> 606375 | I60: =SUM(D40:G40) -> 2189934146 | J60: Chart 1 Profit | Q60: =Q30 -> Billing, Office, Bad Debt | R60: =Inputs!F146 -> 5.92 | T60: =(D$53+D$58)*$R60 -> 5920000 | U60: =(E$53+E$58)*$R60 -> 888000 | V60: =(F$53+F$58)*$R60 -> 932400 | W60: =(G$53+G$58)*$R60 -> 979020
I61: =SUM(L32:O32) -> 1506852766 | J61: Chart 2 Profit | Q61: =Q31 -> Recurring Commission | S61: =Inputs!F147 -> 0.15 | T61: =$S$61*T21 -> 80910000 | U61: =$S$61*U21 -> 84955500 | V61: =$S$61*V21 -> 89203275 | W61: =$S$61*W21 -> 93663439
I62: =SUM(T68:W68) -> 2037442427 | J62: Chart 3 Profit | Q62: =Q32 -> Wholesale Provider Cost | S62: =Inputs!F148 -> 16.64 | T62: =$S$62*12*T10 -> 199680000 | U62: =$S$62*12*U10 -> 209664000 | V62: =$S$62*12*V10 -> 220147200 | W62: =$S$62*12*W10 -> 231154560
I63: =MAX(I60:I62)-MIN(I60:I62) -> 683081380 | J63: Profit Range | Q63: =Q33 -> Marketing Expense | S63: =Inputs!F149 -> 3 | T63: =$S$62*T$10 -> 16640000 | U63: =$S$62*U$10 -> 17472000 | V63: =$S$62*V$10 -> 18345600 | W63: =$S$62*W$10 -> 19262880
I64: =AVERAGE(I60:I62) -> 1911409780 | J64: Average Profit | Q64: =Q34 -> Sales and General Administrative | S64: =Inputs!F150 -> 1 | T64: =$S$62*T$10 -> 16640000 | U64: =$S$62*U$10 -> 17472000 | V64: =$S$62*V$10 -> 18345600 | W64: =$S$62*W$10 -> 19262880
I65: =MAX(I60:I62)/I64-1 -> 0.14571672 | J65: Max to Average % | Q65: =Q35 -> Occupancy | S65: =Inputs!F151 -> 0.25 | T65: =$S$62*T$10 -> 16640000 | U65: =$S$62*U$10 -> 17472000 | V65: =$S$62*V$10 -> 18345600 | W65: =$S$62*W$10 -> 19262880
I66: =MIN(I60:I62)/I64-1 -> -0.21165373 | J66: Min to Average % | Q66: =A38 -> Total Costs | T66: =SUM(T26:T65) -> 8.6439e+08 | U66: =SUM(U26:U65) -> 6.768615e+08 | V66: =SUM(V26:V65) -> 7.1070457e+08 | W66: =SUM(W26:W65) -> 7.462398e+08
I67: =I63/I64 -> 0.35737045 | J67: Range
Q68: =A40 -> Total EBITDA | T68: =T23-T66 -> 3.9166667e+08 | U68: =U23-U66 -> 5.2205417e+08 | V68: =V23-V66 -> 5.4815687e+08 | W68: =W23-W66 -> 5.7556472e+08
T70: Monthly Figurres
T71: ARPU | U71: AVG COST | V71: Gross margin | W71: Margin
T72: =D44 -> 26.552901 | U72: =(SUM(T66:W66)/12/4)/(SUM(T11:W11)/4) -> 15.809475 | V72: =T72-U72 -> 10.743426 | W72: =V72/T72 -> 0.40460459
Q74: =A46 -> *Subscriber number assumes a monthly customer churn rate of 5%

Sheet Entity 3 Out
A1: Entity 3
A2: Revenue and Costs
A3: Base Case Projection
A5: Product Type 1 | C5: 2008-2009 | D5: 2009-2010 | E5: 2010-2011 | F5: 2011-2012
A6: Product 1 | C6: =Inputs!C170 -> 100 | D6: =C6+Inputs!D170 -> 150 | E6: =D6+Inputs!D170 -> 200 | F6: =E6+Inputs!D170 -> 250
A7: Product 2 | C7: =Inputs!C171 -> 150 | D7: =C7+Inputs!D171 -> 200 | E7: =D7+Inputs!D171 -> 250 | F7: =E7+Inputs!D171 -> 300
A8: Product 3 | C8: =Inputs!C172 -> 125 | D8: =C8+Inputs!D172 -> 175 | E8: =D8+Inputs!D172 -> 225 | F8: =E8+Inputs!D172 -> 275
A9: Total Subscribers | C9: =SUM(C6:C8) -> 375 | D9: =SUM(D6:D8) -> 525 | E9: =SUM(E6:E8) -> 675 | F9: =SUM(F6:F8) -> 825
A11: Revenue | B11: Monthly
A12: =A6&" at" -> Product 1 at | B12: =Inputs!E170 -> 3750 | C12: =$B12*C6 -> 375000 | D12: =$B12*D6 -> 562500 | E12: =$B12*E6 -> 750000 | F12: =$B12*F6 -> 937500
A13: =A7&" at" -> Product 2 at | B13: =Inputs!E171 -> 44.95 | C13: =$B13*C7 -> 6742.5 | D13: =$B13*D7 -> 8990 | E13: =$B13*E7 -> 11237.5 | F13: =$B13*F7 -> 13485
A14: =A8&" at" -> Product 3 at | B14: =Inputs!E172 -> 0 | C14: =$B14*C8 -> 0 | D14: =$B14*D8 -> 0 | E14: =$B14*E8 -> 0 | F14: =$B14*F8 -> 0
A15: Total Revenue | C15: =SUM(C12:C14) -> 381742.5 | D15: =SUM(D12:D14) -> 571490 | E15: =SUM(E12:E14) -> 761237.5 | F15: =SUM(F12:F14) -> 950985
A17: Cost of Goods
A18: =A12 -> Product 1 at | B18: =Inputs!F170 -> 3071.25 | C18: =$B18*C6 -> 307125 | D18: =$B18*D6 -> 460687.5 | E18: =$B18*E6 -> 614250 | F18: =$B18*F6 -> 767812.5
A19: =A13 -> Product 2 at | B19: =Inputs!F171 -> 32.0375 | C19: =$B19*C7 -> 4805.625 | D19: =$B19*D7 -> 6407.5 | E19: =$B19*E7 -> 8009.375 | F19: =$B19*F7 -> 9611.25
A20: =A14 -> Product 3 at | B20: =Inputs!F172 -> 0 | C20: =$B20*C8 -> 0 | D20: =$B20*D8 -> 0 | E20: =$B20*E8 -> 0 | F20: =$B20*F8 -> 0
A21: Total Cost of Goods | C21: =SUM(C18:C20) -> 311930.62 | D21: =SUM(D18:D20) -> 467095 | E21: =SUM(E18:E20) -> 622259.38 | F21: =SUM(F18:F20) -> 777423.75
A23: Operating Expenses | B23: Per Sub
A24: =Inputs!B174&"*" -> Sales and Marketing* | B24: =Inputs!C174 -> 45 | C24: =C9*$B24+Inputs!D174 -> 21875 | D24: =D9*$B24 -> 23625 | E24: =E9*$B24 -> 30375 | F24: =F9*$B24 -> 37125
A25: =Inputs!B175 -> General Administrative | B25: =Inputs!C175 -> 45 | C25: =C10*$B25 -> 0 | D25: =D10*$B25 -> 0 | E25: =E10*$B25 -> 0 | F25: =F10*$B25 -> 0
A26: =Inputs!B176 -> Occupancy | B26: =Inputs!C176 -> 45 | C26: =C11*$B26 -> 0 | D26: =D11*$B26 -> 0 | E26: =E11*$B26 -> 0 | F26: =F11*$B26 -> 0
A27: Total Operating Expenses | C27: =SUM(C24:C26) -> 21875 | D27: =SUM(D24:D26) -> 23625 | E27: =SUM(E24:E26) -> 30375 | F27: =SUM(F24:F26) -> 37125
A29: Total EBITDA | C29: =C15-C21-C27 -> 47936.875 | D29: =D15-D21-D27 -> 80770 | E29: =E15-E21-E27 -> 108603.12 | F29: =F15-F21-F27 -> 136436.25
A31: ="*An additional $"&Inputs!D174&" is included in year 1 for launch marketing." -> *An additional $5000 is included in year 1 for launch marketing.

Sheet Summary
A1: Based on Output #1 | H1: Based on Output #2 | O1: Based on Output #3 | V1: Based on Output #4
A2: All Three Entities | H2: =A2 -> All Three Entities | O2: =H2 -> All Three Entities | V2: =O2 -> All Three Entities
A3: Projected Operational Summary | H3: Projected Operational Summary | O3: Projected Operational Summary | V3: Projected Operational Summary
A5: Subscribers | C5: 2008-2009 | D5: 2009-2010 | E5: 2010-2011 | F5: 2011-2012 | H5: Subscribers | J5: 2008-2009 | K5: 2009-2010 | L5: 2010-2011 | M5: 2011-2012 | O5: Subscribers | Q5: 2008-2009 | R5: 2009-2010 | S5: 2010-2011 | T5: 2011-2012 | V5: Subscribers | X5: 2008-2009 | Y5: 2009-2010 | Z5: 2010-2011 | AA5: 2011-2012
A6: Entity 1 | H6: =A6 -> Entity 1 | O6: =H6 -> Entity 1 | V6: =O6 -> Entity 1
B7: ='Entity 1 Outputs'!I7 -> Brand 1 | C7: ='Entity 1 Outputs'!L7 -> 15000 | D7: ='Entity 1 Outputs'!M7 -> 21750 | E7: ='Entity 1 Outputs'!N7 -> 31537.5 | F7: ='Entity 1 Outputs'!O7 -> 45729.375 | I7: =B7 -> Brand 1 | J7: =C7 -> 15000 | K7: =D7 -> 21750 | L7: =E7 -> 31537.5 | M7: =F7 -> 45729.375 | P7: =B7 -> Brand 1 | Q7: =C7 -> 15000 | R7: =D7 -> 21750 | S7: =E7 -> 31537.5 | T7: =F7 -> 45729.375 | W7: =I7 -> Brand 1 | X7: =J7 -> 15000 | Y7: =K7 -> 21750 | Z7: =L7 -> 31537.5 | AA7: =M7 -> 45729.375
B8: ='Entity 1 Outputs'!I8 -> Brand 2 | C8: ='Entity 1 Outputs'!L8 -> 10000 | D8: ='Entity 1 Outputs'!M8 -> 14500 | E8: ='Entity 1 Outputs'!N8 -> 21025 | F8: ='Entity 1 Outputs'!O8 -> 30486.25 | I8: =B8 -> Brand 2 | J8: =C8 -> 10000 | K8: =D8 -> 14500 | L8: =E8 -> 21025 | M8: =F8 -> 30486.25 | P8: =B8 -> Brand 2 | Q8: =C8 -> 10000 | R8: =D8 -> 14500 | S8: =E8 -> 21025 | T8: =F8 -> 30486.25 | W8: =I8 -> Brand 2 | X8: =J8 -> 10000 | Y8: =K8 -> 14500 | Z8: =L8 -> 21025 | AA8: =M8 -> 30486.25
B9: ='Entity 1 Outputs'!I9 -> Brand 3 | C9: ='Entity 1 Outputs'!L9 -> 5000 | D9: ='Entity 1 Outputs'!M9 -> 7250 | E9: ='Entity 1 Outputs'!N9 -> 10512.5 | F9: ='Entity 1 Outputs'!O9 -> 15243.125 | I9: =B9 -> Brand 3 | J9: =C9 -> 5000 | K9: =D9 -> 7250 | L9: =E9 -> 10512.5 | M9: =F9 -> 15243.125 | P9: =B9 -> Brand 3 | Q9: =C9 -> 5000 | R9: =D9 -> 7250 | S9: =E9 -> 10512.5 | T9: =F9 -> 15243.125 | W9: =I9 -> Brand 3 | X9: =J9 -> 5000 | Y9: =K9 -> 7250 | Z9: =L9 -> 10512.5 | AA9: =M9 -> 15243.125
B10: ='Entity 1 Outputs'!I10 -> Brand 4 | C10: ='Entity 1 Outputs'!L10 -> 5000 | D10: ='Entity 1 Outputs'!M10 -> 7250 | E10: ='Entity 1 Outputs'!N10 -> 10512.5 | F10: ='Entity 1 Outputs'!O10 -> 15243.125 | I10: =B10 -> Brand 4 | J10: =C10 -> 5000 | K10: =D10 -> 7250 | L10: =E10 -> 10512.5 | M10: =F10 -> 15243.125 | P10: =B10 -> Brand 4 | Q10: =C10 -> 5000 | R10: =D10 -> 7250 | S10: =E10 -> 10512.5 | T10: =F10 -> 15243.125 | W10: =I10 -> Brand 4 | X10: =J10 -> 5000 | Y10: =K10 -> 7250 | Z10: =L10 -> 10512.5 | AA10: =M10 -> 15243.125
B11: ='Entity 1 Outputs'!I11 -> Brand 5 | C11: ='Entity 1 Outputs'!L11 -> 5000 | D11: ='Entity 1 Outputs'!M11 -> 7250 | E11: ='Entity 1 Outputs'!N11 -> 10512.5 | F11: ='Entity 1 Outputs'!O11 -> 15243.125 | I11: =B11 -> Brand 5 | J11: =C11 -> 5000 | K11: =D11 -> 7250 | L11: =E11 -> 10512.5 | M11: =F11 -> 15243.125 | P11: =B11 -> Brand 5 | Q11: =C11 -> 5000 | R11: =D11 -> 7250 | S11: =E11 -> 10512.5 | T11: =F11 -> 15243.125 | W11: =I11 -> Brand 5 | X11: =J11 -> 5000 | Y11: =K11 -> 7250 | Z11: =L11 -> 10512.5 | AA11: =M11 -> 15243.125
B12: ='Entity 1 Outputs'!I12 -> Brand 6 | C12: ='Entity 1 Outputs'!L12 -> 5000 | D12: ='Entity 1 Outputs'!M12 -> 7250 | E12: ='Entity 1 Outputs'!N12 -> 10512.5 | F12: ='Entity 1 Outputs'!O12 -> 15243.125 | I12: =B12 -> Brand 6 | J12: =C12 -> 5000 | K12: =D12 -> 7250 | L12: =E12 -> 10512.5 | M12: =F12 -> 15243.125 | P12: =B12 -> Brand 6 | Q12: =C12 -> 5000 | R12: =D12 -> 7250 | S12: =E12 -> 10512.5 | T12: =F12 -> 15243.125 | W12: =I12 -> Brand 6 | X12: =J12 -> 5000 | Y12: =K12 -> 7250 | Z12: =L12 -> 10512.5 | AA12: =M12 -> 15243.125
B13: ='Entity 1 Outputs'!I13 -> Brand 7 | C13: ='Entity 1 Outputs'!L13 -> 869.18 | D13: ='Entity 1 Outputs'!M13 -> 1260.311 | E13: ='Entity 1 Outputs'!N13 -> 1827.4509 | F13: ='Entity 1 Outputs'!O13 -> 2649.8039 | I13: =B13 -> Brand 7 | J13: =C13 -> 869.18 | K13: =D13 -> 1260.311 | L13: =E13 -> 1827.4509 | M13: =F13 -> 2649.8039 | P13: =B13 -> Brand 7 | Q13: =C13 -> 869.18 | R13: =D13 -> 1260.311 | S13: =E13 -> 1827.4509 | T13: =F13 -> 2649.8039 | W13: =I13 -> Brand 7 | X13: =J13 -> 869.18 | Y13: =K13 -> 1260.311 | Z13: =L13 -> 1827.4509 | AA13: =M13 -> 2649.8039
B14: ='Entity 1 Outputs'!I14 -> Brand 8 | C14: ='Entity 1 Outputs'!L14 -> 5000 | D14: ='Entity 1 Outputs'!M14 -> 7250 | E14: ='Entity 1 Outputs'!N14 -> 10512.5 | F14: ='Entity 1 Outputs'!O14 -> 15243.125 | I14: =B14 -> Brand 8 | J14: =C14 -> 5000 | K14: =D14 -> 7250 | L14: =E14 -> 10512.5 | M14: =F14 -> 15243.125 | P14: =B14 -> Brand 8 | Q14: =C14 -> 5000 | R14: =D14 -> 7250 | S14: =E14 -> 10512.5 | T14: =F14 -> 15243.125 | W14: =I14 -> Brand 8 | X14: =J14 -> 5000 | Y14: =K14 -> 7250 | Z14: =L14 -> 10512.5 | AA14: =M14 -> 15243.125
B15: ='Entity 1 Outputs'!I15 -> Brand 9 | C15: ='Entity 1 Outputs'!L15 -> 5000 | D15: ='Entity 1 Outputs'!M15 -> 7250 | E15: ='Entity 1 Outputs'!N15 -> 10512.5 | F15: ='Entity 1 Outputs'!O15 -> 15243.125 | I15: =B15 -> Brand 9 | J15: =C15 -> 5000 | K15: =D15 -> 7250 | L15: =E15 -> 10512.5 | M15: =F15 -> 15243.125 | P15: =B15 -> Brand 9 | Q15: =C15 -> 5000 | R15: =D15 -> 7250 | S15: =E15 -> 10512.5 | T15: =F15 -> 15243.125 | W15: =I15 -> Brand 9 | X15: =J15 -> 5000 | Y15: =K15 -> 7250 | Z15: =L15 -> 10512.5 | AA15: =M15 -> 15243.125
B16: Total | C16: ='Entity 1 Outputs'!L16 -> 55870 | D16: ='Entity 1 Outputs'!M16 -> 81010.311 | E16: ='Entity 1 Outputs'!N16 -> 117464.95 | F16: ='Entity 1 Outputs'!O16 -> 170324.18 | I16: =B16 -> Total | J16: =C16 -> 55870 | K16: =D16 -> 81010.311 | L16: =E16 -> 117464.95 | M16: =F16 -> 170324.18 | P16: =B16 -> Total | Q16: =C16 -> 55870 | R16: =D16 -> 81010.311 | S16: =E16 -> 117464.95 | T16: =F16 -> 170324.18 | W16: =I16 -> Total | X16: =J16 -> 55870 | Y16: =K16 -> 81010.311 | Z16: =L16 -> 117464.95 | AA16: =M16 -> 170324.18
A18: Entity 2 | H18: =A18 -> Entity 2 | O18: =H18 -> Entity 2 | V18: =O18 -> Entity 2
B19: ='Entity 2 Out'!A7 -> Product 1 | C19: ='Entity 2 Out'!D7 -> 2133333.3 | D19: ='Entity 2 Out'!E7 -> 2240000 | E19: ='Entity 2 Out'!F7 -> 2352000 | F19: ='Entity 2 Out'!G7 -> 2469600 | I19: =B19 -> Product 1 | J19: =C19 -> 2133333.3 | K19: =D19 -> 2240000 | L19: =E19 -> 2352000 | M19: =F19 -> 2469600 | P19: =B19 -> Product 1 | Q19: =C19 -> 2133333.3 | R19: =D19 -> 2240000 | S19: =E19 -> 2352000 | T19: =F19 -> 2469600 | W19: =I19 -> Product 1 | X19: =J19 -> 2133333.3 | Y19: =K19 -> 2240000 | Z19: =L19 -> 2352000 | AA19: =M19 -> 2469600
B20: ='Entity 2 Out'!A8 -> Product 2 | C20: ='Entity 2 Out'!D8 -> 266666.67 | D20: ='Entity 2 Out'!E8 -> 280000 | E20: ='Entity 2 Out'!F8 -> 294000 | F20: ='Entity 2 Out'!G8 -> 308700 | I20: =B20 -> Product 2 | J20: =C20 -> 266666.67 | K20: =D20 -> 280000 | L20: =E20 -> 294000 | M20: =F20 -> 308700 | P20: =B20 -> Product 2 | Q20: =C20 -> 266666.67 | R20: =D20 -> 280000 | S20: =E20 -> 294000 | T20: =F20 -> 308700 | W20: =I20 -> Product 2 | X20: =J20 -> 266666.67 | Y20: =K20 -> 280000 | Z20: =L20 -> 294000 | AA20: =M20 -> 308700
B21: ='Entity 2 Out'!A9 -> Product 3 | C21: ='Entity 2 Out'!D9 -> 266666.67 | D21: ='Entity 2 Out'!E9 -> 280000 | E21: ='Entity 2 Out'!F9 -> 294000 | F21: ='Entity 2 Out'!G9 -> 308700 | I21: =B21 -> Product 3 | J21: =C21 -> 266666.67 | K21: =D21 -> 280000 | L21: =E21 -> 294000 | M21: =F21 -> 308700 | P21: =B21 -> Product 3 | Q21: =C21 -> 266666.67 | R21: =D21 -> 280000 | S21: =E21 -> 294000 | T21: =F21 -> 308700 | W21: =I21 -> Product 3 | X21: =J21 -> 266666.67 | Y21: =K21 -> 280000 | Z21: =L21 -> 294000 | AA21: =M21 -> 308700
B22: ='Entity 2 Out'!A10 -> Prodcut 4 | C22: ='Entity 2 Out'!D10 -> 1000000 | D22: ='Entity 2 Out'!E10 -> 1050000 | E22: ='Entity 2 Out'!F10 -> 1102500 | F22: ='Entity 2 Out'!G10 -> 1157625 | I22: =B22 -> Prodcut 4 | J22: =C22 -> 1000000 | K22: =D22 -> 1050000 | L22: =E22 -> 1102500 | M22: =F22 -> 1157625 | P22: =B22 -> Prodcut 4 | Q22: =C22 -> 1000000 | R22: =D22 -> 1050000 | S22: =E22 -> 1102500 | T22: =F22 -> 1157625 | W22: =I22 -> Prodcut 4 | X22: =J22 -> 1000000 | Y22: =K22 -> 1050000 | Z22: =L22 -> 1102500 | AA22: =M22 -> 1157625
B23: Total | C23: ='Entity 2 Out'!D11 -> 3666667 | D23: ='Entity 2 Out'!E11 -> 3850000 | E23: ='Entity 2 Out'!F11 -> 4042500 | F23: ='Entity 2 Out'!G11 -> 4244625 | I23: Total | J23: =C23 -> 3666667 | K23: =D23 -> 3850000 | L23: =E23 -> 4042500 | M23: =F23 -> 4244625 | P23: =B23 -> Total | Q23: =C23 -> 3666667 | R23: =D23 -> 3850000 | S23: =E23 -> 4042500 | T23: =F23 -> 4244625 | W23: =I23 -> Total | X23: =J23 -> 3666667 | Y23: =K23 -> 3850000 | Z23: =L23 -> 4042500 | AA23: =M23 -> 4244625
A25: Entity 3 | H25: =A25 -> Entity 3 | O25: =H25 -> Entity 3 | V25: =O25 -> Entity 3
B26: ='Entity 3 Out'!A6 -> Product 1 | C26: ='Entity 3 Out'!C6 -> 100 | D26: ='Entity 3 Out'!D6 -> 150 | E26: ='Entity 3 Out'!E6 -> 200 | F26: ='Entity 3 Out'!F6 -> 250 | I26: =B26 -> Product 1 | J26: =C26 -> 100 | K26: =D26 -> 150 | L26: =E26 -> 200 | M26: =F26 -> 250 | P26: =I26 -> Product 1 | Q26: =C26 -> 100 | R26: =D26 -> 150 | S26: =E26 -> 200 | T26: =F26 -> 250 | W26: =P26 -> Product 1 | X26: =J26 -> 100 | Y26: =K26 -> 150 | Z26: =L26 -> 200 | AA26: =M26 -> 250
B27: ='Entity 3 Out'!A7 -> Product 2 | C27: ='Entity 3 Out'!C7 -> 150 | D27: ='Entity 3 Out'!D7 -> 200 | E27: ='Entity 3 Out'!E7 -> 250 | F27: ='Entity 3 Out'!F7 -> 300 | I27: =B27 -> Product 2 | J27: =C27 -> 150 | K27: =D27 -> 200 | L27: =E27 -> 250 | M27: =F27 -> 300 | P27: =I27 -> Product 2 | Q27: =C27 -> 150 | R27: =D27 -> 200 | S27: =E27 -> 250 | T27: =F27 -> 300 | W27: =P27 -> Product 2 | X27: =J27 -> 150 | Y27: =K27 -> 200 | Z27: =L27 -> 250 | AA27: =M27 -> 300
B28: ='Entity 3 Out'!A8 -> Product 3 | C28: ='Entity 3 Out'!C8 -> 125 | D28: ='Entity 3 Out'!D8 -> 175 | E28: ='Entity 3 Out'!E8 -> 225 | F28: ='Entity 3 Out'!F8 -> 275 | I28: =B28 -> Product 3 | J28: =C28 -> 125 | K28: =D28 -> 175 | L28: =E28 -> 225 | M28: =F28 -> 275 | P28: =I28 -> Product 3 | Q28: =C28 -> 125 | R28: =D28 -> 175 | S28: =E28 -> 225 | T28: =F28 -> 275 | W28: =P28 -> Product 3 | X28: =J28 -> 125 | Y28: =K28 -> 175 | Z28: =L28 -> 225 | AA28: =M28 -> 275
B29: Total | C29: ='Entity 3 Out'!C9 -> 375 | D29: ='Entity 3 Out'!D9 -> 525 | E29: ='Entity 3 Out'!E9 -> 675 | F29: ='Entity 3 Out'!F9 -> 825 | I29: Total | J29: =C29 -> 375 | K29: =D29 -> 525 | L29: =E29 -> 675 | M29: =F29 -> 825 | P29: Total | Q29: =C29 -> 375 | R29: =D29 -> 525 | S29: =E29 -> 675 | T29: =F29 -> 825 | W29: Total | X29: =J29 -> 375 | Y29: =K29 -> 525 | Z29: =L29 -> 675 | AA29: =M29 -> 825
A31: Revenue | H31: Revenue | O31: Revenue | V31: Revenue
A32: =A6 -> Entity 1 | C32: ='Entity 1 Outputs'!L29 -> 34033756 | D32: ='Entity 1 Outputs'!M29 -> 48087794 | E32: ='Entity 1 Outputs'!N29 -> 69727374 | F32: ='Entity 1 Outputs'!O29 -> 101104628 | H32: =H6 -> Entity 1 | J32: ='Entity 1 Outputs'!L29 -> 34033756 | K32: ='Entity 1 Outputs'!M29 -> 48087794 | L32: ='Entity 1 Outputs'!N29 -> 69727374 | M32: ='Entity 1 Outputs'!O29 -> 101104628 | O32: =O6 -> Entity 1 | Q32: ='Entity 1 Outputs'!T29 -> 34033756 | R32: ='Entity 1 Outputs'!U29 -> 48087794 | S32: ='Entity 1 Outputs'!V29 -> 69727374 | T32: ='Entity 1 Outputs'!W29 -> 101104628 | V32: =V6 -> Entity 1 | X32: ='Entity 1 Outputs'!AB29 -> 34033756 | Y32: ='Entity 1 Outputs'!AC29 -> 48087794 | Z32: ='Entity 1 Outputs'!AD29 -> 69727374 | AA32: ='Entity 1 Outputs'!AE29 -> 101104628
A33: =A18 -> Entity 2 | C33: ='Entity 2 Out'!D23 -> 1256056667 | D33: ='Entity 2 Out'!E23 -> 1198915667 | E33: ='Entity 2 Out'!F23 -> 1258861450 | F33: ='Entity 2 Out'!G23 -> 1321804523 | H33: =H18 -> Entity 2 | J33: ='Entity 2 Out'!L23 -> 1256056667 | K33: ='Entity 2 Out'!M23 -> 1198915667 | L33: ='Entity 2 Out'!N23 -> 1258861450 | M33: ='Entity 2 Out'!O23 -> 1321804523 | O33: =O18 -> Entity 2 | Q33: ='Entity 2 Out'!T23 -> 1256056667 | R33: ='Entity 2 Out'!U23 -> 1198915667 | S33: ='Entity 2 Out'!V23 -> 1258861450 | T33: ='Entity 2 Out'!W23 -> 1321804523 | V33: =V18 -> Entity 2 | X33: =Q33 -> 1256056667 | Y33: =R33 -> 1198915667 | Z33: =S33 -> 1258861450 | AA33: =T33 -> 1321804523
A34: =A25 -> Entity 3 | C34: ='Entity 3 Out'!C15 -> 381742.5 | D34: ='Entity 3 Out'!D15 -> 571490 | E34: ='Entity 3 Out'!E15 -> 761237.5 | F34: ='Entity 3 Out'!F15 -> 950985 | H34: =H25 -> Entity 3 | J34: =C34 -> 381742.5 | K34: =D34 -> 571490 | L34: =E34 -> 761237.5 | M34: =F34 -> 950985 | O34: =O25 -> Entity 3 | Q34: =C34 -> 381742.5 | R34: =D34 -> 571490 | S34: =E34 -> 761237.5 | T34: =F34 -> 950985 | V34: =V25 -> Entity 3 | X34: =Q34 -> 381742.5 | Y34: =R34 -> 571490 | Z34: =S34 -> 761237.5 | AA34: =T34 -> 950985
B35: Total | C35: =SUM(C32:C34) -> 1.2904722e+09 | D35: =SUM(D32:D34) -> 1.247575e+09 | E35: =SUM(E32:E34) -> 1.3293501e+09 | F35: =SUM(F32:F34) -> 1423860136 | I35: Total | J35: =SUM(J32:J34) -> 1.2904722e+09 | K35: =SUM(K32:K34) -> 1.247575e+09 | L35: =SUM(L32:L34) -> 1.3293501e+09 | M35: =SUM(M32:M34) -> 1423860136 | P35: Total | Q35: =SUM(Q32:Q34) -> 1.2904722e+09 | R35: =SUM(R32:R34) -> 1.247575e+09 | S35: =SUM(S32:S34) -> 1.3293501e+09 | T35: =SUM(T32:T34) -> 1423860136 | W35: Total | X35: =SUM(X32:X34) -> 1.2904722e+09 | Y35: =SUM(Y32:Y34) -> 1.247575e+09 | Z35: =SUM(Z32:Z34) -> 1.3293501e+09 | AA35: =SUM(AA32:AA34) -> 1423860136
A37: Costs | H37: Costs | O37: Costs | V37: Costs
A38: =A32 -> Entity 1 | C38: ='Entity 1 Outputs'!L47 -> 23670636 | D38: ='Entity 1 Outputs'!M47 -> 32534518 | E38: ='Entity 1 Outputs'!N47 -> 47167323 | F38: ='Entity 1 Outputs'!O47 -> 68384697 | H38: =H32 -> Entity 1 | J38: ='Entity 1 Outputs'!L47 -> 23670636 | K38: ='Entity 1 Outputs'!M47 -> 32534518 | L38: ='Entity 1 Outputs'!N47 -> 47167323 | M38: ='Entity 1 Outputs'!O47 -> 68384697 | O38: =O32 -> Entity 1 | Q38: ='Entity 1 Outputs'!T49 -> 23622790 | R38: ='Entity 1 Outputs'!U49 -> 29156673 | S38: ='Entity 1 Outputs'!V49 -> 42269375 | T38: ='Entity 1 Outputs'!W49 -> 61282737 | V38: =V32 -> Entity 1 | X38: ='Entity 1 Outputs'!AB36 -> 19092686 | Y38: ='Entity 1 Outputs'!AC36 -> 27683999 | Z38: ='Entity 1 Outputs'!AD36 -> 40141798 | AA38: ='Entity 1 Outputs'!AE36 -> 58205608
A39: =A33 -> Entity 2 | C39: ='Entity 2 Out'!D38 -> 817310000 | D39: ='Entity 2 Out'!E38 -> 643424000 | E39: ='Entity 2 Out'!F38 -> 675595200 | F39: ='Entity 2 Out'!G38 -> 709374960 | H39: =H33 -> Entity 2 | J39: ='Entity 2 Out'!L30 -> 818720000 | K39: ='Entity 2 Out'!M30 -> 859656000 | L39: ='Entity 2 Out'!N30 -> 902638800 | M39: ='Entity 2 Out'!O30 -> 947770740 | O39: =O33 -> Entity 2 | Q39: ='Entity 2 Out'!T66 -> 864390000 | R39: ='Entity 2 Out'!U66 -> 676861500 | S39: ='Entity 2 Out'!V66 -> 710704575 | T39: ='Entity 2 Out'!W66 -> 7.462398e+08 | V39: =V33 -> Entity 2 | X39: =Q39 -> 864390000 | Y39: =R39 -> 676861500 | Z39: =S39 -> 710704575 | AA39: =T39 -> 7.462398e+08
A40: =A34 -> Entity 3 | C40: ='Entity 3 Out'!C21+'Entity 3 Out'!C27 -> 333805.62 | D40: ='Entity 3 Out'!D21+'Entity 3 Out'!D27 -> 490720 | E40: ='Entity 3 Out'!E21+'Entity 3 Out'!E27 -> 652634.38 | F40: ='Entity 3 Out'!F21+'Entity 3 Out'!F27 -> 814548.75 | H40: =H34 -> Entity 3 | J40: =C40 -> 333805.62 | K40: =D40 -> 490720 | L40: =E40 -> 652634.38 | M40: =F40 -> 814548.75 | O40: =O34 -> Entity 3 | Q40: =C40 -> 333805.62 | R40: =D40 -> 490720 | S40: =E40 -> 652634.38 | T40: =F40 -> 814548.75 | V40: =V34 -> Entity 3 | X40: =Q40 -> 333805.62 | Y40: =R40 -> 490720 | Z40: =S40 -> 652634.38 | AA40: =T40 -> 814548.75
B41: Total | C41: =SUM(C38:C40) -> 8.4131444e+08 | D41: =SUM(D38:D40) -> 6.7644924e+08 | E41: =SUM(E38:E40) -> 7.2341516e+08 | F41: =SUM(F38:F40) -> 7.7857421e+08 | I41: Total | J41: =SUM(J38:J40) -> 8.4272444e+08 | K41: =SUM(K38:K40) -> 8.9268124e+08 | L41: =SUM(L38:L40) -> 9.5045876e+08 | M41: =SUM(M38:M40) -> 1.01697e+09 | P41: Total | Q41: =SUM(Q38:Q40) -> 8.883466e+08 | R41: =SUM(R38:R40) -> 7.0650889e+08 | S41: =SUM(S38:S40) -> 7.5362658e+08 | T41: =SUM(T38:T40) -> 8.0833709e+08 | W41: Total | X41: =SUM(X38:X40) -> 8.8381649e+08 | Y41: =SUM(Y38:Y40) -> 7.0503622e+08 | Z41: =SUM(Z38:Z40) -> 7.5149901e+08 | AA41: =SUM(AA38:AA40) -> 8.0525996e+08
A43: EBITDA | H43: EBITDA | O43: EBITDA | V43: EBITDA
A44: =A38 -> Entity 1 | C44: ='Entity 1 Outputs'!L49 -> 10363120 | D44: ='Entity 1 Outputs'!M49 -> 15553277 | E44: ='Entity 1 Outputs'!N49 -> 22560051 | F44: ='Entity 1 Outputs'!O49 -> 32719931 | H44: =H38 -> Entity 1 | J44: ='Entity 1 Outputs'!L49 -> 10363120 | K44: ='Entity 1 Outputs'!M49 -> 15553277 | L44: ='Entity 1 Outputs'!N49 -> 22560051 | M44: ='Entity 1 Outputs'!O49 -> 32719931 | O44: =O38 -> Entity 1 | Q44: ='Entity 1 Outputs'!T51 -> 10410966 | R44: ='Entity 1 Outputs'!U51 -> 18931122 | S44: ='Entity 1 Outputs'!V51 -> 27457999 | T44: ='Entity 1 Outputs'!W51 -> 39821891 | V44: =V38 -> Entity 1 | X44: ='Entity 1 Outputs'!AB38 -> 14941069 | Y44: ='Entity 1 Outputs'!AC38 -> 20403795 | Z44: ='Entity 1 Outputs'!AD38 -> 29585576 | AA44: ='Entity 1 Outputs'!AE38 -> 42899020
A45: =A39 -> Entity 2 | C45: ='Entity 2 Out'!D40 -> 4.3874667e+08 | D45: ='Entity 2 Out'!E40 -> 5.5549167e+08 | E45: ='Entity 2 Out'!F40 -> 583266250 | F45: ='Entity 2 Out'!G40 -> 6.1242956e+08 | H45: =H39 -> Entity 2 | J45: ='Entity 2 Out'!L32 -> 4.3733667e+08 | K45: ='Entity 2 Out'!M32 -> 3.3925967e+08 | L45: ='Entity 2 Out'!N32 -> 356222650 | M45: ='Entity 2 Out'!O32 -> 3.7403378e+08 | O45: =O39 -> Entity 2 | Q45: ='Entity 2 Out'!T68 -> 3.9166667e+08 | R45: ='Entity 2 Out'!U68 -> 5.2205417e+08 | S45: ='Entity 2 Out'!V68 -> 548156875 | T45: ='Entity 2 Out'!W68 -> 5.7556472e+08 | V45: =V39 -> Entity 2 | X45: =Q45 -> 3.9166667e+08 | Y45: =R45 -> 5.2205417e+08 | Z45: =S45 -> 548156875 | AA45: =T45 -> 5.7556472e+08
A46: =A40 -> Entity 3 | C46: ='Entity 3 Out'!C29 -> 47936.875 | D46: ='Entity 3 Out'!D29 -> 80770 | E46: ='Entity 3 Out'!E29 -> 108603.12 | F46: ='Entity 3 Out'!F29 -> 136436.25 | H46: =H40 -> Entity 3 | J46: =C46 -> 47936.875 | K46: =D46 -> 80770 | L46: =E46 -> 108603.12 | M46: =F46 -> 136436.25 | O46: =O40 -> Entity 3 | Q46: =C46 -> 47936.875 | R46: =D46 -> 80770 | S46: =E46 -> 108603.12 | T46: =F46 -> 136436.25 | V46: =V40 -> Entity 3 | X46: =Q46 -> 47936.875 | Y46: =R46 -> 80770 | Z46: =S46 -> 108603.12 | AA46: =T46 -> 136436.25
B47: =B41 -> Total | C47: =SUM(C44:C46) -> 4.4915772e+08 | D47: =SUM(D44:D46) -> 5.7112571e+08 | E47: =SUM(E44:E46) -> 6.059349e+08 | F47: =SUM(F44:F46) -> 6.4528593e+08 | I47: =I41 -> Total | J47: =SUM(J44:J46) -> 4.4774772e+08 | K47: =SUM(K44:K46) -> 3.5489371e+08 | L47: =SUM(L44:L46) -> 3.788913e+08 | M47: =SUM(M44:M46) -> 4.0689015e+08 | P47: =P41 -> Total | Q47: =SUM(Q44:Q46) -> 4.0212557e+08 | R47: =SUM(R44:R46) -> 5.4106606e+08 | S47: =SUM(S44:S46) -> 5.7572348e+08 | T47: =SUM(T44:T46) -> 6.1552305e+08 | W47: =W41 -> Total | X47: =SUM(X44:X46) -> 4.0665567e+08 | Y47: =SUM(Y44:Y46) -> 5.4253873e+08 | Z47: =SUM(Z44:Z46) -> 5.7785105e+08 | AA47: =SUM(AA44:AA46) -> 6.1860018e+08

Sheet Valuation
A1: Year 1 Valuation Analysis | H1: Year 4 Valuation Analysis
A2: =Summary!A2 -> All Three Entities | H2: =A2 -> All Three Entities
A4: Entity 1 | H4: =A4 -> Entity 1
B5: Average Customer Worth | C5: =Inputs!C180 -> 1000 | E5: Joint-Venture | F5: =Inputs!F180 -> 0 | I5: =B5 -> Average Customer Worth | J5: =C5 -> 1000 | L5: Joint-Venture | M5: =F5 -> 0
C7: Year 1 Subs | D7: Subscriber Worth | E7: Joint-Venture Value | F7: Retained Value | J7: Year 4 Subs | K7: Subscriber Worth | L7: Joint-Venture Value | M7: Retained Value
B8: ='Entity 1 Outputs'!Q7 -> Brand 1 | C8: ='Entity 1 Outputs'!T7 -> 15000 | D8: =$C$5*C8 -> 15000000 | E8: =D8*Inputs!$F$180 -> 0 | F8: =D8-E8 -> 15000000 | I8: =B8 -> Brand 1 | J8: ='Entity 1 Outputs'!W7 -> 45729.375 | K8: =$C$5*J8 -> 45729375 | L8: =K8*Inputs!$F$180 -> 0 | M8: =K8-L8 -> 45729375
B9: ='Entity 1 Outputs'!Q8 -> Brand 2 | C9: ='Entity 1 Outputs'!T8 -> 10000 | D9: =$C$5*C9 -> 10000000 | E9: =D9*Inputs!$F$180 -> 0 | F9: =D9-E9 -> 10000000 | I9: =B9 -> Brand 2 | J9: ='Entity 1 Outputs'!W8 -> 30486.25 | K9: =$C$5*J9 -> 30486250 | L9: =K9*Inputs!$F$180 -> 0 | M9: =K9-L9 -> 30486250
B10: ='Entity 1 Outputs'!Q9 -> Brand 3 | C10: ='Entity 1 Outputs'!T9 -> 5000 | D10: =$C$5*C10 -> 5000000 | E10: =D10*Inputs!$F$180 -> 0 | F10: =D10-E10 -> 5000000 | I10: =B10 -> Brand 3 | J10: ='Entity 1 Outputs'!W9 -> 15243.125 | K10: =$C$5*J10 -> 15243125 | L10: =K10*Inputs!$F$180 -> 0 | M10: =K10-L10 -> 15243125
B11: ='Entity 1 Outputs'!Q10 -> Brand 4 | C11: ='Entity 1 Outputs'!T10 -> 5000 | D11: =$C$5*C11 -> 5000000 | E11: =D11*Inputs!$F$180 -> 0 | F11: =D11-E11 -> 5000000 | I11: =B11 -> Brand 4 | J11: ='Entity 1 Outputs'!W10 -> 15243.125 | K11: =$C$5*J11 -> 15243125 | L11: =K11*Inputs!$F$180 -> 0 | M11: =K11-L11 -> 15243125
B12: ='Entity 1 Outputs'!Q11 -> Brand 5 | C12: ='Entity 1 Outputs'!T11 -> 5000 | D12: =$C$5*C12 -> 5000000 | E12: =D12*Inputs!$F$180 -> 0 | F12: =D12-E12 -> 5000000 | I12: =B12 -> Brand 5 | J12: ='Entity 1 Outputs'!W11 -> 15243.125 | K12: =$C$5*J12 -> 15243125 | L12: =K12*Inputs!$F$180 -> 0 | M12: =K12-L12 -> 15243125
B13: ='Entity 1 Outputs'!Q12 -> Brand 6 | C13: ='Entity 1 Outputs'!T12 -> 5000 | D13: =$C$5*C13 -> 5000000 | E13: =D13*Inputs!$F$180 -> 0 | F13: =D13-E13 -> 5000000 | I13: =B13 -> Brand 6 | J13: ='Entity 1 Outputs'!W12 -> 15243.125 | K13: =$C$5*J13 -> 15243125 | L13: =K13*Inputs!$F$180 -> 0 | M13: =K13-L13 -> 15243125
B14: ='Entity 1 Outputs'!Q13 -> Brand 7 | C14: ='Entity 1 Outputs'!T13 -> 869.18 | D14: =$C$5*C14 -> 869180 | E14: =D14*Inputs!$F$180 -> 0 | F14: =D14-E14 -> 869180 | I14: =B14 -> Brand 7 | J14: ='Entity 1 Outputs'!W13 -> 2649.8039 | K14: =$C$5*J14 -> 2649803.9 | L14: =K14*Inputs!$F$180 -> 0 | M14: =K14-L14 -> 2649803.9
B15: ='Entity 1 Outputs'!Q14 -> Brand 8 | C15: ='Entity 1 Outputs'!T14 -> 5000 | D15: =$C$5*C15 -> 5000000 | E15: =D15*Inputs!$F$180 -> 0 | F15: =D15-E15 -> 5000000 | I15: =B15 -> Brand 8 | J15: ='Entity 1 Outputs'!W14 -> 15243.125 | K15: =$C$5*J15 -> 15243125 | L15: =K15*Inputs!$F$180 -> 0 | M15: =K15-L15 -> 15243125
B16: ='Entity 1 Outputs'!Q15 -> Brand 9 | C16: ='Entity 1 Outputs'!T15 -> 5000 | D16: =$C$5*C16 -> 5000000 | E16: =D16*Inputs!$F$180 -> 0 | F16: =D16-E16 -> 5000000 | I16: =B16 -> Brand 9 | J16: ='Entity 1 Outputs'!W15 -> 15243.125 | K16: =$C$5*J16 -> 15243125 | L16: =K16*Inputs!$F$180 -> 0 | M16: =K16-L16 -> 15243125
B17: Total | C17: ='Entity 1 Outputs'!T16 -> 55869.18 | D17: =$C$5*C17 -> 55869180 | E17: =D17*Inputs!$F$180 -> 0 | F17: =D17-E17 -> 55869180 | I17: Total | J17: =SUM(J8:J16) -> 170324.18 | K17: =$C$5*J17 -> 1.7032418e+08 | L17: =K17*Inputs!$F$180 -> 0 | M17: =K17-L17 -> 1.7032418e+08
A19: Entity 2 | H19: =A19 -> Entity 2
B20: Average Non-Com. Cust. Worth | D20: =Inputs!C181 -> 1000 | E20: Joint-Venture | F20: =Inputs!F181 -> 0.5 | I20: =B20 -> Average Non-Com. Cust. Worth | K20: =D20 -> 1000 | L20: Joint-Venture | M20: =F20 -> 0.5
B21: Average Com. Cust Worth | D21: =Inputs!D181 -> 1000 | I21: =B21 -> Average Com. Cust Worth | K21: =D21 -> 1000
C23: =C7 -> Year 1 Subs | D23: =D7 -> Subscriber Worth | E23: =E7 -> Joint-Venture Value | F23: =F7 -> Retained Value | J23: =J7 -> Year 4 Subs | K23: =K7 -> Subscriber Worth | L23: =L7 -> Joint-Venture Value | M23: =M7 -> Retained Value
B24: ='Entity 2 Out'!Q7 -> Product 1 | C24: ='Entity 2 Out'!T7 -> 2133333.3 | D24: =$D$20*C24 -> 2133333333 | E24: =$F$20*D24 -> 1.0666667e+09 | F24: =D24-E24 -> 1.0666667e+09 | I24: =B24 -> Product 1 | J24: ='Entity 2 Out'!W7 -> 2469600 | K24: =$D$20*J24 -> 2469600000 | L24: =$F$20*K24 -> 1234800000 | M24: =K24-L24 -> 1234800000
B25: ='Entity 2 Out'!Q8 -> Product 2 | C25: ='Entity 2 Out'!T8 -> 266666.67 | D25: =$D$20*C25 -> 2.6666667e+08 | E25: =$F$20*D25 -> 1.3333333e+08 | F25: =D25-E25 -> 1.3333333e+08 | I25: =B25 -> Product 2 | J25: ='Entity 2 Out'!W8 -> 308700 | K25: =$D$20*J25 -> 308700000 | L25: =$F$20*K25 -> 154350000 | M25: =K25-L25 -> 154350000
B26: ='Entity 2 Out'!Q9 -> Product 3 | C26: ='Entity 2 Out'!T9 -> 266666.67 | D26: =$D$20*C26 -> 2.6666667e+08 | E26: =$F$20*D26 -> 1.3333333e+08 | F26: =D26-E26 -> 1.3333333e+08 | I26: =B26 -> Product 3 | J26: ='Entity 2 Out'!W9 -> 308700 | K26: =$D$20*J26 -> 308700000 | L26: =$F$20*K26 -> 154350000 | M26: =K26-L26 -> 154350000
B27: ='Entity 2 Out'!Q10 -> Prodcut 4 | C27: ='Entity 2 Out'!T10 -> 1000000 | D27: =D21*C27 -> 1000000000 | E27: =$F$20*D27 -> 500000000 | F27: =D27-E27 -> 500000000 | I27: =B27 -> Prodcut 4 | J27: ='Entity 2 Out'!W10 -> 1157625 | K27: =K21*J27 -> 1157625000 | L27: =$F$20*K27 -> 578812500 | M27: =K27-L27 -> 578812500
B28: Total | C28: ='Entity 2 Out'!T11 -> 3666666.7 | D28: =SUM(D24:D27) -> 3.6666667e+09 | E28: =SUM(E24:E27) -> 1.8333333e+09 | F28: =SUM(F24:F27) -> 1.8333333e+09 | I28: Total | J28: =SUM(J24:J27) -> 4244625 | K28: =SUM(K24:K27) -> 4244625000 | L28: =SUM(L24:L27) -> 2122312500 | M28: =SUM(M24:M27) -> 2122312500
A30: Entity 3 | H30: =A30 -> Entity 3
B31: ="Based on "&Inputs!E182&"x earnings" -> Based on 5x earnings | E31: Joint-Venture | F31: =Inputs!F182 -> 0.5 | I31: ="Based on "&Inputs!E182&"x earnings" -> Based on 5x earnings | L31: Joint-Venture | M31: =F31 -> 0.5
C33: Year 1 Earnings | D33: Value | E33: =E23 -> Joint-Venture Value | F33: =F23 -> Retained Value | J33: Year 4 Earnings | K33: Value | L33: =L23 -> Joint-Venture Value | M33: =M23 -> Retained Value
B34: Product 1 | C34: ='Entity 3 Out'!C12 -> 375000 | D34: =Inputs!$E$182*C34 -> 1875000 | E34: =$F$31*D34 -> 937500 | F34: =D34-E34 -> 937500 | I34: =B34 -> Product 1 | J34: ='Entity 3 Out'!F12 -> 937500 | K34: =Inputs!$E$182*J34 -> 4687500 | L34: =$F$31*K34 -> 2343750 | M34: =K34-L34 -> 2343750
B35: Product 2 | C35: ='Entity 3 Out'!C13 -> 6742.5 | D35: =Inputs!$E$182*C35 -> 33712.5 | E35: =$F$31*D35 -> 16856.25 | F35: =D35-E35 -> 16856.25 | I35: =B35 -> Product 2 | J35: ='Entity 3 Out'!F13 -> 13485 | K35: =Inputs!$E$182*J35 -> 67425 | L35: =$F$31*K35 -> 33712.5 | M35: =K35-L35 -> 33712.5
B36: Product 3 | C36: ='Entity 3 Out'!C14 -> 0 | D36: =Inputs!$E$182*C36 -> 0 | E36: =$F$31*D36 -> 0 | F36: =D36-E36 -> 0 | I36: =B36 -> Product 3 | J36: ='Entity 3 Out'!F14 -> 0 | K36: =Inputs!$E$182*J36 -> 0 | L36: =$F$31*K36 -> 0 | M36: =K36-L36 -> 0
B37: Total | C37: =SUM(C34:C36) -> 381742.5 | D37: =SUM(D34:D36) -> 1908712.5 | E37: =SUM(E34:E36) -> 954356.25 | F37: =SUM(F34:F36) -> 954356.25 | I37: Total | J37: =SUM(J34:J36) -> 950985 | K37: =SUM(K34:K36) -> 4754925 | L37: =SUM(L34:L36) -> 2377462.5 | M37: =SUM(M34:M36) -> 2377462.5
A39: =A2 -> All Three Entities | H39: =A39 -> All Three Entities
D40: Total Value | E40: =E7 -> Joint-Venture Value | F40: =F7 -> Retained Value | K40: Total Value | L40: =L7 -> Joint-Venture Value | M40: =M7 -> Retained Value
C41: Entity 1 | D41: =D17 -> 55869180 | E41: =E17 -> 0 | F41: =F17 -> 55869180 | J41: =C41 -> Entity 1 | K41: =K17 -> 1.7032418e+08 | L41: =L17 -> 0 | M41: =M17 -> 1.7032418e+08
C42: Entity 2 | D42: =D28 -> 3.6666667e+09 | E42: =E28 -> 1.8333333e+09 | F42: =F28 -> 1.8333333e+09 | J42: =C42 -> Entity 2 | K42: =K28 -> 4244625000 | L42: =L28 -> 2122312500 | M42: =M28 -> 2122312500
C43: Entity 3 | D43: =D37 -> 1908712.5 | E43: =E37 -> 954356.25 | F43: =F37 -> 954356.25 | J43: =C43 -> Entity 3 | K43: =K37 -> 4754925 | L43: =L37 -> 2377462.5 | M43: =M37 -> 2377462.5
C44: Total | D44: =SUM(D41:D43) -> 3.7244446e+09 | E44: =SUM(E41:E43) -> 1.8342877e+09 | F44: =SUM(F41:F43) -> 1.8901569e+09 | J44: Total | K44: =SUM(K41:K43) -> 4.4197041e+09 | L44: =SUM(L41:L43) -> 2.12469e+09 | M44: =SUM(M41:M43) -> 2.2950141e+09
B47: Precent Retained | C47: Entity 1 | D47: Entity 2 | E47: Entity 3 | F47: Total | I47: =B47 -> Precent Retained | J47: =C47 -> Entity 1 | K47: =D47 -> Entity 2 | L47: =E47 -> Entity 3 | M47: =F47 -> Total
B48: 0.2 | C48: =B48*$F$17 -> 11173836 | D48: =B48*$F$28 -> 3.6666667e+08 | E48: =B48*$F$37 -> 190871.25 | F48: =F$44*B48 -> 3.7803137e+08 | I48: =B48 -> 0.2 | J48: =I48*$M$17 -> 34064836 | K48: =I48*$M$28 -> 424462500 | L48: =I48*$M$37 -> 475492.5 | M48: =M$44*I48 -> 4.5900283e+08
B49: =B48-0.01 -> 0.19 | C49: =B49*$F$17 -> 10615144 | D49: =B49*$F$28 -> 3.4833333e+08 | E49: =B49*$F$37 -> 181327.69 | F49: =F$44*B49 -> 3.5912981e+08 | I49: =B49 -> 0.19 | J49: =I49*$M$17 -> 32361594 | K49: =I49*$M$28 -> 403239375 | L49: =I49*$M$37 -> 451717.88 | M49: =M$44*I49 -> 4.3605269e+08
B50: =B49-0.01 -> 0.18 | C50: =B50*$F$17 -> 10056452 | D50: =B50*$F$28 -> 3.3e+08 | E50: =B50*$F$37 -> 171784.12 | F50: =F$44*B50 -> 3.4022824e+08 | I50: =B50 -> 0.18 | J50: =I50*$M$17 -> 30658352 | K50: =I50*$M$28 -> 382016250 | L50: =I50*$M$37 -> 427943.25 | M50: =M$44*I50 -> 4.1310255e+08
B51: =B50-0.01 -> 0.17 | C51: =B51*$F$17 -> 9497760.6 | D51: =B51*$F$28 -> 3.1166667e+08 | E51: =B51*$F$37 -> 162240.56 | F51: =F$44*B51 -> 3.2132667e+08 | I51: =B51 -> 0.17 | J51: =I51*$M$17 -> 28955110 | K51: =I51*$M$28 -> 360793125 | L51: =I51*$M$37 -> 404168.62 | M51: =M$44*I51 -> 3.901524e+08
B52: =B51-0.01 -> 0.16 | C52: =B52*$F$17 -> 8939068.8 | D52: =B52*$F$28 -> 2.9333333e+08 | E52: =B52*$F$37 -> 152697 | F52: =F$44*B52 -> 3.024251e+08 | I52: =B52 -> 0.16 | J52: =I52*$M$17 -> 27251869 | K52: =I52*$M$28 -> 339570000 | L52: =I52*$M$37 -> 380394 | M52: =M$44*I52 -> 3.6720226e+08
B53: =B52-0.01 -> 0.15 | C53: =B53*$F$17 -> 8380377 | D53: =B53*$F$28 -> 2.75e+08 | E53: =B53*$F$37 -> 143153.44 | F53: =F$44*B53 -> 2.8352353e+08 | I53: =B53 -> 0.15 | J53: =I53*$M$17 -> 25548627 | K53: =I53*$M$28 -> 318346875 | L53: =I53*$M$37 -> 356619.38 | M53: =M$44*I53 -> 3.4425212e+08
B54: =B53-0.01 -> 0.14 | C54: =B54*$F$17 -> 7821685.2 | D54: =B54*$F$28 -> 2.5666667e+08 | E54: =B54*$F$37 -> 133609.88 | F54: =F$44*B54 -> 2.6462196e+08 | I54: =B54 -> 0.14 | J54: =I54*$M$17 -> 23845385 | K54: =I54*$M$28 -> 297123750 | L54: =I54*$M$37 -> 332844.75 | M54: =M$44*I54 -> 3.2130198e+08
B55: =B54-0.01 -> 0.13 | C55: =B55*$F$17 -> 7262993.4 | D55: =B55*$F$28 -> 2.3833333e+08 | E55: =B55*$F$37 -> 124066.31 | F55: =F$44*B55 -> 2.4572039e+08 | I55: =B55 -> 0.13 | J55: =I55*$M$17 -> 22142143 | K55: =I55*$M$28 -> 275900625 | L55: =I55*$M$37 -> 309070.12 | M55: =M$44*I55 -> 2.9835184e+08
B56: =B55-0.01 -> 0.12 | C56: =B56*$F$17 -> 6704301.6 | D56: =B56*$F$28 -> 2.2e+08 | E56: =B56*$F$37 -> 114522.75 | F56: =F$44*B56 -> 2.2681882e+08 | I56: =B56 -> 0.12 | J56: =I56*$M$17 -> 20438901 | K56: =I56*$M$28 -> 254677500 | L56: =I56*$M$37 -> 285295.5 | M56: =M$44*I56 -> 2.754017e+08
B57: =B56-0.01 -> 0.11 | C57: =B57*$F$17 -> 6145609.8 | D57: =B57*$F$28 -> 2.0166667e+08 | E57: =B57*$F$37 -> 104979.19 | F57: =F$44*B57 -> 2.0791726e+08 | I57: =B57 -> 0.11 | J57: =I57*$M$17 -> 18735660 | K57: =I57*$M$28 -> 233454375 | L57: =I57*$M$37 -> 261520.88 | M57: =M$44*I57 -> 2.5245156e+08
B58: =B57-0.01 -> 0.1 | C58: =B58*$F$17 -> 5586918 | D58: =B58*$F$28 -> 1.8333333e+08 | E58: =B58*$F$37 -> 95435.625 | F58: =F$44*B58 -> 1.8901569e+08 | I58: =B58 -> 0.1 | J58: =I58*$M$17 -> 17032418 | K58: =I58*$M$28 -> 212231250 | L58: =I58*$M$37 -> 237746.25 | M58: =M$44*I58 -> 2.2950141e+08
B59: =B58-0.01 -> 0.09 | C59: =B59*$F$17 -> 5028226.2 | D59: =B59*$F$28 -> 1.65e+08 | E59: =B59*$F$37 -> 85892.062 | F59: =F$44*B59 -> 1.7011412e+08 | I59: =B59 -> 0.09 | J59: =I59*$M$17 -> 15329176 | K59: =I59*$M$28 -> 191008125 | L59: =I59*$M$37 -> 213971.62 | M59: =M$44*I59 -> 2.0655127e+08
B60: =B59-0.01 -> 0.08 | C60: =B60*$F$17 -> 4469534.4 | D60: =B60*$F$28 -> 1.4666667e+08 | E60: =B60*$F$37 -> 76348.5 | F60: =F$44*B60 -> 1.5121255e+08 | I60: =B60 -> 0.08 | J60: =I60*$M$17 -> 13625934 | K60: =I60*$M$28 -> 169785000 | L60: =I60*$M$37 -> 190197 | M60: =M$44*I60 -> 1.8360113e+08
... B67: =B66-0.01 -> 0.01 | C67: =B67*$F$17 -> 558691.8 | D67: =B67*$F$28 -> 18333333 | E67: =B67*$F$37 -> 9543.5625 | F67: =F$44*B67 -> 18901569 | I67: =B67 -> 0.01 | J67: =I67*$M$17 -> 1703241.8 | K67: =I67*$M$28 -> 21223125 | L67: =I67*$M$37 -> 23774.625 | M67: =M$44*I67 -> 22950141
B68: =B67/2 -> 0.005 | C68: =B68*$F$17 -> 279345.9 | D68: =B68*$F$28 -> 9166666.7 | E68: =B68*$F$37 -> 4771.7812 | F68: =F$44*B68 -> 9450784.3 | I68: =B68 -> 0.005 | J68: =I68*$M$17 -> 851620.89 | K68: =I68*$M$28 -> 10611562 | L68: =I68*$M$37 -> 11887.312 | M68: =M$44*I68 -> 11475071
B70: Growth Amount (From 0) | C70: 1 | D70: 1 | E70: 1 | F70: 1 | I70: Growth Amount (FromYear 4) | J70: =(J68-C68)/C68 -> 2.048625 | K70: =(K68-D68)/D68 -> 0.157625 | L70: =(L68-E68)/E68 -> 1.4911688 | M70: =(M68-F68)/F68 -> 0.21419242

Sheet Customer Growth
A1: Entity 1 Services Subscribers | O1: Operational | P1: Estimated Intra-Year Customer-Base Growth
A2: Entity | B2: 39479 | C2: =B2+31 -> 39510 | D2: =C2+31 -> 39541 | E2: =D2+31 -> 39572 | F2: =E2+31 -> 39603 | G2: =F2+31 -> 39634 | H2: =G2+31 -> 39665 | I2: =H2+31 -> 39696 | J2: =I2+31 -> 39727 | ... M2: =L2+31 -> 39820 | N2: Total Subs | O2: Months | P2: Percentage of Total New Customer Growth | Q2: 100 | AC2: X | AD2: Total | AE2: Month | AF2: Percentage
A3: =Inputs!B30 -> Brand 1 | B3: =$AE$28*Inputs!$D30 -> 0 | C3: =$AE$29*Inputs!$D30 -> 197.36842 | D3: =$AE$30*Inputs!$D30 -> 197.36842 | E3: =$AE$31*Inputs!$D30 -> 394.73684 | F3: =$AE$32*Inputs!$D30 -> 394.73684 | G3: =$AE$33*Inputs!$D30 -> 592.10526 | H3: =$AE$34*Inputs!$D30 -> 789.47368 | I3: =$AE$35*Inputs!$D30 -> 1184.2105 | J3: =$AE$36*Inputs!$D30 -> 1578.9474 | K3: =$AE$37*Inputs!$D30 -> 2368.4211 | L3: =$AE$38*Inputs!$D30 -> 3355.2632 | M3: =$AE$39*Inputs!$D30 -> 3947.3684 | N3: =SUM(B3:M3) -> 15000 | O3: =COUNTA(B3:M3) -> 12 | Q3: =Q2-5 -> 95 | AC3: X | AD3: Revenue | AE3: 1 | AF3: ='Customer Growth'!AE28 -> 0
A4: =Inputs!B31 -> Brand 2 | B4: =$AE$28*Inputs!$D31 -> 0 | C4: =$AE$29*Inputs!$D31 -> 131.57895 | D4: =$AE$30*Inputs!$D31 -> 131.57895 | E4: =$AE$31*Inputs!$D31 -> 263.15789 | F4: =$AE$32*Inputs!$D31 -> 263.15789 | G4: =$AE$33*Inputs!$D31 -> 394.73684 | H4: =$AE$34*Inputs!$D31 -> 526.31579 | I4: =$AE$35*Inputs!$D31 -> 789.47368 | J4: =$AE$36*Inputs!$D31 -> 1052.6316 | K4: =$AE$37*Inputs!$D31 -> 1578.9474 | L4: =$AE$38*Inputs!$D31 -> 2236.8421 | M4: =$AE$39*Inputs!$D31 -> 2631.5789 | N4: =SUM(B4:M4) -> 10000 | O4: =COUNTA(B4:M4) -> 12 | Q4: =Q3-5 -> 90 | AC4: X | AD4: Blocks | AE4: 2 | AF4: ='Customer Growth'!AE29 -> 0.013157895
A5: =Inputs!B32 -> Brand 3 | B5: =$AE$28*Inputs!$D32 -> 0 | C5: =$AE$29*Inputs!$D32 -> 65.789474 | D5: =$AE$30*Inputs!$D32 -> 65.789474 | E5: =$AE$31*Inputs!$D32 -> 131.57895 | F5: =$AE$32*Inputs!$D32 -> 131.57895 | G5: =$AE$33*Inputs!$D32 -> 197.36842 | H5: =$AE$34*Inputs!$D32 -> 263.15789 | I5: =$AE$35*Inputs!$D32 -> 394.73684 | J5: =$AE$36*Inputs!$D32 -> 526.31579 | K5: =$AE$37*Inputs!$D32 -> 789.47368 | L5: =$AE$38*Inputs!$D32 -> 1118.4211 | M5: =$AE$39*Inputs!$D32 -> 1315.7895 | N5: =SUM(B5:M5) -> 5000 | O5: =COUNTA(B5:M5) -> 12 | Q5: =Q4-5 -> 85 | AB5: X | AC5: X | AD5: =COUNTA('Customer Growth'!R2:AC21) -> 76 | AE5: 3 | AF5: ='Customer Growth'!AE30 -> 0.013157895
A6: =Inputs!B33 -> Brand 4 | B6: =$AE$28*Inputs!$D33 -> 0 | C6: =$AE$29*Inputs!$D33 -> 65.789474 | D6: =$AE$30*Inputs!$D33 -> 65.789474 | E6: =$AE$31*Inputs!$D33 -> 131.57895 | F6: =$AE$32*Inputs!$D33 -> 131.57895 | G6: =$AE$33*Inputs!$D33 -> 197.36842 | H6: =$AE$34*Inputs!$D33 -> 263.15789 | I6: =$AE$35*Inputs!$D33 -> 394.73684 | J6: =$AE$36*Inputs!$D33 -> 526.31579 | K6: =$AE$37*Inputs!$D33 -> 789.47368 | L6: =$AE$38*Inputs!$D33 -> 1118.4211 | M6: =$AE$39*Inputs!$D33 -> 1315.7895 | N6: =SUM(B6:M6) -> 5000 | O6: =COUNTA(B6:M6) -> 12 | Q6: =Q5-5 -> 80 | AB6: X | AC6: X | AD6: Possible | AE6: 4 | AF6: ='Customer Growth'!AE31 -> 0.026315789
A7: =Inputs!B34 -> Brand 5 | B7: =$AE$28*Inputs!$D34 -> 0 | C7: =$AE$29*Inputs!$D34 -> 65.789474 | D7: =$AE$30*Inputs!$D34 -> 65.789474 | E7: =$AE$31*Inputs!$D34 -> 131.57895 | F7: =$AE$32*Inputs!$D34 -> 131.57895 | G7: =$AE$33*Inputs!$D34 -> 197.36842 | H7: =$AE$34*Inputs!$D34 -> 263.15789 | I7: =$AE$35*Inputs!$D34 -> 394.73684 | J7: =$AE$36*Inputs!$D34 -> 526.31579 | K7: =$AE$37*Inputs!$D34 -> 789.47368 | L7: =$AE$38*Inputs!$D34 -> 1118.4211 | M7: =$AE$39*Inputs!$D34 -> 1315.7895 | N7: =SUM(B7:M7) -> 5000 | O7: =COUNTA(B7:M7) -> 12 | Q7: =Q6-5 -> 75 | AB7: X | AC7: X | AD7: Revenue | AE7: 5 | AF7: ='Customer Growth'!AE32 -> 0.026315789
A8: =Inputs!B35 -> Brand 6 | B8: =$AE$28*Inputs!$D35 -> 0 | C8: =$AE$29*Inputs!$D35 -> 65.789474 | D8: =$AE$30*Inputs!$D35 -> 65.789474 | E8: =$AE$31*Inputs!$D35 -> 131.57895 | F8: =$AE$32*Inputs!$D35 -> 131.57895 | G8: =$AE$33*Inputs!$D35 -> 197.36842 | H8: =$AE$34*Inputs!$D35 -> 263.15789 | I8: =$AE$35*Inputs!$D35 -> 394.73684 | J8: =$AE$36*Inputs!$D35 -> 526.31579 | K8: =$AE$37*Inputs!$D35 -> 789.47368 | L8: =$AE$38*Inputs!$D35 -> 1118.4211 | M8: =$AE$39*Inputs!$D35 -> 1315.7895 | N8: =SUM(B8:M8) -> 5000 | O8: =COUNTA(B8:M8) -> 12 | Q8: =Q7-5 -> 70 | AB8: X | AC8: X | AD8: Blocks | AE8: 6 | AF8: ='Customer Growth'!AE33 -> 0.039473684
A9: =Inputs!B36 -> Brand 7 | B9: =$AE$28*Inputs!$D36 -> 0 | C9: =$AE$29*Inputs!$D36 -> 11.436579 | D9: =$AE$30*Inputs!$D36 -> 11.436579 | E9: =$AE$31*Inputs!$D36 -> 22.873158 | F9: =$AE$32*Inputs!$D36 -> 22.873158 | G9: =$AE$33*Inputs!$D36 -> 34.309737 | H9: =$AE$34*Inputs!$D36 -> 45.746316 | I9: =$AE$35*Inputs!$D36 -> 68.619474 | J9: =$AE$36*Inputs!$D36 -> 91.492632 | K9: =$AE$37*Inputs!$D36 -> 137.23895 | L9: =$AE$38*Inputs!$D36 -> 194.42184 | M9: =$AE$39*Inputs!$D36 -> 228.73158 | N9: =SUM(B9:M9) -> 869.18 | O9: =COUNTA(B9:M9) -> 12 | Q9: =Q8-5 -> 65 | AB9: X | AC9: X | AD9: =20*12 -> 240 | AE9: 7 | AF9: ='Customer Growth'!AE34 -> 0.052631579
A10: =Inputs!B37 -> Brand 8 | B10: =$AE$28*Inputs!$D37 -> 0 | C10: =$AE$29*Inputs!$D37 -> 65.789474 | D10: =$AE$30*Inputs!$D37 -> 65.789474 | E10: =$AE$31*Inputs!$D37 -> 131.57895 | F10: =$AE$32*Inputs!$D37 -> 131.57895 | G10: =$AE$33*Inputs!$D37 -> 197.36842 | H10: =$AE$34*Inputs!$D37 -> 263.15789 | I10: =$AE$35*Inputs!$D37 -> 394.73684 | J10: =$AE$36*Inputs!$D37 -> 526.31579 | K10: =$AE$37*Inputs!$D37 -> 789.47368 | L10: =$AE$38*Inputs!$D37 -> 1118.4211 | M10: =$AE$39*Inputs!$D37 -> 1315.7895 | N10: =SUM(B10:M10) -> 5000 | O10: =COUNTA(B10:M10) -> 12 | Q10: =Q9-5 -> 60 | AA10: X | AB10: X | AC10: X | AD10: Potential | AE10: 8 | AF10: ='Customer Growth'!AE35 -> 0.078947368
A11: =Inputs!B38 -> Brand 9 | B11: =$AE$28*Inputs!$D38 -> 0 | C11: =$AE$29*Inputs!$D38 -> 65.789474 | D11: =$AE$30*Inputs!$D38 -> 65.789474 | E11: =$AE$31*Inputs!$D38 -> 131.57895 | F11: =$AE$32*Inputs!$D38 -> 131.57895 | G11: =$AE$33*Inputs!$D38 -> 197.36842 | H11: =$AE$34*Inputs!$D38 -> 263.15789 | I11: =$AE$35*Inputs!$D38 -> 394.73684 | J11: =$AE$36*Inputs!$D38 -> 526.31579 | K11: =$AE$37*Inputs!$D38 -> 789.47368 | L11: =$AE$38*Inputs!$D38 -> 1118.4211 | M11: =$AE$39*Inputs!$D38 -> 1315.7895 | N11: =SUM(B11:M11) -> 5000 | O11: =COUNTA(B11:M11) -> 12 | Q11: =Q10-5 -> 55 | AA11: X | AB11: X | AC11: X | AD11: Revenue | AE11: 9 | AF11: ='Customer Growth'!AE36 -> 0.10526316
A12: Total | B12: =SUM(B3:B11) -> 0 | C12: =SUM(C3:C11) -> 735.12079 | D12: =SUM(D3:D11) -> 735.12079 | E12: =SUM(E3:E11) -> 1470.2416 | F12: =SUM(F3:F11) -> 1470.2416 | G12: =SUM(G3:G11) -> 2205.3624 | H12: =SUM(H3:H11) -> 2940.4832 | I12: =SUM(I3:I11) -> 4410.7247 | ... M12: =SUM(M3:M11) -> 14702.416 | N12: Average | O12: =AVERAGE(O3:O11) -> 12 | Q12: =Q11-5 -> 50 | AA12: X | AB12: X | AC12: X | AD12: Percentage | AE12: 10 | AF12: ='Customer Growth'!AE37 -> 0.15789474
Q13: =Q12-5 -> 45 | AA13: X | AB13: X | AC13: X | AD13: =AD5/AD9 -> 0.31666667 | AE13: 11 | AF13: ='Customer Growth'!AE38 -> 0.22368421
A14: Revenue | Q14: =Q13-5 -> 40 | Z14: X | AA14: X | AB14: X | AC14: X | AE14: 12 | AF14: ='Customer Growth'!AE39 -> 0.26315789
A15: Entity | B15: 39479 | C15: =B15+31 -> 39510 | D15: =C15+31 -> 39541 | E15: =D15+31 -> 39572 | F15: =E15+31 -> 39603 | G15: =F15+31 -> 39634 | H15: =G15+31 -> 39665 | I15: =H15+31 -> 39696 | J15: =I15+31 -> 39727 | ... M15: =L15+31 -> 39820 | N15: Total Rev | Q15: =Q14-5 -> 35 | Z15: X | AA15: X | AB15: X | AC15: X
A16: =A3 -> Brand 1 | M16: =$AD52*Inputs!$D$30 -> 0 | N16: =SUM(B16:M16) -> 0 | Q16: =Q15-5 -> 30 | Y16: X | Z16: X | AA16: X | AB16: X | AC16: X
A17: =A4 -> Brand 2 | N17: =SUM(B17:M17) -> 0 | Q17: =Q16-5 -> 25 | Y17: X | Z17: X | AA17: X | AB17: X | AC17: X
A18: =A5 -> Brand 3 | N18: =SUM(B18:M18) -> 0 | Q18: =Q17-5 -> 20 | X18: X | Y18: X | Z18: X | AA18: X | AB18: X | AC18: X
A19: =A6 -> Brand 4 | N19: =SUM(B19:M19) -> 0 | Q19: =Q18-5 -> 15 | W19: X | X19: X | Y19: X | Z19: X | AA19: X | AB19: X | AC19: X
A20: =A7 -> Brand 5 | N20: =SUM(B20:M20) -> 0 | Q20: =Q19-5 -> 10 | U20: X | V20: X | W20: X | X20: X | Y20: X | Z20: X | AA20: X | AB20: X | AC20: X
A21: =A8 -> Brand 6 | N21: =SUM(B21:M21) -> 0 | Q21: =Q20-5 -> 5 | S21: X | T21: X | U21: X | V21: X | W21: X | X21: X | Y21: X | Z21: X | AA21: X | AB21: X | AC21: X
A22: =A9 -> Brand 7 | N22: =SUM(B22:M22) -> 0 | Q22: Percentage | R22: =COUNTA(R2:R21)*5/100 -> 0 | S22: =COUNTA(S2:S21)*5/100 -> 0.05 | T22: =COUNTA(T2:T21)*5/100 -> 0.05 | U22: =COUNTA(U2:U21)*5/100 -> 0.1 | V22: =COUNTA(V2:V21)*5/100 -> 0.1 | W22: =COUNTA(W2:W21)*5/100 -> 0.15 | X22: =COUNTA(X2:X21)*5/100 -> 0.2 | Y22: =COUNTA(Y2:Y21)*5/100 -> 0.3 | ... AC22: =COUNTA(AC2:AC21)*5/100 -> 1
A23: =A10 -> Brand 8 | N23: =SUM(B23:M23) -> 0 | R23: 1 | S23: =R23+1 -> 2 | T23: =S23+1 -> 3 | U23: =T23+1 -> 4 | V23: =U23+1 -> 5 | W23: =V23+1 -> 6 | X23: =W23+1 -> 7 | Y23: =X23+1 -> 8 | Z23: =Y23+1 -> 9 | ... AC23: =AB23+1 -> 12
A24: =A11 -> Brand 9 | N24: =SUM(B24:M24) -> 0 | R24: Month Number
A25: Total | B25: =SUM(B16:B24) -> 0 | C25: =SUM(C16:C24) -> 0 | D25: =SUM(D16:D24) -> 0 | E25: =SUM(E16:E24) -> 0 | F25: =SUM(F16:F24) -> 0 | G25: =SUM(G16:G24) -> 0 | H25: =SUM(H16:H24) -> 0 | I25: =SUM(I16:I24) -> 0 | ... M25: =SUM(M16:M24) -> 0
Q26: Revenue Model | AD26: Revenue Blocks | AE26: Monthly Revenue % | AF26: Cumulative Revenue % | AG26: Subs
A27: Entity 2 Subscribers | O27: Operational | Q27: Month | R27: Equation | AG27: 100000
A28: Entity | B28: 39479 | C28: =B28+31 -> 39510 | D28: =C28+31 -> 39541 | E28: =D28+31 -> 39572 | F28: =E28+31 -> 39603 | G28: =F28+31 -> 39634 | H28: =G28+31 -> 39665 | I28: =H28+31 -> 39696 | J28: =I28+31 -> 39727 | ... M28: =L28+31 -> 39820 | N28: Total Subs | O28: Months | Q28: 1 | R28: ='Customer Growth'!R22*100&"% * Total Customers * Revenue per customer" -> 0% * Total Customers * Revenue per customer | AD28: =COUNTA('Customer Growth'!$R$2:$R$21) -> 0 | AE28: =AD28/COUNTA('Customer Growth'!$R$2:$AC$21) -> 0 | AF28: =AE28 -> 0 | AG28: =AF28*$AG$27 -> 0
A29: Product 1 | G29: =$AE$33*Inputs!$D149 -> 0.11842105 | H29: =$AE$34*Inputs!$D149 -> 0.15789474 | I29: =$AE$35*Inputs!$D149 -> 0.23684211 | J29: =$AE$36*Inputs!$D149 -> 0.31578947 | K29: =$AE$37*Inputs!$D149 -> 0.47368421 | L29: =$AE$38*Inputs!$D149 -> 0.67105263 | M29: =$AE$39*Inputs!$D149 -> 0.78947368 | N29: =SUM(B29:M29) -> 2.7631579 | O29: =COUNTA(B29:M29) -> 7 | Q29: =Q28+1 -> 2 | R29: ="("&'Customer Growth'!S$22*100&"% * Total Customers * Revenue per customer) + Month "&Q28 -> (5% * Total Customers * Revenue per customer) + Month 1 | AD29: =COUNTA('Customer Growth'!$S$2:$S$21) -> 1 | AE29: =AD29/COUNTA('Customer Growth'!$R$2:$AC$21) -> 0.013157895 | AF29: =AE29+AF28 -> 0.013157895 | AG29: =AF29*$AG$27 -> 1315.7895
A30: Product 2 | G30: =$AE$33*Inputs!$D150 -> 0.039473684 | H30: =$AE$34*Inputs!$D150 -> 0.052631579 | I30: =$AE$35*Inputs!$D150 -> 0.078947368 | J30: =$AE$36*Inputs!$D150 -> 0.10526316 | K30: =$AE$37*Inputs!$D150 -> 0.15789474 | L30: =$AE$38*Inputs!$D150 -> 0.22368421 | M30: =$AE$39*Inputs!$D150 -> 0.26315789 | N30: =SUM(B30:M30) -> 0.92105263 | O30: =COUNTA(B30:M30) -> 7 | Q30: =Q29+1 -> 3 | R30: ="("&'Customer Growth'!T$22*100&"% * Total Customers * Revenue per customer) + Month "&Q29 -> (5% * Total Customers * Revenue per customer) + Month 2 | AD30: =COUNTA('Customer Growth'!$T$2:$T$21) -> 1 | AE30: =AD30/COUNTA('Customer Growth'!$R$2:$AC$21) -> 0.013157895 | AF30: =AE30+AF29 -> 0.026315789 | AG30: =AF30*$AG$27 -> 2631.5789
A31: Product 3 | G31: =$AE$33*Inputs!$D151 -> 0.0098684211 | H31: =$AE$34*Inputs!$D151 -> 0.013157895 | I31: =$AE$35*Inputs!$D151 -> 0.019736842 | J31: =$AE$36*Inputs!$D151 -> 0.026315789 | K31: =$AE$37*Inputs!$D151 -> 0.039473684 | L31: =$AE$38*Inputs!$D151 -> 0.055921053 | M31: =$AE$39*Inputs!$D151 -> 0.065789474 | N31: =SUM(B31:M31) -> 0.23026316 | O31: =COUNTA(B31:M31) -> 7 | Q31: =Q30+1 -> 4 | R31: ="("&'Customer Growth'!U$22*100&"% * Total Customers * Revenue per customer) + Month "&Q30 -> (10% * Total Customers * Revenue per customer) + Month 3 | AD31: =COUNTA('Customer Growth'!$U$2:$U$21) -> 2 | AE31: =AD31/COUNTA('Customer Growth'!$R$2:$AC$21) -> 0.026315789 | AF31: =AE31+AF30 -> 0.052631579 | AG31: =AF31*$AG$27 -> 5263.1579
A32: Product 4 | G32: =$AE$33*Inputs!$D152 -> 1.1838158 | H32: =$AE$34*Inputs!$D152 -> 1.5784211 | I32: =$AE$35*Inputs!$D152 -> 2.3676316 | J32: =$AE$36*Inputs!$D152 -> 3.1568421 | K32: =$AE$37*Inputs!$D152 -> 4.7352632 | L32: =$AE$38*Inputs!$D152 -> 6.7082895 | M32: =$AE$39*Inputs!$D152 -> 7.8921053 | N32: =SUM(B32:M32) -> 27.622368 | O32: =COUNTA(B32:M32) -> 7 | Q32: =Q31+1 -> 5 | R32: ="("&'Customer Growth'!V$22*100&"% * Total Customers * Revenue per customer) + Month "&Q31 -> (10% * Total Customers * Revenue per customer) + Month 4 | AD32: =COUNTA('Customer Growth'!$V$2:$V$21) -> 2 | AE32: =AD32/COUNTA('Customer Growth'!$R$2:$AC$21) -> 0.026315789 | AF32: =AE32+AF31 -> 0.078947368 | AG32: =AF32*$AG$27 -> 7894.7368
A33: Total | B33: =SUM(B29:B32) -> 0 | C33: =SUM(C29:C32) -> 0 | D33: =SUM(D29:D32) -> 0 | E33: =SUM(E29:E32) -> 0 | F33: =SUM(F29:F32) -> 0 | G33: =SUM(G29:G32) -> 1.3515789 | H33: =SUM(H29:H32) -> 1.8021053 | I33: =SUM(I29:I32) -> 2.7031579 | ... M33: =SUM(M29:M32) -> 9.0105263 | N33: Average | O33: =AVERAGE(O29:O32) -> 7 | Q33: =Q32+1 -> 6 | R33: ="("&'Customer Growth'!W$22*100&"% * Total Customers * Revenue per customer) + Month "&Q32 -> (15% * Total Customers * Revenue per customer) + Month 5 | AD33: =COUNTA('Customer Growth'!$W$2:$W$21) -> 3 | AE33: =AD33/COUNTA('Customer Growth'!$R$2:$AC$21) -> 0.039473684 | AF33: =AE33+AF32 -> 0.11842105 | AG33: =AF33*$AG$27 -> 11842.105
Q34: =Q33+1 -> 7 | R34: ="("&'Customer Growth'!X$22*100&"% * Total Customers * Revenue per customer) + Month "&Q33 -> (20% * Total Customers * Revenue per customer) + Month 6 | AD34: =COUNTA('Customer Growth'!$X$2:$X$21) -> 4 | AE34: =AD34/COUNTA('Customer Growth'!$R$2:$AC$21) -> 0.052631579 | AF34: =AE34+AF33 -> 0.17105263 | AG34: =AF34*$AG$27 -> 17105.263
A35: Revenue | Q35: =Q34+1 -> 8 | R35: ="("&'Customer Growth'!Y$22*100&"% * Total Customers * Revenue per customer) + Month "&Q34 -> (30% * Total Customers * Revenue per customer) + Month 7 | AD35: =COUNTA('Customer Growth'!$Y$2:$Y$21) -> 6 | AE35: =AD35/COUNTA('Customer Growth'!$R$2:$AC$21) -> 0.078947368 | AF35: =AE35+AF34 -> 0.25 | AG35: =AF35*$AG$27 -> 25000
A36: Entity | B36: 39479 | C36: =B36+31 -> 39510 | D36: =C36+31 -> 39541 | E36: =D36+31 -> 39572 | F36: =E36+31 -> 39603 | G36: =F36+31 -> 39634 | H36: =G36+31 -> 39665 | I36: =H36+31 -> 39696 | J36: =I36+31 -> 39727 | ... M36: =L36+31 -> 39820 | N36: Total Rev | Q36: =Q35+1 -> 9 | R36: ="("&'Customer Growth'!Z$22*100&"% * Total Customers * Revenue per customer) + Month "&Q35 -> (40% * Total Customers * Revenue per customer) + Month 8 | AD36: =COUNTA('Customer Growth'!$Z$2:$Z$21) -> 8 | AE36: =AD36/COUNTA('Customer Growth'!$R$2:$AC$21) -> 0.10526316 | AF36: =AE36+AF35 -> 0.35526316 | AG36: =AF36*$AG$27 -> 35526.316
A37: =A29 -> Product 1 | M37: =$AD78*Inputs!$D$30 -> 0 | N37: =SUM(B37:M37) -> 0 | Q37: =Q36+1 -> 10 | R37: ="("&'Customer Growth'!AA$22*100&"% * Total Customers * Revenue per customer) + Month "&Q36 -> (60% * Total Customers * Revenue per customer) + Month 9 | AD37: =COUNTA('Customer Growth'!$AA$2:$AA$21) -> 12 | AE37: =AD37/COUNTA('Customer Growth'!$R$2:$AC$21) -> 0.15789474 | AF37: =AE37+AF36 -> 0.51315789 | AG37: =AF37*$AG$27 -> 51315.789
A38: =A30 -> Product 2 | N38: =SUM(B38:M38) -> 0 | Q38: =Q37+1 -> 11 | R38: ="("&'Customer Growth'!AB$22*100&"% * Total Customers * Revenue per customer) + Month "&Q37 -> (85% * Total Customers * Revenue per customer) + Month 10 | AD38: =COUNTA('Customer Growth'!$AB$2:$AB$21) -> 17 | AE38: =AD38/COUNTA('Customer Growth'!$R$2:$AC$21) -> 0.22368421 | AF38: =AE38+AF37 -> 0.73684211 | AG38: =AF38*$AG$27 -> 73684.211
A39: =A31 -> Product 3 | N39: =SUM(B39:M39) -> 0 | Q39: =Q38+1 -> 12 | R39: ="("&'Customer Growth'!AC$22*100&"% * Total Customers * Revenue per customer) + Month "&Q38 -> (100% * Total Customers * Revenue per customer) + Month 11 | AD39: =COUNTA('Customer Growth'!$AC$2:$AC$21) -> 20 | AE39: =AD39/COUNTA('Customer Growth'!$R$2:$AC$21) -> 0.26315789 | AF39: =AE39+AF38 -> 1 | AG39: =AF39*$AG$27 -> 100000
A40: =A32 -> Product 4 | N40: =SUM(B40:M40) -> 0
A41: Total | B41: =SUM(B37:B40) -> 0 | C41: =SUM(C37:C40) -> 0 | D41: =SUM(D37:D40) -> 0 | E41: =SUM(E37:E40) -> 0 | F41: =SUM(F37:F40) -> 0 | G41: =SUM(G37:G40) -> 0 | H41: =SUM(H37:H40) -> 0 | I41: =SUM(I37:I40) -> 0 | ... M41: =SUM(M37:M40) -> 0
P47: Estimated Intra-Year Customer-Base Growth
P48: Percentage of Total New Customer Growth | Q48: 100 | AC48: X
AC49: X
AC50: X
AC51: X
AC52: X
Q53: =Q48-5 -> 95 | AC53: X
AC54: X
AB55: X | AC55: X
AB56: X | AC56: X
AB57: X | AC57: X
Q58: =Q53-5 -> 90 | AB58: X | AC58: X
AB59: X | AC59: X
AB60: X | AC60: X
AB61: X | AC61: X
AB62: X | AC62: X
Q63: =Q58-5 -> 85 | AB63: X | AC63: X
AB64: X | AC64: X
AB65: X | AC65: X
AA66: X | AB66: X | AC66: X
AA67: X | AB67: X | AC67: X
Q68: =Q63-5 -> 80 | AA68: X | AB68: X | AC68: X
AA69: X | AB69: X | AC69: X
AA70: X | AB70: X | AC70: X
AA71: X | AB71: X | AC71: X
AA72: X | AB72: X | AC72: X
Q73: =Q68-5 -> 75 | AA73: X | AB73: X | AC73: X
AA74: X | AB74: X | AC74: X
AA75: X | AB75: X | AC75: X
AA76: X | AB76: X | AC76: X
AA77: X | AB77: X | AC77: X
Q78: =Q73-5 -> 70 | AA78: X | AB78: X | AC78: X
AA79: X | AB79: X | AC79: X
AA80: X | AB80: X | AC80: X
AA81: X | AB81: X | AC81: X
AA82: X | AB82: X | AC82: X
Q83: =Q78-5 -> 65 | AA83: X | AB83: X | AC83: X
AA84: X | AB84: X | AC84: X
AA85: X | AB85: X | AC85: X
AA86: X | AB86: X | AC86: X
Z87: X | AA87: X | AB87: X | AC87: X
Q88: =Q83-5 -> 60 | Z88: X | AA88: X | AB88: X | AC88: X
Z89: X | AA89: X | AB89: X | AC89: X
Z90: X | AA90: X | AB90: X | AC90: X
Z91: X | AA91: X | AB91: X | AC91: X
Z92: X | AA92: X | AB92: X | AC92: X
Q93: =Q88-5 -> 55 | Z93: X | AA93: X | AB93: X | AC93: X
Z94: X | AA94: X | AB94: X | AC94: X
Z95: X | AA95: X | AB95: X | AC95: X
Z96: X | AA96: X | AB96: X | AC96: X
Z97: X | AA97: X | AB97: X | AC97: X
Q98: =Q93-5 -> 50 | Z98: X | AA98: X | AB98: X | AC98: X
Z99: X | AA99: X | AB99: X | AC99: X
Z100: X | AA100: X | AB100: X | AC100: X
Y101: X | Z101: X | AA101: X | AB101: X | AC101: X
Y102: X | Z102: X | AA102: X | AB102: X | AC102: X
Q103: =Q98-5 -> 45 | Y103: X | Z103: X | AA103: X | AB103: X | AC103: X
Y104: X | Z104: X | AA104: X | AB104: X | AC104: X
Y105: X | Z105: X | AA105: X | AB105: X | AC105: X
...

Sheet Competitor Comparison
A1: Competitor Prices (per Product 1)
A2: (Plans as of September, 12, 2008) | F2: Entity 1 | G2: =Inputs!E3 -> 0.11296647 | H2: for Product 1
A3: ="Average Unweighted Retail Price (Product 1): $"&A49 -> Average Unweighted Retail Price (Product 1): $0.1403 | F3: Entity 1 Price Advantage | G3: =-G2+A49 -> 0.027333531 | H3: for Product 1
A4: Company 1 | C4: Company 6
A5: Product A | B5: 0.15 | C5: Product A | D5: 0.1 | G5: Rate | H5: Entity 2 Advantage
A6: Product B | B6: 0.1 | C6: Product B | D6: 0.25 | F6: Company 12 - Product 1 | G6: 24.99 | H6: -
A7: Product C | B7: 0.1 | C7: Product C | D7: =29.99/200 -> 0.14995 | F7: Company 12 - Product 2 | G7: 49.99 | H7: -
A8: Product D | B8: 0.1 | C8: Product D | D8: =39.99/300 -> 0.1333 | F8: Entity 2 - Product 2 | H8: =-G8+G6 -> 24.99
A9: Product E | B9: =29.99/200 -> 0.14995 | C9: Product E | D9: =49.99/400 -> 0.124975 | F9: Entity 2 - Product 1 | H9: =-G9+G6 -> 24.99
A10: Product F | B10: =39.99/400 -> 0.099975 | C10: Product F | D10: =69.99/650 -> 0.10767692 | F10: Entity 2 - Product 3 | H10: =G7-G10 -> 49.99
A11: Product G | B11: =69.99/700 -> 0.099985714 | C11: Company 7 | F11: Note: Prices do not include taxes
A12: Company 2 | C12: Product A | D12: 0.1
A13: Product A | B13: 0.1 | C13: Product B | D13: 0.05 | F13: Included with Monthly Service Charge
A14: Product B | B14: =30/400 -> 0.075 | C14: Product C | D14: 0.02 | F14: Product Service | G14: Company 12 | H14: Entity 2
A15: Product C | B15: =50/1000 -> 0.05 | C15: Product D | F15: Service Portion A | G15: Yes | H15: Yes
A16: Product D | B16: 0.1 | C16: Product E | F16: Service Portion B | G16: Yes | H16: Yes
A17: Product E | B17: 0.2 | C17: Product F | F17: Service Portion C | G17: Yes | H17: Yes
A18: Product F | C18: Company 8 | F18: Service Portion D | G18: Yes | H18: Yes
A19: Product G | C19: Product A | D19: 0.1 | F19: Service Portion E | G19: Yes | H19: Yes
A20: Product H | C20: Product B | D20: =100/1000 -> 0.1 | F20: Service Portion F | G20: Yes | H20: Yes
A21: Product I | C21: Product C | D21: =50/400 -> 0.125 | F21: Service Portion G | G21: Yes | H21: Yes
A22: Product J | C22: Product D | D22: =25/130 -> 0.19230769 | F22: Service Portion H | G22: Yes | H22: Yes
A23: Product K | C23: Product E | D23: =10/30 -> 0.33333333 | F23: Service Portion I | G23: Yes | H23: Yes
A24: Company 3 | C24: Product F | F24: Service Portion J | G24: Yes | H24: Yes
